Workbook

Sheet Резюме
B2: Резюме проекта
B4: Суть проекта:
B5: Проектом предусматривается создание, внедрение и ввод в промышленную эксплуатацию нейросетевого программного модуля, встраиваемого в корпоративную HRM-систему МКПАО «Яндекс». Назначение модуля – автоматизированный анализ компетенций сотрудников, выявление дефицита навыков, прогнозирование вероятных карьерных переходов и формирование персонализированных рекомендаций по обучению и развитию.
B6: Инициатор проекта:
B7: Цель проекта:
B8: Создание нейросетевого модуля для повышения эффективности управления кадрами компании "Яндекс"
B10: Основные характеристики проекта
B11: Наименование | C11: Значение
B12: Суть проекта | C12: Создание нейросетевого модуля в корпоративную HRM-систему "Яндекса", содержащего
B13: Срок реализации проекта | C13: 10 лет, 1 год разработка, 9 лет - реализация
B14: Количество работников | C14: 18 человек
B15: Количество сотрудников "Яндекс" | C15: 29000
B16: Обучение ориентировано на (численность обучающихся), чел. | C16: 5200
B17: Цель проекта | C17: Создание не фрагментарного, а единого управляющего модуля для обучения и развития персонала
B18: Предмет разработки | C18: Нейросетевой HRM-модуль
B19: Первый блок разработки | C19: Ядро HRM модуля
B20: Второй блок | C20: Модуль анализа компетенций
B21: Третий блок | C21: Модуль карьерных переходов
B22: Четвертый блок | C22: Рекомендательный модуль обучения
B23: Пятый блок | C23: Витрина данных, ETL и единая модель компетенций
B24: Шестой блок | C24: Интерфейсы и дашборды
B25: Седьмой блок | C25: Контур интеграций. Обеспечить обмен данными с HRM, LMS, BI, корпоративными API, а также формирование журналов событий, логирования и мониторинга.
B26: Восьмой блок | C26: Контур ИБ и защиты персональных данных
B28: Потребность в финансировании проекта
B29: Источник финансирования | C29: Сумма, руб.
B30: Всего вложений | C30: 276961520
B31: в т. ч. По источникам финансирования
B32: Собственные средства | C32: 276961520
B33: Заемные средства | C33: 0

Sheet Исходные данные
C2: Исходные данные:
C4: Система налогообложения: | D4: упрощенная система (доходы)
C5: Организационная форма бизнеса: | D5: ООО
C7: Временные показатели: | D7: Значение
C8: год | D8: № год
C9: месяц | D9: № мес.
F10: 1 год | R10: 2 год | AD10: 3 год | AP10: 4 год | BB10: 5 год | BN10: 6 год | BZ10: 7 год | CL10: 8 год | CX10: 9 год | DJ10: 10 год
C11: Наименование | D11: Ед. из. (мес. / руб.) | E11: Сумма | F11: 1 | G11: 2 | H11: 3 | I11: 4 | J11: 5 | K11: 6 | L11: 7 | M11: 8 | N11: 9 | O11: 10 | P11: 11 | Q11: 12 | R11: 1 | S11: 2 | T11: 3 | U11: 4 | V11: 5 | W11: 6 | X11: 7 | Y11: 8 | Z11: 9 | AA11: 10 | AB11: 11 | AC11: 12 | AD11: 1 | AE11: 2 | AF11: 3 | AG11: 4 | AH11: 5 | AI11: 6 | AJ11: 7 | AK11: 8 | AL11: 9 | AM11: 10 | AN11: 11 | AO11: 12 | AP11: 1 | AQ11: 2 | AR11: 3 | AS11: 4 | AT11: 5 | AU11: 6 | AV11: 7 | AW11: 8 | AX11: 9 | AY11: 10 | AZ11: 11 | BA11: 12 | BB11: 1 | BC11: 2 | BD11: 3 | BE11: 4 | BF11: 5 | BG11: 6 | BH11: 7 | BI11: 8 | BJ11: 9 | BK11: 10 | BL11: 11 | BM11: 12 | BN11: 1 | BO11: 2 | BP11: 3 | BQ11: 4 | BR11: 5 | BS11: 6 | BT11: 7 | BU11: 8 | BV11: 9 | BW11: 10 | BX11: 11 | BY11: 12 | BZ11: 1 | CA11: 2 | CB11: 3 | CC11: 4 | CD11: 5 | CE11: 6 | CF11: 7 | CG11: 8 | CH11: 9 | CI11: 10 | CJ11: 11 | CK11: 12 | CL11: 1 | CM11: 2 | CN11: 3 | CO11: 4 | CP11: 5 | CQ11: 6 | CR11: 7 | CS11: 8 | CT11: 9 | CU11: 10 | CV11: 11 | CW11: 12 | CX11: 1 | CY11: 2 | CZ11: 3 | DA11: 4 | DB11: 5 | DC11: 6 | DD11: 7 | DE11: 8 | DF11: 9 | DG11: 10 | DH11: 11 | DI11: 12 | DJ11: 1 | DK11: 2 | DL11: 3 | DM11: 4 | DN11: 5 | DO11: 6 | DP11: 7 | DQ11: 8 | DR11: 9 | DS11: 10 | DT11: 11 | DU11: 12
F12: 1 | G12: 2 | H12: 3 | I12: 4 | J12: 5 | K12: 6 | L12: 7 | M12: 8 | N12: 9 | O12: 10 | P12: 11 | Q12: 12 | R12: 13 | S12: 14 | T12: 15 | U12: 16 | V12: 17 | W12: 18 | X12: 19 | Y12: 20 | Z12: 21 | AA12: 22 | AB12: 23 | AC12: 24 | AD12: 25 | AE12: 26 | AF12: 27 | AG12: 28 | AH12: 29 | AI12: 30 | AJ12: 31 | AK12: 32 | AL12: 33 | AM12: 34 | AN12: 35 | AO12: 36 | AP12: 37 | AQ12: =AP12+1 -> 38 | AR12: =AQ12+1 -> 39 | AS12: =AR12+1 -> 40 | AT12: =AS12+1 -> 41 | AU12: =AT12+1 -> 42 | AV12: =AU12+1 -> 43 | AW12: =AV12+1 -> 44 | AX12: =AW12+1 -> 45 | ... DU12: =DT12+1 -> 120
C13: 1. Наименование вида налога и сбора
C14: ОСНО налог на прибыль | D14: % | E14: 0.05 | F14: 0.05 | G14: 0.05 | H14: 0.05 | I14: 0.05 | J14: 0.05 | K14: 0.05 | L14: 0.05 | M14: 0.05 | N14: 0.05 | O14: 0.05 | P14: 0.05 | Q14: 0.05 | R14: 0.05 | S14: 0.05 | T14: 0.05 | U14: 0.05 | V14: 0.05 | W14: 0.05 | X14: 0.05 | Y14: 0.05 | Z14: 0.05 | AA14: 0.05 | AB14: 0.05 | AC14: 0.05 | AD14: 0.05 | AE14: 0.05 | AF14: 0.05 | AG14: 0.05 | AH14: 0.05 | AI14: 0.05 | AJ14: 0.05 | AK14: 0.05 | AL14: 0.05 | AM14: 0.05 | AN14: 0.05 | AO14: 0.05 | AP14: 0.05 | AQ14: 0.05 | AR14: 0.05 | AS14: 0.05 | AT14: 0.05 | AU14: 0.05 | AV14: 0.05 | AW14: 0.05 | AX14: 0.05 | AY14: 0.05 | AZ14: 0.05 | BA14: 0.05 | BB14: 0.05 | BC14: 0.05 | BD14: 0.05 | BE14: 0.05 | BF14: 0.05 | BG14: 0.05 | BH14: 0.05 | BI14: 0.05 | BJ14: 0.05 | BK14: 0.05 | BL14: 0.05 | BM14: 0.05 | BN14: 0.05 | BO14: 0.05 | BP14: 0.05 | BQ14: 0.05 | BR14: 0.05 | BS14: 0.05 | BT14: 0.05 | BU14: 0.05 | BV14: 0.05 | BW14: 0.05 | BX14: 0.05 | BY14: 0.05 | BZ14: 0.05 | CA14: 0.05 | CB14: 0.05 | CC14: 0.05 | CD14: 0.05 | CE14: 0.05 | CF14: 0.05 | CG14: 0.05 | CH14: 0.05 | CI14: 0.05 | CJ14: 0.05 | CK14: 0.05 | CL14: 0.05 | CM14: 0.05 | CN14: 0.05 | CO14: 0.05 | CP14: 0.05 | CQ14: 0.05 | CR14: 0.05 | CS14: 0.05 | CT14: 0.05 | CU14: 0.05 | CV14: 0.05 | CW14: 0.05 | CX14: 0.05 | CY14: 0.05 | CZ14: 0.05 | DA14: 0.05 | DB14: 0.05 | DC14: 0.05 | DD14: 0.05 | DE14: 0.05 | DF14: 0.05 | DG14: 0.05 | DH14: 0.05 | DI14: 0.05 | DJ14: 0.05 | DK14: 0.05 | DL14: 0.05 | DM14: 0.05 | DN14: 0.05 | DO14: 0.05 | DP14: 0.05 | DQ14: 0.05 | DR14: 0.05 | DS14: 0.05 | DT14: 0.05 | DU14: 0.05
C15: Налог на имущество | D15: % | E15: 0.025 | F15: 0.00208 | G15: 0.00208 | H15: 0.00208 | I15: 0.00208 | J15: 0.00208 | K15: 0.00208 | L15: 0.00208 | M15: 0.00208 | N15: 0.00208 | O15: 0.00208 | P15: 0.00208 | Q15: 0.00208 | R15: 0.00208 | S15: 0.00208 | T15: 0.00208 | U15: 0.00208 | V15: 0.00208 | W15: 0.00208 | X15: 0.00208 | Y15: 0.00208 | Z15: 0.00208 | AA15: 0.00208 | AB15: 0.00208 | AC15: 0.00208 | AD15: 0.00208 | AE15: 0.00208 | AF15: 0.00208 | AG15: 0.00208 | AH15: 0.00208 | AI15: 0.00208 | AJ15: 0.00208 | AK15: 0.00208 | AL15: 0.00208 | AM15: 0.00208 | AN15: 0.00208 | AO15: 0.00208 | AP15: 0.00208 | AQ15: 0.00208 | AR15: 0.00208 | AS15: 0.00208 | AT15: 0.00208 | AU15: 0.00208 | AV15: 0.00208 | AW15: 0.00208 | AX15: 0.00208 | AY15: 0.00208 | AZ15: 0.00208 | BA15: 0.00208 | BB15: 0.00208 | BC15: 0.00208 | BD15: 0.00208 | BE15: 0.00208 | BF15: 0.00208 | BG15: 0.00208 | BH15: 0.00208 | BI15: 0.00208 | BJ15: 0.00208 | BK15: 0.00208 | BL15: 0.00208 | BM15: 0.00208 | BN15: 0.00208 | BO15: 0.00208 | BP15: 0.00208 | BQ15: 0.00208 | BR15: 0.00208 | BS15: 0.00208 | BT15: 0.00208 | BU15: 0.00208 | BV15: 0.00208 | BW15: 0.00208 | BX15: 0.00208 | BY15: 0.00208 | BZ15: 0.00208 | CA15: 0.00208 | CB15: 0.00208 | CC15: 0.00208 | CD15: 0.00208 | CE15: 0.00208 | CF15: 0.00208 | CG15: 0.00208 | CH15: 0.00208 | CI15: 0.00208 | CJ15: 0.00208 | CK15: 0.00208 | CL15: 0.00208 | CM15: 0.00208 | CN15: 0.00208 | CO15: 0.00208 | CP15: 0.00208 | CQ15: 0.00208 | CR15: 0.00208 | CS15: 0.00208 | CT15: 0.00208 | CU15: 0.00208 | CV15: 0.00208 | CW15: 0.00208 | CX15: 0.00208 | CY15: 0.00208 | CZ15: 0.00208 | DA15: 0.00208 | DB15: 0.00208 | DC15: 0.00208 | DD15: 0.00208 | DE15: 0.00208 | DF15: 0.00208 | DG15: 0.00208 | DH15: 0.00208 | DI15: 0.00208 | DJ15: 0.00208 | DK15: 0.00208 | DL15: 0.00208 | DM15: 0.00208 | DN15: 0.00208 | DO15: 0.00208 | DP15: 0.00208 | DQ15: 0.00208 | DR15: 0.00208 | DS15: 0.00208 | DT15: 0.00208 | DU15: 0.00208
C16: Налог на доходы физических лиц (НДФЛ) | D16: % | E16: 0.13 | F16: 0.13 | G16: 0.13 | H16: 0.13 | I16: 0.13 | J16: 0.13 | K16: 0.13 | L16: 0.13 | M16: 0.13 | N16: 0.13 | O16: 0.13 | P16: 0.13 | Q16: 0.13 | R16: 0.13 | S16: 0.13 | T16: 0.13 | U16: 0.13 | V16: 0.13 | W16: 0.13 | X16: 0.13 | Y16: 0.13 | Z16: 0.13 | AA16: 0.13 | AB16: 0.13 | AC16: 0.13 | AD16: 0.13 | AE16: 0.13 | AF16: 0.13 | AG16: 0.13 | AH16: 0.13 | AI16: 0.13 | AJ16: 0.13 | AK16: 0.13 | AL16: 0.13 | AM16: 0.13 | AN16: 0.13 | AO16: 0.13 | AP16: 0.13 | AQ16: 0.13 | AR16: 0.13 | AS16: 0.13 | AT16: 0.13 | AU16: 0.13 | AV16: 0.13 | AW16: 0.13 | AX16: 0.13 | AY16: 0.13 | AZ16: 0.13 | BA16: 0.13 | BB16: 0.13 | BC16: 0.13 | BD16: 0.13 | BE16: 0.13 | BF16: 0.13 | BG16: 0.13 | BH16: 0.13 | BI16: 0.13 | BJ16: 0.13 | BK16: 0.13 | BL16: 0.13 | BM16: 0.13 | BN16: 0.13 | BO16: 0.13 | BP16: 0.13 | BQ16: 0.13 | BR16: 0.13 | BS16: 0.13 | BT16: 0.13 | BU16: 0.13 | BV16: 0.13 | BW16: 0.13 | BX16: 0.13 | BY16: 0.13 | BZ16: 0.13 | CA16: 0.13 | CB16: 0.13 | CC16: 0.13 | CD16: 0.13 | CE16: 0.13 | CF16: 0.13 | CG16: 0.13 | CH16: 0.13 | CI16: 0.13 | CJ16: 0.13 | CK16: 0.13 | CL16: 0.13 | CM16: 0.13 | CN16: 0.13 | CO16: 0.13 | CP16: 0.13 | CQ16: 0.13 | CR16: 0.13 | CS16: 0.13 | CT16: 0.13 | CU16: 0.13 | CV16: 0.13 | CW16: 0.13 | CX16: 0.13 | CY16: 0.13 | CZ16: 0.13 | DA16: 0.13 | DB16: 0.13 | DC16: 0.13 | DD16: 0.13 | DE16: 0.13 | DF16: 0.13 | DG16: 0.13 | DH16: 0.13 | DI16: 0.13 | DJ16: 0.13 | DK16: 0.13 | DL16: 0.13 | DM16: 0.13 | DN16: 0.13 | DO16: 0.13 | DP16: 0.13 | DQ16: 0.13 | DR16: 0.13 | DS16: 0.13 | DT16: 0.13 | DU16: 0.13
C17: НДС | D17: % | E17: 0.18 | F17: 0.18 | G17: 0.18 | H17: 0.18 | I17: 0.18 | J17: 0.18 | K17: 0.18 | L17: 0.18 | M17: 0.18 | N17: 0.18 | O17: 0.18 | P17: 0.18 | Q17: 0.18 | R17: 0.18 | S17: 0.18 | T17: 0.18 | U17: 0.18 | V17: 0.18 | W17: 0.18 | X17: 0.18 | Y17: 0.18 | Z17: 0.18 | AA17: 0.18 | AB17: 0.18 | AC17: 0.18 | AD17: 0.18 | AE17: 0.18 | AF17: 0.18 | AG17: 0.18 | AH17: 0.18 | AI17: 0.18 | AJ17: 0.18 | AK17: 0.18 | AL17: 0.18 | AM17: 0.18 | AN17: 0.18 | AO17: 0.18 | AP17: 0.18 | AQ17: 0.18 | AR17: 0.18 | AS17: 0.18 | AT17: 0.18 | AU17: 0.18 | AV17: 0.18 | AW17: 0.18 | AX17: 0.18 | AY17: 0.18 | AZ17: 0.18 | BA17: 0.18 | BB17: 0.18 | BC17: 0.18 | BD17: 0.18 | BE17: 0.18 | BF17: 0.18 | BG17: 0.18 | BH17: 0.18 | BI17: 0.18 | BJ17: 0.18 | BK17: 0.18 | BL17: 0.18 | BM17: 0.18 | BN17: 0.18 | BO17: 0.18 | BP17: 0.18 | BQ17: 0.18 | BR17: 0.18 | BS17: 0.18 | BT17: 0.18 | BU17: 0.18 | BV17: 0.18 | BW17: 0.18 | BX17: 0.18 | BY17: 0.18 | BZ17: 0.18 | CA17: 0.18 | CB17: 0.18 | CC17: 0.18 | CD17: 0.18 | CE17: 0.18 | CF17: 0.18 | CG17: 0.18 | CH17: 0.18 | CI17: 0.18 | CJ17: 0.18 | CK17: 0.18 | CL17: 0.18 | CM17: 0.18 | CN17: 0.18 | CO17: 0.18 | CP17: 0.18 | CQ17: 0.18 | CR17: 0.18 | CS17: 0.18 | CT17: 0.18 | CU17: 0.18 | CV17: 0.18 | CW17: 0.18 | CX17: 0.18 | CY17: 0.18 | CZ17: 0.18 | DA17: 0.18 | DB17: 0.18 | DC17: 0.18 | DD17: 0.18 | DE17: 0.18 | DF17: 0.18 | DG17: 0.18 | DH17: 0.18 | DI17: 0.18 | DJ17: 0.18 | DK17: 0.18 | DL17: 0.18 | DM17: 0.18 | DN17: 0.18 | DO17: 0.18 | DP17: 0.18 | DQ17: 0.18 | DR17: 0.18 | DS17: 0.18 | DT17: 0.18 | DU17: 0.18
C18: Страховые взносы по персоналу: | D18: 7.6 | E18: 7.6 | F18: 7.6 | G18: 7.6 | H18: 7.6 | I18: 7.6 | J18: 7.6 | K18: 7.6 | L18: 7.6 | M18: 7.6 | N18: 7.6 | O18: 7.6 | P18: 7.6 | Q18: 7.6 | R18: 7.6 | S18: 7.6 | T18: 7.6 | U18: 7.6 | V18: 7.6 | W18: 7.6 | X18: 7.6 | Y18: 7.6 | Z18: 7.6 | AA18: 7.6 | AB18: 7.6 | AC18: 7.6 | AD18: 7.6 | AE18: 7.6 | AF18: 7.6 | AG18: 7.6 | AH18: 7.6 | AI18: 7.6 | AJ18: 7.6 | AK18: 7.6 | AL18: 7.6 | AM18: 7.6 | AN18: 7.6 | AO18: 7.6 | AP18: 7.6 | AQ18: 7.6 | AR18: 7.6 | AS18: 7.6 | AT18: 7.6 | AU18: 7.6 | AV18: 7.6 | AW18: 7.6 | AX18: 7.6 | AY18: 7.6 | AZ18: 7.6 | BA18: 7.6 | BB18: 7.6 | BC18: 7.6 | BD18: 7.6 | BE18: 7.6 | BF18: 7.6 | BG18: 7.6 | BH18: 7.6 | BI18: 7.6 | BJ18: 7.6 | BK18: 7.6 | BL18: 7.6 | BM18: 7.6 | BN18: 7.6 | BO18: 7.6 | BP18: 7.6 | BQ18: 7.6 | BR18: 7.6 | BS18: 7.6 | BT18: 7.6 | BU18: 7.6 | BV18: 7.6 | BW18: 7.6 | BX18: 7.6 | BY18: 7.6 | BZ18: 7.6 | CA18: 7.6 | CB18: 7.6 | CC18: 7.6 | CD18: 7.6 | CE18: 7.6 | CF18: 7.6 | CG18: 7.6 | CH18: 7.6 | CI18: 7.6 | CJ18: 7.6 | CK18: 7.6 | CL18: 7.6 | CM18: 7.6 | CN18: 7.6 | CO18: 7.6 | CP18: 7.6 | CQ18: 7.6 | CR18: 7.6 | CS18: 7.6 | CT18: 7.6 | CU18: 7.6 | CV18: 7.6 | CW18: 7.6 | CX18: 7.6 | CY18: 7.6 | CZ18: 7.6 | DA18: 7.6 | DB18: 7.6 | DC18: 7.6 | DD18: 7.6 | DE18: 7.6 | DF18: 7.6 | DG18: 7.6 | DH18: 7.6 | DI18: 7.6 | DJ18: 7.6 | DK18: 7.6 | DL18: 7.6 | DM18: 7.6 | DN18: 7.6 | DO18: 7.6 | DP18: 7.6 | DQ18: 7.6 | DR18: 7.6 | DS18: 7.6 | DT18: 7.6 | DU18: 7.6
C19: Пенсионный фонд (ПФР) | D19: % | E19: 0.06 | F19: 0.06 | G19: 0.06 | H19: 0.06 | I19: 0.06 | J19: 0.06 | K19: 0.06 | L19: 0.06 | M19: 0.06 | N19: 0.06 | O19: 0.06 | P19: 0.06 | Q19: 0.06 | R19: 0.06 | S19: 0.06 | T19: 0.06 | U19: 0.06 | V19: 0.06 | W19: 0.06 | X19: 0.06 | Y19: 0.06 | Z19: 0.06 | AA19: 0.06 | AB19: 0.06 | AC19: 0.06 | AD19: 0.06 | AE19: 0.06 | AF19: 0.06 | AG19: 0.06 | AH19: 0.06 | AI19: 0.06 | AJ19: 0.06 | AK19: 0.06 | AL19: 0.06 | AM19: 0.06 | AN19: 0.06 | AO19: 0.06 | AP19: 0.06 | AQ19: 0.06 | AR19: 0.06 | AS19: 0.06 | AT19: 0.06 | AU19: 0.06 | AV19: 0.06 | AW19: 0.06 | AX19: 0.06 | AY19: 0.06 | AZ19: 0.06 | BA19: 0.06 | BB19: 0.06 | BC19: 0.06 | BD19: 0.06 | BE19: 0.06 | BF19: 0.06 | BG19: 0.06 | BH19: 0.06 | BI19: 0.06 | BJ19: 0.06 | BK19: 0.06 | BL19: 0.06 | BM19: 0.06 | BN19: 0.06 | BO19: 0.06 | BP19: 0.06 | BQ19: 0.06 | BR19: 0.06 | BS19: 0.06 | BT19: 0.06 | BU19: 0.06 | BV19: 0.06 | BW19: 0.06 | BX19: 0.06 | BY19: 0.06 | BZ19: 0.06 | CA19: 0.06 | CB19: 0.06 | CC19: 0.06 | CD19: 0.06 | CE19: 0.06 | CF19: 0.06 | CG19: 0.06 | CH19: 0.06 | CI19: 0.06 | CJ19: 0.06 | CK19: 0.06 | CL19: 0.06 | CM19: 0.06 | CN19: 0.06 | CO19: 0.06 | CP19: 0.06 | CQ19: 0.06 | CR19: 0.06 | CS19: 0.06 | CT19: 0.06 | CU19: 0.06 | CV19: 0.06 | CW19: 0.06 | CX19: 0.06 | CY19: 0.06 | CZ19: 0.06 | DA19: 0.06 | DB19: 0.06 | DC19: 0.06 | DD19: 0.06 | DE19: 0.06 | DF19: 0.06 | DG19: 0.06 | DH19: 0.06 | DI19: 0.06 | DJ19: 0.06 | DK19: 0.06 | DL19: 0.06 | DM19: 0.06 | DN19: 0.06 | DO19: 0.06 | DP19: 0.06 | DQ19: 0.06 | DR19: 0.06 | DS19: 0.06 | DT19: 0.06 | DU19: 0.06
C20: Фонд социального страхования (ФСС) | D20: % | E20: 0.015 | F20: 0.015 | G20: 0.015 | H20: 0.015 | I20: 0.015 | J20: 0.015 | K20: 0.015 | L20: 0.015 | M20: 0.015 | N20: 0.015 | O20: 0.015 | P20: 0.015 | Q20: 0.015 | R20: 0.015 | S20: 0.015 | T20: 0.015 | U20: 0.015 | V20: 0.015 | W20: 0.015 | X20: 0.015 | Y20: 0.015 | Z20: 0.015 | AA20: 0.015 | AB20: 0.015 | AC20: 0.015 | AD20: 0.015 | AE20: 0.015 | AF20: 0.015 | AG20: 0.015 | AH20: 0.015 | AI20: 0.015 | AJ20: 0.015 | AK20: 0.015 | AL20: 0.015 | AM20: 0.015 | AN20: 0.015 | AO20: 0.015 | AP20: 0.015 | AQ20: 0.015 | AR20: 0.015 | AS20: 0.015 | AT20: 0.015 | AU20: 0.015 | AV20: 0.015 | AW20: 0.015 | AX20: 0.015 | AY20: 0.015 | AZ20: 0.015 | BA20: 0.015 | BB20: 0.015 | BC20: 0.015 | BD20: 0.015 | BE20: 0.015 | BF20: 0.015 | BG20: 0.015 | BH20: 0.015 | BI20: 0.015 | BJ20: 0.015 | BK20: 0.015 | BL20: 0.015 | BM20: 0.015 | BN20: 0.015 | BO20: 0.015 | BP20: 0.015 | BQ20: 0.015 | BR20: 0.015 | BS20: 0.015 | BT20: 0.015 | BU20: 0.015 | BV20: 0.015 | BW20: 0.015 | BX20: 0.015 | BY20: 0.015 | BZ20: 0.015 | CA20: 0.015 | CB20: 0.015 | CC20: 0.015 | CD20: 0.015 | CE20: 0.015 | CF20: 0.015 | CG20: 0.015 | CH20: 0.015 | CI20: 0.015 | CJ20: 0.015 | CK20: 0.015 | CL20: 0.015 | CM20: 0.015 | CN20: 0.015 | CO20: 0.015 | CP20: 0.015 | CQ20: 0.015 | CR20: 0.015 | CS20: 0.015 | CT20: 0.015 | CU20: 0.015 | CV20: 0.015 | CW20: 0.015 | CX20: 0.015 | CY20: 0.015 | CZ20: 0.015 | DA20: 0.015 | DB20: 0.015 | DC20: 0.015 | DD20: 0.015 | DE20: 0.015 | DF20: 0.015 | DG20: 0.015 | DH20: 0.015 | DI20: 0.015 | DJ20: 0.015 | DK20: 0.015 | DL20: 0.015 | DM20: 0.015 | DN20: 0.015 | DO20: 0.015 | DP20: 0.015 | DQ20: 0.015 | DR20: 0.015 | DS20: 0.015 | DT20: 0.015 | DU20: 0.015
C21: Фонд обязательного медицинского страхования (ФОМС) | D21: % | E21: 0.001 | F21: 0.001 | G21: 0.001 | H21: 0.001 | I21: 0.001 | J21: 0.001 | K21: 0.001 | L21: 0.001 | M21: 0.001 | N21: 0.001 | O21: 0.001 | P21: 0.001 | Q21: 0.001 | R21: 0.001 | S21: 0.001 | T21: 0.001 | U21: 0.001 | V21: 0.001 | W21: 0.001 | X21: 0.001 | Y21: 0.001 | Z21: 0.001 | AA21: 0.001 | AB21: 0.001 | AC21: 0.001 | AD21: 0.001 | AE21: 0.001 | AF21: 0.001 | AG21: 0.001 | AH21: 0.001 | AI21: 0.001 | AJ21: 0.001 | AK21: 0.001 | AL21: 0.001 | AM21: 0.001 | AN21: 0.001 | AO21: 0.001 | AP21: 0.001 | AQ21: 0.001 | AR21: 0.001 | AS21: 0.001 | AT21: 0.001 | AU21: 0.001 | AV21: 0.001 | AW21: 0.001 | AX21: 0.001 | AY21: 0.001 | AZ21: 0.001 | BA21: 0.001 | BB21: 0.001 | BC21: 0.001 | BD21: 0.001 | BE21: 0.001 | BF21: 0.001 | BG21: 0.001 | BH21: 0.001 | BI21: 0.001 | BJ21: 0.001 | BK21: 0.001 | BL21: 0.001 | BM21: 0.001 | BN21: 0.001 | BO21: 0.001 | BP21: 0.001 | BQ21: 0.001 | BR21: 0.001 | BS21: 0.001 | BT21: 0.001 | BU21: 0.001 | BV21: 0.001 | BW21: 0.001 | BX21: 0.001 | BY21: 0.001 | BZ21: 0.001 | CA21: 0.001 | CB21: 0.001 | CC21: 0.001 | CD21: 0.001 | CE21: 0.001 | CF21: 0.001 | CG21: 0.001 | CH21: 0.001 | CI21: 0.001 | CJ21: 0.001 | CK21: 0.001 | CL21: 0.001 | CM21: 0.001 | CN21: 0.001 | CO21: 0.001 | CP21: 0.001 | CQ21: 0.001 | CR21: 0.001 | CS21: 0.001 | CT21: 0.001 | CU21: 0.001 | CV21: 0.001 | CW21: 0.001 | CX21: 0.001 | CY21: 0.001 | CZ21: 0.001 | DA21: 0.001 | DB21: 0.001 | DC21: 0.001 | DD21: 0.001 | DE21: 0.001 | DF21: 0.001 | DG21: 0.001 | DH21: 0.001 | DI21: 0.001 | DJ21: 0.001 | DK21: 0.001 | DL21: 0.001 | DM21: 0.001 | DN21: 0.001 | DO21: 0.001 | DP21: 0.001 | DQ21: 0.001 | DR21: 0.001 | DS21: 0.001 | DT21: 0.001 | DU21: 0.001
C22: Страховые взносы по ООО^ | D22: руб. | E22: =SUM(F22:DU22) -> 5.4721566e+09 | F22: =SUM(F23:F25) -> 45613047 | G22: =SUM(G23:G25) -> 45613047 | H22: =SUM(H23:H25) -> 45613047 | I22: =SUM(I23:I25) -> 45613047 | J22: =SUM(J23:J25) -> 45613047 | K22: =SUM(K23:K25) -> 45613047 | L22: =SUM(L23:L25) -> 45613047 | M22: =SUM(M23:M25) -> 45613047 | ... DU22: =SUM(DU23:DU25) -> 45600000
C23: Пенсионный фонд (ПФР) | D23: руб. | E23: =SUM(F23:DU23) -> 4.3201236e+09 | F23: =F33*F19 -> 36010300 | G23: =G33*G19 -> 36010300 | H23: =H33*H19 -> 36010300 | I23: =I33*I19 -> 36010300 | J23: =J33*J19 -> 36010300 | K23: =K33*K19 -> 36010300 | L23: =L33*L19 -> 36010300 | M23: =M33*M19 -> 36010300 | ... DU23: =DU33*DU19 -> 36000000
C24: Фонд обязательного медицинского страхования (ФОМС) | D24: руб. | E24: =SUM(F24:DU24) -> 1.0800309e+09 | F24: =F33*F20 -> 9002575 | G24: =G33*G20 -> 9002575 | H24: =H33*H20 -> 9002575 | I24: =I33*I20 -> 9002575 | J24: =J33*J20 -> 9002575 | K24: =K33*K20 -> 9002575 | L24: =L33*L20 -> 9002575 | M24: =M33*M20 -> 9002575 | ... DU24: =DU33*DU20 -> 9000000
C25: Медицинские взносы | D25: руб. | E25: =SUM(F25:DU25) -> 72002060 | F25: =F33*F21 -> 600171.67 | G25: =G33*G21 -> 600171.67 | H25: =H33*H21 -> 600171.67 | I25: =I33*I21 -> 600171.67 | J25: =J33*J21 -> 600171.67 | K25: =K33*K21 -> 600171.67 | L25: =L33*L21 -> 600171.67 | M25: =M33*M21 -> 600171.67 | ... DU25: =DU33*DU21 -> 600000
C26: 2. Коэффициенты
C27: Ключевая ставка ЦБ РФ | D27: % | E27: 14.5
C28: Рентабельность проекта | D28: % | E28: 23.33
C29: 3. Инвестиции в проект
C30: 3.1. Капитальные затраты | D30: руб. | E30: =SUM(F30:DU30) -> 0 | F30: 0 | G30: 0 | H30: 0 | I30: 0 | J30: 0 | K30: 0 | L30: 0 | M30: 0 | N30: 0 | O30: 0 | P30: 0 | Q30: 0 | R30: 0 | S30: 0 | T30: 0 | U30: 0 | V30: 0 | W30: 0 | X30: 0 | Y30: 0 | Z30: 0 | AA30: 0 | AB30: 0 | AC30: 0 | AD30: 0 | AE30: 0 | AF30: 0 | AG30: 0 | AH30: 0 | AI30: 0 | AJ30: 0 | AK30: 0 | AL30: 0 | AM30: 0 | AN30: 0 | AO30: 0 | AP30: 0 | AQ30: 0 | AR30: 0 | AS30: 0 | AT30: 0 | AU30: 0 | AV30: 0 | AW30: 0 | AX30: 0 | AY30: 0 | AZ30: 0 | BA30: 0 | BB30: 0 | BC30: 0 | BD30: 0 | BE30: 0 | BF30: 0 | BG30: 0 | BH30: 0 | BI30: 0 | BJ30: 0 | BK30: 0 | BL30: 0 | BM30: 0 | BN30: 0 | BO30: 0 | BP30: 0 | BQ30: 0 | BR30: 0 | BS30: 0 | BT30: 0 | BU30: 0 | BV30: 0 | BW30: 0 | BX30: 0 | BY30: 0 | BZ30: 0 | CA30: 0 | CB30: 0 | CC30: 0 | CD30: 0 | CE30: 0 | CF30: 0 | CG30: 0 | CH30: 0 | CI30: 0 | CJ30: 0 | CK30: 0 | CL30: 0 | CM30: 0 | CN30: 0 | CO30: 0 | CP30: 0 | CQ30: 0 | CR30: 0 | CS30: 0 | CT30: 0 | CU30: 0 | CV30: 0 | CW30: 0 | CX30: 0 | CY30: 0 | CZ30: 0 | DA30: 0 | DB30: 0 | DC30: 0 | DD30: 0 | DE30: 0 | DF30: 0 | DG30: 0 | DH30: 0 | DI30: 0 | DJ30: 0 | DK30: 0 | DL30: 0 | DM30: 0 | DN30: 0 | DO30: 0 | DP30: 0 | DQ30: 0 | DR30: 0 | DS30: 0 | DT30: 0 | DU30: 0
C31: 3.2. Операционные затраты | D31: руб. | E31: =SUM(E32:E34) -> 2.1604282e+10 | F31: =F32+F33+F34 -> 600171666 | G31: =G32+G33+G34 -> 600171666 | H31: =H32+H33+H34 -> 600171666 | I31: =I32+I33+I34 -> 600171666 | J31: =J32+J33+J34 -> 600171666 | K31: =K32+K33+K34 -> 600171666 | L31: =L32+L33+L34 -> 600171666 | M31: =M32+M33+M34 -> 600171666 | ... DU31: =DU32+DU33+DU34 -> 6.0009259e+08
C32: 3.2.1. Текущие затраты | D32: руб. | E32: =SUM(F32:AO32) -> 2222222.4 | F32: ='Операционные затраты'!E8 -> 0 | G32: 0 | H32: 0 | I32: 0 | J32: 0 | K32: 0 | L32: 0 | M32: 0 | N32: 0 | O32: 0 | P32: 0 | Q32: 0 | R32: 92592.6 | S32: 92592.6 | T32: 92592.6 | U32: 92592.6 | V32: 92592.6 | W32: 92592.6 | X32: 92592.6 | Y32: 92592.6 | Z32: 92592.6 | AA32: 92592.6 | AB32: 92592.6 | AC32: 92592.6 | AD32: 92592.6 | AE32: 92592.6 | AF32: 92592.6 | AG32: 92592.6 | AH32: 92592.6 | AI32: 92592.6 | AJ32: 92592.6 | AK32: 92592.6 | AL32: 92592.6 | AM32: 92592.6 | AN32: 92592.6 | AO32: 92592.6 | AP32: 92592.6 | AQ32: 92592.6 | AR32: 92592.6 | AS32: 92592.6 | AT32: 92592.6 | AU32: 92592.6 | AV32: 92592.6 | AW32: 92592.6 | AX32: 92592.6 | AY32: 92592.6 | AZ32: 92592.6 | BA32: 92592.6 | BB32: 92592.6 | BC32: 92592.6 | BD32: 92592.6 | BE32: 92592.6 | BF32: 92592.6 | BG32: 92592.6 | BH32: 92592.6 | BI32: 92592.6 | BJ32: 92592.6 | BK32: 92592.6 | BL32: 92592.6 | BM32: 92592.6 | BN32: 92592.6 | BO32: 92592.6 | BP32: 92592.6 | BQ32: 92592.6 | BR32: 92592.6 | BS32: 92592.6 | BT32: 92592.6 | BU32: 92592.6 | BV32: 92592.6 | BW32: 92592.6 | BX32: 92592.6 | BY32: 92592.6 | BZ32: 92592.6 | CA32: 92592.6 | CB32: 92592.6 | CC32: 92592.6 | CD32: 92592.6 | CE32: 92592.6 | CF32: 92592.6 | CG32: 92592.6 | CH32: 92592.6 | CI32: 92592.6 | CJ32: 92592.6 | CK32: 92592.6 | CL32: 92592.6 | CM32: 92592.6 | CN32: 92592.6 | CO32: 92592.6 | CP32: 92592.6 | CQ32: 92592.6 | CR32: 92592.6 | CS32: 92592.6 | CT32: 92592.6 | CU32: 92592.6 | CV32: 92592.6 | CW32: 92592.6 | CX32: 92592.6 | CY32: 92592.6 | CZ32: 92592.6 | DA32: 92592.6 | DB32: 92592.6 | DC32: 92592.6 | DD32: 92592.6 | DE32: 92592.6 | DF32: 92592.6 | DG32: 92592.6 | DH32: 92592.6 | DI32: 92592.6 | DJ32: 92592.6 | DK32: 92592.6 | DL32: 92592.6 | DM32: 92592.6 | DN32: 92592.6 | DO32: 92592.6 | DP32: 92592.6 | DQ32: 92592.6 | DR32: 92592.6 | DS32: 92592.6 | DT32: 92592.6 | DU32: 92592.6
C33: 3.2.2.Административные затраты | D33: руб. | E33: =SUM(F33:AO33) -> 21602059992 | F33: =SUM('Операционные затраты'!E8,'Операционные затраты'!E22,'Операционные затраты'!E24) -> 600171666 | G33: =SUM('Операционные затраты'!F8,'Операционные затраты'!F22,'Операционные затраты'!F24) -> 600171666 | H33: =SUM('Операционные затраты'!G8,'Операционные затраты'!G22,'Операционные затраты'!G24) -> 600171666 | I33: =SUM('Операционные затраты'!H8,'Операционные затраты'!H22,'Операционные затраты'!H24) -> 600171666 | J33: =SUM('Операционные затраты'!I8,'Операционные затраты'!I22,'Операционные затраты'!I24) -> 600171666 | K33: =SUM('Операционные затраты'!J8,'Операционные затраты'!J22,'Операционные затраты'!J24) -> 600171666 | L33: =SUM('Операционные затраты'!K8,'Операционные затраты'!K22,'Операционные затраты'!K24) -> 600171666 | M33: =SUM('Операционные затраты'!L8,'Операционные затраты'!L22,'Операционные затраты'!L24) -> 600171666 | ... DU33: =SUM('Операционные затраты'!DT8,'Операционные затраты'!DT22,'Операционные затраты'!DT24) -> 600000000
C34: 3.2.3. Прочие расходы | D34: руб. | E34: =SUM(F34:AO34) -> 0 | F34: 0 | G34: 0 | H34: 0 | I34: 0 | J34: 0 | K34: 0 | L34: 0 | M34: 0 | N34: 0 | O34: 0 | P34: 0 | Q34: 0 | R34: 0 | S34: 0 | T34: 0 | U34: 0 | V34: 0 | W34: 0 | X34: 0 | Y34: 0 | Z34: 0 | AA34: 0 | AB34: 0 | AC34: 0 | AD34: 0 | AE34: 0 | AF34: 0 | AG34: 0 | AH34: 0 | AI34: 0 | AJ34: 0 | AK34: 0 | AL34: 0 | AM34: 0 | AN34: 0 | AO34: 0 | AP34: 0 | AQ34: 0 | AR34: 0 | AS34: 0 | AT34: 0 | AU34: 0 | AV34: 0 | AW34: 0 | AX34: 0 | AY34: 0 | AZ34: 0 | BA34: 0 | BB34: 0 | BC34: 0 | BD34: 0 | BE34: 0 | BF34: 0 | BG34: 0 | BH34: 0 | BI34: 0 | BJ34: 0 | BK34: 0 | BL34: 0 | BM34: 0 | BN34: 0 | BO34: 0 | BP34: 0 | BQ34: 0 | BR34: 0 | BS34: 0 | BT34: 0 | BU34: 0 | BV34: 0 | BW34: 0 | BX34: 0 | BY34: 0 | BZ34: 0 | CA34: 0 | CB34: 0 | CC34: 0 | CD34: 0 | CE34: 0 | CF34: 0 | CG34: 0 | CH34: 0 | CI34: 0 | CJ34: 0 | CK34: 0 | CL34: 0 | CM34: 0 | CN34: 0 | CO34: 0 | CP34: 0 | CQ34: 0 | CR34: 0 | CS34: 0 | CT34: 0 | CU34: 0 | CV34: 0 | CW34: 0 | CX34: 0 | CY34: 0 | CZ34: 0 | DA34: 0 | DB34: 0 | DC34: 0 | DD34: 0 | DE34: 0 | DF34: 0 | DG34: 0 | DH34: 0 | DI34: 0 | DJ34: 0 | DK34: 0 | DL34: 0 | DM34: 0 | DN34: 0 | DO34: 0 | DP34: 0 | DQ34: 0 | DR34: 0 | DS34: 0 | DT34: 0 | DU34: 0
C36: Заемные средства | D36: руб. | E36: =SUM(F36:I36) -> 0 | F36: 0 | G36: 0 | H36: 0 | I36: 0 | J36: 0 | K36: 0 | L36: 0 | M36: 0 | N36: 0 | O36: 0 | P36: 0 | Q36: 0 | R36: 0 | S36: 0 | T36: 0 | U36: 0 | V36: 0 | W36: 0 | X36: 0 | Y36: 0 | Z36: 0 | AA36: 0 | AB36: 0 | AC36: 0 | AD36: 0 | AE36: 0 | AF36: 0 | AG36: 0 | AH36: 0 | AI36: 0 | AJ36: 0 | AK36: 0 | AL36: 0 | AM36: 0 | AN36: 0 | AO36: 0 | AP36: 0 | AQ36: 0 | AR36: 0 | AS36: 0 | AT36: 0 | AU36: 0 | AV36: 0 | AW36: 0 | AX36: 0 | AY36: 0 | AZ36: 0 | BA36: 0 | BB36: 0 | BC36: 0 | BD36: 0 | BE36: 0 | BF36: 0 | BG36: 0 | BH36: 0 | BI36: 0 | BJ36: 0 | BK36: 0 | BL36: 0 | BM36: 0 | BN36: 0 | BO36: 0 | BP36: 0 | BQ36: 0 | BR36: 0 | BS36: 0 | BT36: 0 | BU36: 0 | BV36: 0 | BW36: 0 | BX36: 0 | BY36: 0 | BZ36: 0 | CA36: 0 | CB36: 0 | CC36: 0 | CD36: 0 | CE36: 0 | CF36: 0 | CG36: 0 | CH36: 0 | CI36: 0 | CJ36: 0 | CK36: 0 | CL36: 0 | CM36: 0 | CN36: 0 | CO36: 0 | CP36: 0 | CQ36: 0 | CR36: 0 | CS36: 0 | CT36: 0 | CU36: 0 | CV36: 0 | CW36: 0 | CX36: 0 | CY36: 0 | CZ36: 0 | DA36: 0 | DB36: 0 | DC36: 0 | DD36: 0 | DE36: 0 | DF36: 0 | DG36: 0 | DH36: 0 | DI36: 0 | DJ36: 0 | DK36: 0 | DL36: 0 | DM36: 0 | DN36: 0 | DO36: 0 | DP36: 0 | DQ36: 0 | DR36: 0 | DS36: 0 | DT36: 0 | DU36: 0
C37: 4. Источники финансирования:
C38: Доля собственных средств | D38: %, 100 | E38: =SUM(F38:DU38) -> 276961520 | F38: 276961520 | G38: 0 | H38: 0 | I38: 0 | J38: 0 | K38: 0 | L38: 0 | M38: 0 | N38: 0 | O38: 0 | P38: 0 | Q38: 0 | R38: 0 | S38: 0 | T38: 0 | U38: 0 | V38: 0 | W38: 0 | X38: 0 | Y38: 0 | Z38: 0 | AA38: 0 | AB38: 0 | AC38: 0 | AD38: 0 | AE38: 0 | AF38: 0 | AG38: 0 | AH38: 0 | AI38: 0 | AJ38: 0 | AK38: 0 | AL38: 0 | AM38: 0 | AN38: 0 | AO38: 0 | AP38: 0 | AQ38: =AQ30 -> 0 | AR38: =AR30 -> 0 | AS38: =AS30 -> 0 | AT38: =AT30 -> 0 | AU38: =AU30 -> 0 | AV38: =AV30 -> 0 | AW38: =AW30 -> 0 | AX38: =AX30 -> 0 | ... DU38: =DU30 -> 0
C39: Доля заемных средств, вкладываемых в производство | D39: % | E39: 0 | F39: 0 | G39: 0 | H39: 0 | I39: 0 | J39: 0 | K39: 0 | L39: 0 | M39: 0 | N39: 0 | O39: 0 | P39: 0 | Q39: 0 | R39: 0 | S39: 0 | T39: 0 | U39: 0 | V39: 0 | W39: 0 | X39: 0 | Y39: 0 | Z39: 0 | AA39: 0 | AB39: 0 | AC39: 0 | AD39: 0 | AE39: 0 | AF39: 0 | AG39: 0 | AH39: 0 | AI39: 0 | AJ39: 0 | AK39: 0 | AL39: 0 | AM39: 0 | AN39: 0 | AO39: 0 | AP39: 0 | AQ39: 0 | AR39: 0 | AS39: 0 | AT39: 0 | AU39: 0 | AV39: 0 | AW39: 0 | AX39: 0 | AY39: 0 | AZ39: 0 | BA39: 0 | BB39: 0 | BC39: 0 | BD39: 0 | BE39: 0 | BF39: 0 | BG39: 0 | BH39: 0 | BI39: 0 | BJ39: 0 | BK39: 0 | BL39: 0 | BM39: 0 | BN39: 0 | BO39: 0 | BP39: 0 | BQ39: 0 | BR39: 0 | BS39: 0 | BT39: 0 | BU39: 0 | BV39: 0 | BW39: 0 | BX39: 0 | BY39: 0 | BZ39: 0 | CA39: 0 | CB39: 0 | CC39: 0 | CD39: 0 | CE39: 0 | CF39: 0 | CG39: 0 | CH39: 0 | CI39: 0 | CJ39: 0 | CK39: 0 | CL39: 0 | CM39: 0 | CN39: 0 | CO39: 0 | CP39: 0 | CQ39: 0 | CR39: 0 | CS39: 0 | CT39: 0 | CU39: 0 | CV39: 0 | CW39: 0 | CX39: 0 | CY39: 0 | CZ39: 0 | DA39: 0 | DB39: 0 | DC39: 0 | DD39: 0 | DE39: 0 | DF39: 0 | DG39: 0 | DH39: 0 | DI39: 0 | DJ39: 0 | DK39: 0 | DL39: 0 | DM39: 0 | DN39: 0 | DO39: 0 | DP39: 0 | DQ39: 0 | DR39: 0 | DS39: 0 | DT39: 0 | DU39: 0
C40: 5. Индекс инфляции | D40: % | E40: 0.145 | F40: =(1+(1+$E$40)^(1/12)-1)^1 -> 1.0113476 | G40: =(1+(1+$E$40)^(1/12)-1)^2 -> 1.022824 | H40: =(1+(1+$E$40)^(1/12)-1)^3 -> 1.0344306 | I40: =(1+(1+$E$40)^(1/12)-1)^4 -> 1.046169 | J40: =(1+(1+$E$40)^(1/12)-1)^5 -> 1.0580405 | K40: =(1+(1+$E$40)^(1/12)-1)^6 -> 1.0700467 | L40: =(1+(1+$E$40)^(1/12)-1)^7 -> 1.0821892 | M40: =(1+(1+$E$40)^(1/12)-1)^8 -> 1.0944695 | N40: =(1+(1+$E$40)^(1/12)-1)^9 -> 1.1068891 | O40: =(1+(1+$E$40)^(1/12)-1)^10 -> 1.1194497 | P40: =(1+(1+$E$40)^(1/12)-1)^11 -> 1.1321528 | Q40: =(1+(1+$E$40)^(1/12)-1)^12 -> 1.145 | R40: =(1+(1+$E$40)^(1/12)-1)^13 -> 1.157993 | S40: =(1+(1+$E$40)^(1/12)-1)^14 -> 1.1711335 | T40: =(1+(1+$E$40)^(1/12)-1)^15 -> 1.1844231 | U40: =(1+(1+$E$40)^(1/12)-1)^16 -> 1.1978635 | V40: =(1+(1+$E$40)^(1/12)-1)^17 -> 1.2114564 | W40: =(1+(1+$E$40)^(1/12)-1)^18 -> 1.2252035 | X40: =(1+(1+$E$40)^(1/12)-1)^19 -> 1.2391066 | Y40: =(1+(1+$E$40)^(1/12)-1)^20 -> 1.2531676 | Z40: =(1+(1+$E$40)^(1/12)-1)^Z12 -> 1.267388 | AA40: =(1+(1+$E$40)^(1/12)-1)^AA12 -> 1.2817699 | AB40: =(1+(1+$E$40)^(1/12)-1)^AB12 -> 1.2963149 | AC40: =(1+(1+$E$40)^(1/12)-1)^AC12 -> 1.311025 | AD40: =(1+(1+$E$40)^(1/12)-1)^AD12 -> 1.325902 | AE40: =(1+(1+$E$40)^(1/12)-1)^AE12 -> 1.3409478 | AF40: =(1+(1+$E$40)^(1/12)-1)^AF12 -> 1.3561644 | AG40: =(1+(1+$E$40)^(1/12)-1)^AG12 -> 1.3715537 | ... DU40: =(1+(1+$E$40)^(1/12)-1)^DU12 -> 3.8730657
C41: 6. Основные средства | D41: руб. | E41: =SUM(F41:DU41) -> 355200000000000 | F41: ='Амортизация, до'!I18 -> 2960000000000 | G41: ='Амортизация, до'!J18 -> 2960000000000 | H41: ='Амортизация, до'!K18 -> 2960000000000 | I41: ='Амортизация, до'!L18 -> 2960000000000 | J41: ='Амортизация, до'!M18 -> 2960000000000 | K41: ='Амортизация, до'!N18 -> 2960000000000 | L41: ='Амортизация, до'!O18 -> 2960000000000 | M41: ='Амортизация, до'!P18 -> 2960000000000 | ... DU41: ='Амортизация, до'!DX18 -> 2960000000000
C42: 7. Амортизация | D42: руб. | E42: =SUM(F42:DU42) -> 8.400565e+11 | F42: ='Амортизация, до'!I17 -> 8222288000 | G42: ='Амортизация, до'!J17 -> 8.1994481e+09 | H42: ='Амортизация, до'!K17 -> 8.1766717e+09 | I42: ='Амортизация, до'!L17 -> 8.1539585e+09 | J42: ='Амортизация, до'!M17 -> 8.1313085e+09 | K42: ='Амортизация, до'!N17 -> 8.1087213e+09 | L42: ='Амортизация, до'!O17 -> 8.0861969e+09 | M42: ='Амортизация, до'!P17 -> 8.0637351e+09 | ... DU42: ='Амортизация, до'!DX17 -> 5.9051825e+09

Sheet Выручка, до
A1: Выручка до внедрения
D2: 1 год | P2: 2 год | AB2: 3 год | AN2: 4 год | AZ2: 5 год | BL2: 6 год | BX2: 7 год | CJ2: 8 год | CV2: 9 год | DH2: 10 год
A3: Показатель | B3: Ед. из. | C3: Сумма | D3: 1 | E3: 2 | F3: 3 | G3: 4 | H3: 5 | I3: 6 | J3: 7 | K3: 8 | L3: 9 | M3: 10 | N3: 11 | O3: 12 | P3: 1 | Q3: 2 | R3: 3 | S3: 4 | T3: 5 | U3: 6 | V3: 7 | W3: 8 | X3: 9 | Y3: 10 | Z3: 11 | AA3: 12 | AB3: 1 | AC3: 2 | AD3: 3 | AE3: 4 | AF3: 5 | AG3: 6 | AH3: 7 | AI3: 8 | AJ3: 9 | AK3: 10 | AL3: 11 | AM3: 12 | AN3: 1 | AO3: 2 | AP3: 3 | AQ3: 4 | AR3: 5 | AS3: 6 | AT3: 7 | AU3: 8 | AV3: 9 | AW3: 10 | AX3: 11 | AY3: 12 | AZ3: 1 | BA3: 2 | BB3: 3 | BC3: 4 | BD3: 5 | BE3: 6 | BF3: 7 | BG3: 8 | BH3: 9 | BI3: 10 | BJ3: 11 | BK3: 12 | BL3: 1 | BM3: 2 | BN3: 3 | BO3: 4 | BP3: 5 | BQ3: 6 | BR3: 7 | BS3: 8 | BT3: 9 | BU3: 10 | BV3: 11 | BW3: 12 | BX3: 1 | BY3: 2 | BZ3: 3 | CA3: 4 | CB3: 5 | CC3: 6 | CD3: 7 | CE3: 8 | CF3: 9 | CG3: 10 | CH3: 11 | CI3: 12 | CJ3: 1 | CK3: 2 | CL3: 3 | CM3: 4 | CN3: 5 | CO3: 6 | CP3: 7 | CQ3: 8 | CR3: 9 | CS3: 10 | CT3: 11 | CU3: 12 | CV3: 1 | CW3: 2 | CX3: 3 | CY3: 4 | CZ3: 5 | DA3: 6 | DB3: 7 | DC3: 8 | DD3: 9 | DE3: 10 | DF3: 11 | DG3: 12 | DH3: 1 | DI3: 2 | DJ3: 3 | DK3: 4 | DL3: 5 | DM3: 6 | DN3: 7 | DO3: 8 | DP3: 9 | DQ3: 10 | DR3: 11 | DS3: 12
D4: 1 | E4: 2 | F4: 3 | G4: 4 | H4: 5 | I4: 6 | J4: 7 | K4: 8 | L4: 9 | M4: 10 | N4: 11 | O4: 12 | P4: 13 | Q4: 14 | R4: 15 | S4: 16 | T4: 17 | U4: 18 | V4: 19 | W4: 20 | X4: 21 | Y4: 22 | Z4: 23 | AA4: 24 | AB4: 25 | AC4: 26 | AD4: 27 | AE4: 28 | AF4: 29 | AG4: 30 | AH4: 31 | AI4: 32 | AJ4: 33 | AK4: 34 | AL4: 35 | AM4: 36 | AN4: 1 | AO4: 2 | AP4: 3 | AQ4: 4 | AR4: 5 | AS4: 6 | AT4: 7 | AU4: 8 | AV4: 9 | AW4: 10 | AX4: 11 | AY4: 12 | AZ4: 13 | BA4: 14 | BB4: 15 | BC4: 16 | BD4: 17 | BE4: 18 | BF4: 19 | BG4: 20 | BH4: 21 | BI4: 22 | BJ4: 23 | BK4: 24 | BL4: 1 | BM4: 2 | BN4: 3 | BO4: 4 | BP4: 5 | BQ4: 6 | BR4: 7 | BS4: 8 | BT4: 9 | BU4: 10 | BV4: 11 | BW4: 12 | BX4: 13 | BY4: 14 | BZ4: 15 | CA4: 16 | CB4: 17 | CC4: 18 | CD4: 19 | CE4: 20 | CF4: 21 | CG4: 22 | CH4: 23 | CI4: 24 | CJ4: 25 | CK4: 26 | CL4: 27 | CM4: 28 | CN4: 29 | CO4: 30 | CP4: 31 | CQ4: 32 | CR4: 33 | CS4: 34 | CT4: 35 | CU4: 36 | CV4: 1 | CW4: 2 | CX4: 3 | CY4: 4 | CZ4: 5 | DA4: 6 | DB4: 7 | DC4: 8 | DD4: 9 | DE4: 10 | DF4: 11 | DG4: 12 | DH4: 13 | DI4: 14 | DJ4: 15 | DK4: 16 | DL4: 17 | DM4: 18 | DN4: 19 | DO4: 20 | DP4: 21 | DQ4: 22 | DR4: 23 | DS4: 24
A5: Количество клиентов | B5: чел. | C5: =SUM(D5:DS5) -> 2.087913e+09 | D5: 9076356 | E5: =1.01*D5 -> 9167119.6 | F5: =1.01*E5 -> 9258790.8 | G5: =1.01*F5 -> 9351378.7 | H5: =1.01*G5 -> 9444892.4 | I5: =1.01*H5 -> 9539341.4 | J5: =1.01*I5 -> 9634734.8 | K5: =1.01*J5 -> 9731082.1 | L5: =1.01*K5 -> 9828393 | ... DS5: =1.01*DR5 -> 29658897
A6: Средний чек | B6: руб. | C6: =SUM(D6:DS6) -> 1150193.4 | D6: 5000 | E6: =D6*1.01 -> 5050 | F6: =E6*1.01 -> 5100.5 | G6: =F6*1.01 -> 5151.505 | H6: =G6*1.01 -> 5203.0201 | I6: =H6*1.01 -> 5255.0503 | J6: =I6*1.01 -> 5307.6008 | K6: =J6*1.01 -> 5360.6768 | L6: =K6*1.01 -> 5414.2835 | ... DS6: =DR6*1.01 -> 16338.549
A7: Выручка | B7: руб. | C7: =SUM(D7:DS7) -> 2.2335408e+13 | D7: =D5*D6 -> 45381780000 | E7: =E5*E6 -> 46293953778 | F7: =F5*F6 -> 4.7224462e+10 | G7: =G5*G6 -> 4.8173674e+10 | H7: =H5*H6 -> 4.9141965e+10 | I7: =I5*I6 -> 5.0129718e+10 | J7: =J5*J6 -> 5.1137326e+10 | K7: =K5*K6 -> 5.2165186e+10 | ... DS7: =DS5*DS6 -> 4.8458335e+11
A8: Инфляция | B8: % | C8: ='Исходные данные'!E40 -> 0.145 | D8: ='Исходные данные'!F40 -> 1.0113476 | E8: ='Исходные данные'!G40 -> 1.022824 | F8: ='Исходные данные'!H40 -> 1.0344306 | G8: ='Исходные данные'!I40 -> 1.046169 | H8: ='Исходные данные'!J40 -> 1.0580405 | I8: ='Исходные данные'!K40 -> 1.0700467 | J8: ='Исходные данные'!L40 -> 1.0821892 | ... DS8: ='Исходные данные'!DU40 -> 3.8730657
A9: Выручка с учетом инфляции | B9: руб. | C9: =SUM(D9:DS9) -> 8.2014455e+13 | D9: =D7+D7*D8 -> 9.1278535e+10 | E9: =E7+E7*E8 -> 9.3644521e+10 | F9: =F7+F7*F8 -> 9.6074892e+10 | G9: =G7+G7*G8 -> 9.8571476e+10 | H9: =H7+H7*H8 -> 1.0113615e+11 | I9: =I7+I7*I8 -> 1.0377086e+11 | J9: =J7+J7*J8 -> 1.0647759e+11 | K9: =K7+K7*K8 -> 1.0925839e+11 | ... DS9: =DS7+DS7*DS8 -> 2.3614065e+12

Sheet Экономический эффект
B2: Выручка
E3: 1 год | Q3: 2 год | AC3: 3 год | AO3: 4 год | BA3: 5 год | BM3: 6 год | BY3: 7 год | CK3: 8 год | CW3: 9 год | DI3: 10 год
B4: Показатель | C4: Ед. из. | D4: Сумма | E4: 1 | F4: 2 | G4: 3 | H4: 4 | I4: 5 | J4: 6 | K4: 7 | L4: 8 | M4: 9 | N4: 10 | O4: 11 | P4: 12 | Q4: 1 | R4: 2 | S4: 3 | T4: 4 | U4: 5 | V4: 6 | W4: 7 | X4: 8 | Y4: 9 | Z4: 10 | AA4: 11 | AB4: 12 | AC4: 1 | AD4: 2 | AE4: 3 | AF4: 4 | AG4: 5 | AH4: 6 | AI4: 7 | AJ4: 8 | AK4: 9 | AL4: 10 | AM4: 11 | AN4: 12 | AO4: 1 | AP4: 2 | AQ4: 3 | AR4: 4 | AS4: 5 | AT4: 6 | AU4: 7 | AV4: 8 | AW4: 9 | AX4: 10 | AY4: 11 | AZ4: 12 | BA4: 1 | BB4: 2 | BC4: 3 | BD4: 4 | BE4: 5 | BF4: 6 | BG4: 7 | BH4: 8 | BI4: 9 | BJ4: 10 | BK4: 11 | BL4: 12 | BM4: 1 | BN4: 2 | BO4: 3 | BP4: 4 | BQ4: 5 | BR4: 6 | BS4: 7 | BT4: 8 | BU4: 9 | BV4: 10 | BW4: 11 | BX4: 12 | BY4: 1 | BZ4: 2 | CA4: 3 | CB4: 4 | CC4: 5 | CD4: 6 | CE4: 7 | CF4: 8 | CG4: 9 | CH4: 10 | CI4: 11 | CJ4: 12 | CK4: 1 | CL4: 2 | CM4: 3 | CN4: 4 | CO4: 5 | CP4: 6 | CQ4: 7 | CR4: 8 | CS4: 9 | CT4: 10 | CU4: 11 | CV4: 12 | CW4: 1 | CX4: 2 | CY4: 3 | CZ4: 4 | DA4: 5 | DB4: 6 | DC4: 7 | DD4: 8 | DE4: 9 | DF4: 10 | DG4: 11 | DH4: 12 | DI4: 1 | DJ4: 2 | DK4: 3 | DL4: 4 | DM4: 5 | DN4: 6 | DO4: 7 | DP4: 8 | DQ4: 9 | DR4: 10 | DS4: 11 | DT4: 12
E5: 1 | F5: 2 | G5: 3 | H5: 4 | I5: 5 | J5: 6 | K5: 7 | L5: 8 | M5: 9 | N5: 10 | O5: 11 | P5: 12 | Q5: 13 | R5: 14 | S5: 15 | T5: 16 | U5: 17 | V5: 18 | W5: 19 | X5: 20 | Y5: 21 | Z5: 22 | AA5: 23 | AB5: 24 | AC5: 25 | AD5: 26 | AE5: 27 | AF5: 28 | AG5: 29 | AH5: 30 | AI5: 31 | AJ5: 32 | AK5: 33 | AL5: 34 | AM5: 35 | AN5: 36 | AO5: 1 | AP5: 2 | AQ5: 3 | AR5: 4 | AS5: 5 | AT5: 6 | AU5: 7 | AV5: 8 | AW5: 9 | AX5: 10 | AY5: 11 | AZ5: 12 | BA5: 13 | BB5: 14 | BC5: 15 | BD5: 16 | BE5: 17 | BF5: 18 | BG5: 19 | BH5: 20 | BI5: 21 | BJ5: 22 | BK5: 23 | BL5: 24 | BM5: 1 | BN5: 2 | BO5: 3 | BP5: 4 | BQ5: 5 | BR5: 6 | BS5: 7 | BT5: 8 | BU5: 9 | BV5: 10 | BW5: 11 | BX5: 12 | BY5: 13 | BZ5: 14 | CA5: 15 | CB5: 16 | CC5: 17 | CD5: 18 | CE5: 19 | CF5: 20 | CG5: 21 | CH5: 22 | CI5: 23 | CJ5: 24 | CK5: 25 | CL5: 26 | CM5: 27 | CN5: 28 | CO5: 29 | CP5: 30 | CQ5: 31 | CR5: 32 | CS5: 33 | CT5: 34 | CU5: 35 | CV5: 36 | CW5: 1 | CX5: 2 | CY5: 3 | CZ5: 4 | DA5: 5 | DB5: 6 | DC5: 7 | DD5: 8 | DE5: 9 | DF5: 10 | DG5: 11 | DH5: 12 | DI5: 13 | DJ5: 14 | DK5: 15 | DL5: 16 | DM5: 17 | DN5: 18 | DO5: 19 | DP5: 20 | DQ5: 21 | DR5: 22 | DS5: 23 | DT5: 24
B6: Экономичесский эффект от роста выручки | D6: =D7 -> 1.1718224e+10 | E6: =E7 -> 0 | F6: =F7 -> 0 | G6: =G7 -> 0 | H6: =H7 -> 0 | I6: =I7 -> 0 | J6: =J7 -> 0 | K6: =K7 -> 0 | ... DT6: =DT7 -> 1.7617054e+08
B7: Экономический эффект: повышение производительности | C7: чел. | D7: =SUM(E7:DT7) -> 1.1718224e+10 | E7: 0 | F7: 0 | G7: 0 | H7: 0 | I7: 0 | J7: 0 | K7: 0 | L7: 0 | M7: 0 | N7: 0 | O7: 0 | P7: 0 | Q7: 60750000 | R7: =Q7*1.01 -> 61357500 | S7: =R7*1.01 -> 61971075 | T7: =S7*1.01 -> 62590786 | U7: =T7*1.01 -> 63216694 | V7: =U7*1.01 -> 63848861 | W7: =V7*1.01 -> 64487349 | X7: =W7*1.01 -> 65132223 | Y7: =X7*1.01 -> 65783545 | ... DT7: =DS7*1.01 -> 1.7617054e+08
B8: Экономический эффект от снижения затрат | C8: руб. | D8: =SUM(D9,D12) -> 9.2588438e+09 | E8: =SUM(E9,E12) -> 0 | F8: =SUM(F9,F12) -> 0 | G8: =SUM(G9,G12) -> 0 | H8: =SUM(H9,H12) -> 0 | I8: =SUM(I9,I12) -> 0 | J8: =SUM(J9,J12) -> 0 | K8: =SUM(K9,K12) -> 0 | ... DT8: =SUM(DT9,DT12) -> 1.3919647e+08
B9: Снижение текучести на 1 п.п.: | C9: руб. | D9: =SUM(E9:DT9) -> 1.5913638e+09 | E9: 0 | F9: =E9*1.01 -> 0 | G9: =F9*1.01 -> 0 | H9: =G9*1.01 -> 0 | I9: =H9*1.01 -> 0 | J9: =I9*1.01 -> 0 | K9: =J9*1.01 -> 0 | L9: =K9*1.01 -> 0 | M9: =L9*1.01 -> 0 | ... P9: =O9*1.01 -> 0 | Q9: 8250000 | R9: =Q9*1.01 -> 8332500 | S9: =R9*1.01 -> 8415825 | T9: =S9*1.01 -> 8499983.2 | U9: =T9*1.01 -> 8584983.1 | V9: =U9*1.01 -> 8670832.9 | W9: =V9*1.01 -> 8757541.2 | X9: =W9*1.01 -> 8845116.7 | Y9: =X9*1.01 -> 8933567.8 | ... DT9: =DS9*1.01 -> 23924394
B10: Затраты на подбор и обучение персонала до | C10: руб. | D10: =SUM(E10:DT10) -> 9720000000 | E10: 0 | F10: 0 | G10: 0 | H10: 0 | I10: 0 | J10: 0 | K10: 0 | L10: 0 | M10: 0 | N10: 0 | O10: 0 | P10: 0 | Q10: 90000000 | R10: 90000000 | S10: 90000000 | T10: 90000000 | U10: 90000000 | V10: 90000000 | W10: 90000000 | X10: 90000000 | Y10: 90000000 | Z10: 90000000 | AA10: 90000000 | AB10: 90000000 | AC10: 90000000 | AD10: 90000000 | AE10: 90000000 | AF10: 90000000 | AG10: 90000000 | AH10: 90000000 | AI10: 90000000 | AJ10: 90000000 | AK10: 90000000 | AL10: 90000000 | AM10: 90000000 | AN10: 90000000 | AO10: 90000000 | AP10: 90000000 | AQ10: 90000000 | AR10: 90000000 | AS10: 90000000 | AT10: 90000000 | AU10: 90000000 | AV10: 90000000 | AW10: 90000000 | AX10: 90000000 | AY10: 90000000 | AZ10: 90000000 | BA10: 90000000 | BB10: 90000000 | BC10: 90000000 | BD10: 90000000 | BE10: 90000000 | BF10: 90000000 | BG10: 90000000 | BH10: 90000000 | BI10: 90000000 | BJ10: 90000000 | BK10: 90000000 | BL10: 90000000 | BM10: 90000000 | BN10: 90000000 | BO10: 90000000 | BP10: 90000000 | BQ10: 90000000 | BR10: 90000000 | BS10: 90000000 | BT10: 90000000 | BU10: 90000000 | BV10: 90000000 | BW10: 90000000 | BX10: 90000000 | BY10: 90000000 | BZ10: 90000000 | CA10: 90000000 | CB10: 90000000 | CC10: 90000000 | CD10: 90000000 | CE10: 90000000 | CF10: 90000000 | CG10: 90000000 | CH10: 90000000 | CI10: 90000000 | CJ10: 90000000 | CK10: 90000000 | CL10: 90000000 | CM10: 90000000 | CN10: 90000000 | CO10: 90000000 | CP10: 90000000 | CQ10: 90000000 | CR10: 90000000 | CS10: 90000000 | CT10: 90000000 | CU10: 90000000 | CV10: 90000000 | CW10: 90000000 | CX10: 90000000 | CY10: 90000000 | CZ10: 90000000 | DA10: 90000000 | DB10: 90000000 | DC10: 90000000 | DD10: 90000000 | DE10: 90000000 | DF10: 90000000 | DG10: 90000000 | DH10: 90000000 | DI10: 90000000 | DJ10: 90000000 | DK10: 90000000 | DL10: 90000000 | DM10: 90000000 | DN10: 90000000 | DO10: 90000000 | DP10: 90000000 | DQ10: 90000000 | DR10: 90000000 | DS10: 90000000 | DT10: 90000000
B11: Затраты на подбор и обучение персонала после | C11: руб. | D11: =SUM(E11:DT11) -> 8.1286362e+09 | E11: 0 | F11: 0 | G11: 0 | H11: 0 | I11: 0 | J11: 0 | K11: 0 | L11: 0 | M11: 0 | N11: 0 | O11: 0 | P11: 0 | Q11: =Q10-Q9 -> 81750000 | R11: =R10-R9 -> 81667500 | S11: =S10-S9 -> 81584175 | T11: =T10-T9 -> 81500017 | U11: =U10-U9 -> 81415017 | V11: =V10-V9 -> 81329167 | W11: =W10-W9 -> 81242459 | X11: =X10-X9 -> 81154883 | ... DT11: =DT10-DT9 -> 66075606
B12: Оптимизация адаптации и подбора персонала, после | C12: руб. | D12: =SUM(E12:DT12) -> 7.66748e+09 | E12: 0 | F12: 0 | G12: 0 | H12: 0 | I12: 0 | J12: 0 | K12: 0 | L12: 0 | M12: 0 | N12: 0 | O12: 0 | P12: 0 | Q12: 39750000 | R12: =Q12*1.01 -> 40147500 | S12: =R12*1.01 -> 40548975 | T12: =S12*1.01 -> 40954465 | U12: =T12*1.01 -> 41364009 | V12: =U12*1.01 -> 41777649 | W12: =V12*1.01 -> 42195426 | X12: =W12*1.01 -> 42617380 | Y12: =X12*1.01 -> 43043554 | ... DT12: =DS12*1.01 -> 1.1527208e+08
B13: Общий экономический эффект | C13: руб. | D13: =SUM(E13:DT13) -> 2.0977068e+10 | E13: =SUM(E7:E12) -> 0 | F13: =SUM(F7:F12) -> 0 | G13: =SUM(G7:G12) -> 0 | H13: =SUM(H7:H12) -> 0 | I13: =SUM(I7:I12) -> 0 | J13: =SUM(J7:J12) -> 0 | K13: =SUM(K7:K12) -> 0 | L13: =SUM(L7:L12) -> 0 | ... P13: =SUM(P7:P12) -> 0 | Q13: =SUM(Q7+Q9+Q12) -> 108750000 | R13: =SUM(R7+R9+R12) -> 109837500 | S13: =SUM(S7+S9+S12) -> 110935875 | T13: =SUM(T7+T9+T12) -> 1.1204523e+08 | U13: =SUM(U7+U9+U12) -> 1.1316569e+08 | V13: =SUM(V7+V9+V12) -> 1.1429734e+08 | W13: =SUM(W7+W9+W12) -> 1.1544032e+08 | X13: =SUM(X7+X9+X12) -> 1.1659472e+08 | ... DT13: =SUM(DT7+DT9+DT12) -> 3.1536701e+08
B14: Коэффициент инфляции | C14: % | D14: ='Исходные данные'!E40 -> 0.145 | E14: ='Исходные данные'!F40 -> 1.0113476 | F14: ='Исходные данные'!G40 -> 1.022824 | G14: ='Исходные данные'!H40 -> 1.0344306 | H14: ='Исходные данные'!I40 -> 1.046169 | I14: ='Исходные данные'!J40 -> 1.0580405 | J14: ='Исходные данные'!K40 -> 1.0700467 | K14: ='Исходные данные'!L40 -> 1.0821892 | ... DT14: ='Исходные данные'!DU40 -> 3.8730657
B15: Экономический эффект с учетом инфляции | C15: руб. | D15: =SUM(E15:DT15) -> 7.324461e+10 | E15: =E13*'Исходные данные'!F40 -> 0 | F15: =F13*'Исходные данные'!G40 -> 0 | G15: =G13*'Исходные данные'!H40 -> 0 | H15: =H13*'Исходные данные'!I40 -> 0 | I15: =I13*'Исходные данные'!J40 -> 0 | J15: =J13*'Исходные данные'!K40 -> 0 | K15: =K13*'Исходные данные'!L40 -> 0 | L15: =L13*'Исходные данные'!M40 -> 0 | ... P15: =P13*'Исходные данные'!Q40 -> 0 | Q15: =Q13+Q13*Q14 -> 2.3468174e+08 | R15: =R13+R13*R14 -> 2.3847187e+08 | S15: =S13+S13*S14 -> 2.4233088e+08 | T15: =T13+T13*T14 -> 2.4626012e+08 | U15: =U13+U13*U14 -> 2.5026098e+08 | V15: =V13+V13*V14 -> 2.5433485e+08 | W15: =W13+W13*W14 -> 2.5848318e+08 | X15: =X13+X13*X14 -> 2.6270744e+08 | ... DT15: =DT13+DT13*DT14 -> 1.5368042e+09
B18: Экономический эффект достигается за счет следующих результатов: - растет выручка за счет роста производительности труда; за счет снижение текучести персонала сокращаются расходы на подбор, отбор и адаптацию персонала, увеличивается производительность за счет сохранения преемственности персонала и человеческого капитала; за счет снижения текусти сокращаются расходы на обучение персонала. На рост выручки влияет: увеличение производительности, выскоая квалификация кадров, сокращение простоев. На затраты влияет: текучестсь кадров, снижение человеческого капитала в организации, снижение опыта работы сотрудников в организации, необходимость дообучения и адаптации.

Sheet Капитальные затраты до
A1: Капитальные затраты
D2: 1 год | P2: 2 год | AB2: 3 год | AN2: 4 год | AZ2: 5 год | BL2: 6 год | BX2: 7 год | CJ2: 8 год | CV2: 9 год | DH2: 10 год
A3: Наименование затрат | B3: Ед. из. | C3: Итого: | D3: 1 | E3: 2 | F3: 3 | G3: 4 | H3: 5 | I3: 6 | J3: 7 | K3: 8 | L3: 9 | M3: 10 | N3: 11 | O3: 12 | P3: 1 | Q3: 2 | R3: 3 | S3: 4 | T3: 5 | U3: 6 | V3: 7 | W3: 8 | X3: 9 | Y3: 10 | Z3: 11 | AA3: 12 | AB3: 1 | AC3: 2 | AD3: 3 | AE3: 4 | AF3: 5 | AG3: 6 | AH3: 7 | AI3: 8 | AJ3: 9 | AK3: 10 | AL3: 11 | AM3: 12 | AN3: 1 | AO3: 2 | AP3: 3 | AQ3: 4 | AR3: 5 | AS3: 6 | AT3: 7 | AU3: 8 | AV3: 9 | AW3: 10 | AX3: 11 | AY3: 12 | AZ3: 1 | BA3: 2 | BB3: 3 | BC3: 4 | BD3: 5 | BE3: 6 | BF3: 7 | BG3: 8 | BH3: 9 | BI3: 10 | BJ3: 11 | BK3: 12 | BL3: 1 | BM3: 2 | BN3: 3 | BO3: 4 | BP3: 5 | BQ3: 6 | BR3: 7 | BS3: 8 | BT3: 9 | BU3: 10 | BV3: 11 | BW3: 12 | BX3: 1 | BY3: 2 | BZ3: 3 | CA3: 4 | CB3: 5 | CC3: 6 | CD3: 7 | CE3: 8 | CF3: 9 | CG3: 10 | CH3: 11 | CI3: 12 | CJ3: 1 | CK3: 2 | CL3: 3 | CM3: 4 | CN3: 5 | CO3: 6 | CP3: 7 | CQ3: 8 | CR3: 9 | CS3: 10 | CT3: 11 | CU3: 12 | CV3: 1 | CW3: 2 | CX3: 3 | CY3: 4 | CZ3: 5 | DA3: 6 | DB3: 7 | DC3: 8 | DD3: 9 | DE3: 10 | DF3: 11 | DG3: 12 | DH3: 1 | DI3: 2 | DJ3: 3 | DK3: 4 | DL3: 5 | DM3: 6 | DN3: 7 | DO3: 8 | DP3: 9 | DQ3: 10 | DR3: 11 | DS3: 12
D4: 1 | E4: 2 | F4: 3 | G4: 4 | H4: 5 | I4: 6 | J4: 7 | K4: 8 | L4: 9 | M4: 10 | N4: 11 | O4: 12 | P4: 13 | Q4: 14 | R4: 15 | S4: 16 | T4: 17 | U4: 18 | V4: 19 | W4: 20 | X4: 21 | Y4: 22 | Z4: 23 | AA4: 24 | AB4: 25 | AC4: 26 | AD4: 27 | AE4: 28 | AF4: 29 | AG4: 30 | AH4: 31 | AI4: 32 | AJ4: 33 | AK4: 34 | AL4: 35 | AM4: 36 | AN4: 1 | AO4: 2 | AP4: 3 | AQ4: 4 | AR4: 5 | AS4: 6 | AT4: 7 | AU4: 8 | AV4: 9 | AW4: 10 | AX4: 11 | AY4: 12 | AZ4: 13 | BA4: 14 | BB4: 15 | BC4: 16 | BD4: 17 | BE4: 18 | BF4: 19 | BG4: 20 | BH4: 21 | BI4: 22 | BJ4: 23 | BK4: 24 | BL4: 1 | BM4: 2 | BN4: 3 | BO4: 4 | BP4: 5 | BQ4: 6 | BR4: 7 | BS4: 8 | BT4: 9 | BU4: 10 | BV4: 11 | BW4: 12 | BX4: 13 | BY4: 14 | BZ4: 15 | CA4: 16 | CB4: 17 | CC4: 18 | CD4: 19 | CE4: 20 | CF4: 21 | CG4: 22 | CH4: 23 | CI4: 24 | CJ4: 25 | CK4: 26 | CL4: 27 | CM4: 28 | CN4: 29 | CO4: 30 | CP4: 31 | CQ4: 32 | CR4: 33 | CS4: 34 | CT4: 35 | CU4: 36 | CV4: 1 | CW4: 2 | CX4: 3 | CY4: 4 | CZ4: 5 | DA4: 6 | DB4: 7 | DC4: 8 | DD4: 9 | DE4: 10 | DF4: 11 | DG4: 12 | DH4: 13 | DI4: 14 | DJ4: 15 | DK4: 16 | DL4: 17 | DM4: 18 | DN4: 19 | DO4: 20 | DP4: 21 | DQ4: 22 | DR4: 23 | DS4: 24
A5: Предпроектное обследование и проектирование решения | B5: руб. | C5: =SUM(D5:DS5) -> 0 | D5: 0 | E5: 0 | F5: 0 | G5: 0 | H5: 0 | I5: 0 | J5: 0 | K5: 0 | L5: 0 | M5: 0 | N5: 0 | O5: 0 | P5: 0 | Q5: 0 | R5: 0 | S5: 0 | T5: 0 | U5: 0 | V5: 0 | W5: 0 | X5: 0 | Y5: 0 | Z5: 0 | AA5: 0 | AB5: 0 | AC5: 0 | AD5: 0 | AE5: 0 | AF5: 0 | AG5: 0 | AH5: 0 | AI5: 0 | AJ5: 0 | AK5: 0 | AL5: 0 | AM5: 0 | AN5: 0 | AO5: 0 | AP5: 0 | AQ5: 0 | AR5: 0 | AS5: 0 | AT5: 0 | AU5: 0 | AV5: 0 | AW5: 0 | AX5: 0 | AY5: 0 | AZ5: 0 | BA5: 0 | BB5: 0 | BC5: 0 | BD5: 0 | BE5: 0 | BF5: 0 | BG5: 0 | BH5: 0 | BI5: 0 | BJ5: 0 | BK5: 0 | BL5: 0 | BM5: 0 | BN5: 0 | BO5: 0 | BP5: 0 | BQ5: 0 | BR5: 0 | BS5: 0 | BT5: 0 | BU5: 0 | BV5: 0 | BW5: 0 | BX5: 0 | BY5: 0 | BZ5: 0 | CA5: 0 | CB5: 0 | CC5: 0 | CD5: 0 | CE5: 0 | CF5: 0 | CG5: 0 | CH5: 0 | CI5: 0 | CJ5: 0 | CK5: 0 | CL5: 0 | CM5: 0 | CN5: 0 | CO5: 0 | CP5: 0 | CQ5: 0 | CR5: 0 | CS5: 0 | CT5: 0 | CU5: 0 | CV5: 0 | CW5: 0 | CX5: 0 | CY5: 0 | CZ5: 0 | DA5: 0 | DB5: 0 | DC5: 0 | DD5: 0 | DE5: 0 | DF5: 0 | DG5: 0 | DH5: 0 | DI5: 0 | DJ5: 0 | DK5: 0 | DL5: 0 | DM5: 0 | DN5: 0 | DO5: 0 | DP5: 0 | DQ5: 0 | DR5: 0 | DS5: 0
A6: Разработка ядра HRM-модуля и всех модулей анализа/рекомендаций/карьеры/витрины/ETL/интеграций/ИБ/тестирования/пилота/документации/обучения/внедрения в эксплуатацию | B6: руб. | C6: =SUM(D6:DS6) -> 0 | D6: 0 | E6: 0 | F6: 0 | G6: 0 | H6: 0 | I6: 0 | J6: 0 | K6: 0 | L6: 0 | M6: 0 | N6: 0 | O6: 0 | P6: 0 | Q6: 0 | R6: 0 | S6: 0 | T6: 0 | U6: 0 | V6: 0 | W6: 0 | X6: 0 | Y6: 0 | Z6: 0 | AA6: 0 | AB6: 0 | AC6: 0 | AD6: 0 | AE6: 0 | AF6: 0 | AG6: 0 | AH6: 0 | AI6: 0 | AJ6: 0 | AK6: 0 | AL6: 0 | AM6: 0 | AN6: 0 | AO6: 0 | AP6: 0 | AQ6: 0 | AR6: 0 | AS6: 0 | AT6: 0 | AU6: 0 | AV6: 0 | AW6: 0 | AX6: 0 | AY6: 0 | AZ6: 0 | BA6: 0 | BB6: 0 | BC6: 0 | BD6: 0 | BE6: 0 | BF6: 0 | BG6: 0 | BH6: 0 | BI6: 0 | BJ6: 0 | BK6: 0 | BL6: 0 | BM6: 0 | BN6: 0 | BO6: 0 | BP6: 0 | BQ6: 0 | BR6: 0 | BS6: 0 | BT6: 0 | BU6: 0 | BV6: 0 | BW6: 0 | BX6: 0 | BY6: 0 | BZ6: 0 | CA6: 0 | CB6: 0 | CC6: 0 | CD6: 0 | CE6: 0 | CF6: 0 | CG6: 0 | CH6: 0 | CI6: 0 | CJ6: 0 | CK6: 0 | CL6: 0 | CM6: 0 | CN6: 0 | CO6: 0 | CP6: 0 | CQ6: 0 | CR6: 0 | CS6: 0 | CT6: 0 | CU6: 0 | CV6: 0 | CW6: 0 | CX6: 0 | CY6: 0 | CZ6: 0 | DA6: 0 | DB6: 0 | DC6: 0 | DD6: 0 | DE6: 0 | DF6: 0 | DG6: 0 | DH6: 0 | DI6: 0 | DJ6: 0 | DK6: 0 | DL6: 0 | DM6: 0 | DN6: 0 | DO6: 0 | DP6: 0 | DQ6: 0 | DR6: 0 | DS6: 0
A7: Приобретение оборудования (серверы, СХД, сеть, рабочие станции, ИБ, резервирование и т.д.) — см. ниже таблицы оборудования | B7: руб. | C7: =SUM(D7:DS7) -> 0 | D7: 0 | E7: 0 | F7: 0 | G7: 0 | H7: 0 | I7: 0 | J7: 0 | K7: 0 | L7: 0 | M7: 0 | N7: 0 | O7: 0 | P7: 0 | Q7: 0 | R7: 0 | S7: 0 | T7: 0 | U7: 0 | V7: 0 | W7: 0 | X7: 0 | Y7: 0 | Z7: 0 | AA7: 0 | AB7: 0 | AC7: 0 | AD7: 0 | AE7: 0 | AF7: 0 | AG7: 0 | AH7: 0 | AI7: 0 | AJ7: 0 | AK7: 0 | AL7: 0 | AM7: 0 | AN7: 0 | AO7: 0 | AP7: 0 | AQ7: 0 | AR7: 0 | AS7: 0 | AT7: 0 | AU7: 0 | AV7: 0 | AW7: 0 | AX7: 0 | AY7: 0 | AZ7: 0 | BA7: 0 | BB7: 0 | BC7: 0 | BD7: 0 | BE7: 0 | BF7: 0 | BG7: 0 | BH7: 0 | BI7: 0 | BJ7: 0 | BK7: 0 | BL7: 0 | BM7: 0 | BN7: 0 | BO7: 0 | BP7: 0 | BQ7: 0 | BR7: 0 | BS7: 0 | BT7: 0 | BU7: 0 | BV7: 0 | BW7: 0 | BX7: 0 | BY7: 0 | BZ7: 0 | CA7: 0 | CB7: 0 | CC7: 0 | CD7: 0 | CE7: 0 | CF7: 0 | CG7: 0 | CH7: 0 | CI7: 0 | CJ7: 0 | CK7: 0 | CL7: 0 | CM7: 0 | CN7: 0 | CO7: 0 | CP7: 0 | CQ7: 0 | CR7: 0 | CS7: 0 | CT7: 0 | CU7: 0 | CV7: 0 | CW7: 0 | CX7: 0 | CY7: 0 | CZ7: 0 | DA7: 0 | DB7: 0 | DC7: 0 | DD7: 0 | DE7: 0 | DF7: 0 | DG7: 0 | DH7: 0 | DI7: 0 | DJ7: 0 | DK7: 0 | DL7: 0 | DM7: 0 | DN7: 0 | DO7: 0 | DP7: 0 | DQ7: 0 | DR7: 0 | DS7: 0
A8: Итого: | C8: =SUM(C5:C7) -> 0 | D8: =SUM(D5:D7) -> 0 | E8: =SUM(E5:E7) -> 0 | F8: =SUM(F5:F7) -> 0 | G8: =SUM(G5:G7) -> 0 | H8: =SUM(H5:H7) -> 0 | I8: =SUM(I5:I7) -> 0 | J8: =SUM(J5:J7) -> 0 | ... DS8: =SUM(DS5:DS7) -> 0
A9: Серверы вычислительного контура для ML/NLP-моделей (GPU/CPU) | B9: руб. | C9: 43000000 | D9: 0 | E9: 0 | F9: 0 | G9: 0 | H9: 0 | I9: 0 | J9: 0 | K9: 0 | L9: 0 | M9: 0 | N9: 0 | O9: 0 | P9: 0 | Q9: 0 | R9: 0 | S9: 0 | T9: 0 | U9: 0 | V9: 0 | W9: 0 | X9: 0 | Y9: 0 | Z9: 0 | AA9: 0 | AB9: 0 | AC9: 0 | AD9: 0 | AE9: 0 | AF9: 0 | AG9: 0 | AH9: 0 | AI9: 0 | AJ9: 0 | AK9: 0 | AL9: 0 | AM9: 0 | AN9: 0 | AO9: 0 | AP9: 0 | AQ9: 0 | AR9: 0 | AS9: 0 | AT9: 0 | AU9: 0 | AV9: 0 | AW9: 0 | AX9: 0 | AY9: 0 | AZ9: 0 | BA9: 0 | BB9: 0 | BC9: 0 | BD9: 0 | BE9: 0 | BF9: 0 | BG9: 0 | BH9: 0 | BI9: 0 | BJ9: 0 | BK9: 0 | BL9: 0 | BM9: 0 | BN9: 0 | BO9: 0 | BP9: 0 | BQ9: 0 | BR9: 0 | BS9: 0 | BT9: 0 | BU9: 0 | BV9: 0 | BW9: 0 | BX9: 0 | BY9: 0 | BZ9: 0 | CA9: 0 | CB9: 0 | CC9: 0 | CD9: 0 | CE9: 0 | CF9: 0 | CG9: 0 | CH9: 0 | CI9: 0 | CJ9: 0 | CK9: 0 | CL9: 0 | CM9: 0 | CN9: 0 | CO9: 0 | CP9: 0 | CQ9: 0 | CR9: 0 | CS9: 0 | CT9: 0 | CU9: 0 | CV9: 0 | CW9: 0 | CX9: 0 | CY9: 0 | CZ9: 0 | DA9: 0 | DB9: 0 | DC9: 0 | DD9: 0 | DE9: 0 | DF9: 0 | DG9: 0 | DH9: 0 | DI9: 0 | DJ9: 0 | DK9: 0 | DL9: 0 | DM9: 0 | DN9: 0 | DO9: 0 | DP9: 0 | DQ9: 0 | DR9: 0 | DS9: 0
A10: Серверы тестового и промышленного контуров (CPU) | B10: руб. | C10: 3000000 | D10: 0 | E10: 0 | F10: 0 | G10: 0 | H10: 0 | I10: 0 | J10: 0 | K10: 0 | L10: 0 | M10: 0 | N10: 0 | O10: 0 | P10: 0 | Q10: 0 | R10: 0 | S10: 0 | T10: 0 | U10: 0 | V10: 0 | W10: 0 | X10: 0 | Y10: 0 | Z10: 0 | AA10: 0 | AB10: 0 | AC10: 0 | AD10: 0 | AE10: 0 | AF10: 0 | AG10: 0 | AH10: 0 | AI10: 0 | AJ10: 0 | AK10: 0 | AL10: 0 | AM10: 0 | AN10: 0 | AO10: 0 | AP10: 0 | AQ10: 0 | AR10: 0 | AS10: 0 | AT10: 0 | AU10: 0 | AV10: 0 | AW10: 0 | AX10: 0 | AY10: 0 | AZ10: 0 | BA10: 0 | BB10: 0 | BC10: 0 | BD10: 0 | BE10: 0 | BF10: 0 | BG10: 0 | BH10: 0 | BI10: 0 | BJ10: 0 | BK10: 0 | BL10: 0 | BM10: 0 | BN10: 0 | BO10: 0 | BP10: 0 | BQ10: 0 | BR10: 0 | BS10: 0 | BT10: 0 | BU10: 0 | BV10: 0 | BW10: 0 | BX10: 0 | BY10: 0 | BZ10: 0 | CA10: 0 | CB10: 0 | CC10: 0 | CD10: 0 | CE10: 0 | CF10: 0 | CG10: 0 | CH10: 0 | CI10: 0 | CJ10: 0 | CK10: 0 | CL10: 0 | CM10: 0 | CN10: 0 | CO10: 0 | CP10: 0 | CQ10: 0 | CR10: 0 | CS10: 0 | CT10: 0 | CU10: 0 | CV10: 0 | CW10: 0 | CX10: 0 | CY10: 0 | CZ10: 0 | DA10: 0 | DB10: 0 | DC10: 0 | DD10: 0 | DE10: 0 | DF10: 0 | DG10: 0 | DH10: 0 | DI10: 0 | DJ10: 0 | DK10: 0 | DL10: 0 | DM10: 0 | DN10: 0 | DO10: 0 | DP10: 0 | DQ10: 0 | DR10: 0 | DS10: 0
A11: СХД для исторических данных и моделей (NAS/SAN) | B11: руб. | C11: 6000000 | D11: 0 | E11: 0 | F11: 0 | G11: 0 | H11: 0 | I11: 0 | J11: 0 | K11: 0 | L11: 0 | M11: 0 | N11: 0 | O11: 0 | P11: 0 | Q11: 0 | R11: 0 | S11: 0 | T11: 0 | U11: 0 | V11: 0 | W11: 0 | X11: 0 | Y11: 0 | Z11: 0 | AA11: 0 | AB11: 0 | AC11: 0 | AD11: 0 | AE11: 0 | AF11: 0 | AG11: 0 | AH11: 0 | AI11: 0 | AJ11: 0 | AK11: 0 | AL11: 0 | AM11: 0 | AN11: 0 | AO11: 0 | AP11: 0 | AQ11: 0 | AR11: 0 | AS11: 0 | AT11: 0 | AU11: 0 | AV11: 0 | AW11: 0 | AX11: 0 | AY11: 0 | AZ11: 0 | BA11: 0 | BB11: 0 | BC11: 0 | BD11: 0 | BE11: 0 | BF11: 0 | BG11: 0 | BH11: 0 | BI11: 0 | BJ11: 0 | BK11: 0 | BL11: 0 | BM11: 0 | BN11: 0 | BO11: 0 | BP11: 0 | BQ11: 0 | BR11: 0 | BS11: 0 | BT11: 0 | BU11: 0 | BV11: 0 | BW11: 0 | BX11: 0 | BY11: 0 | BZ11: 0 | CA11: 0 | CB11: 0 | CC11: 0 | CD11: 0 | CE11: 0 | CF11: 0 | CG11: 0 | CH11: 0 | CI11: 0 | CJ11: 0 | CK11: 0 | CL11: 0 | CM11: 0 | CN11: 0 | CO11: 0 | CP11: 0 | CQ11: 0 | CR11: 0 | CS11: 0 | CT11: 0 | CU11: 0 | CV11: 0 | CW11: 0 | CX11: 0 | CY11: 0 | CZ11: 0 | DA11: 0 | DB11: 0 | DC11: 0 | DD11: 0 | DE11: 0 | DF11: 0 | DG11: 0 | DH11: 0 | DI11: 0 | DJ11: 0 | DK11: 0 | DL11: 0 | DM11: 0 | DN11: 0 | DO11: 0 | DP11: 0 | DQ11: 0 | DR11: 0 | DS11: 0
A12: Сетевое оборудование ядра проекта (коммутаторы, маршрутизаторы) | B12: руб. | C12: 2100000 | D12: 0 | E12: 0 | F12: 0 | G12: 0 | H12: 0 | I12: 0 | J12: 0 | K12: 0 | L12: 0 | M12: 0 | N12: 0 | O12: 0 | P12: 0 | Q12: 0 | R12: 0 | S12: 0 | T12: 0 | U12: 0 | V12: 0 | W12: 0 | X12: 0 | Y12: 0 | Z12: 0 | AA12: 0 | AB12: 0 | AC12: 0 | AD12: 0 | AE12: 0 | AF12: 0 | AG12: 0 | AH12: 0 | AI12: 0 | AJ12: 0 | AK12: 0 | AL12: 0 | AM12: 0 | AN12: 0 | AO12: 0 | AP12: 0 | AQ12: 0 | AR12: 0 | AS12: 0 | AT12: 0 | AU12: 0 | AV12: 0 | AW12: 0 | AX12: 0 | AY12: 0 | AZ12: 0 | BA12: 0 | BB12: 0 | BC12: 0 | BD12: 0 | BE12: 0 | BF12: 0 | BG12: 0 | BH12: 0 | BI12: 0 | BJ12: 0 | BK12: 0 | BL12: 0 | BM12: 0 | BN12: 0 | BO12: 0 | BP12: 0 | BQ12: 0 | BR12: 0 | BS12: 0 | BT12: 0 | BU12: 0 | BV12: 0 | BW12: 0 | BX12: 0 | BY12: 0 | BZ12: 0 | CA12: 0 | CB12: 0 | CC12: 0 | CD12: 0 | CE12: 0 | CF12: 0 | CG12: 0 | CH12: 0 | CI12: 0 | CJ12: 0 | CK12: 0 | CL12: 0 | CM12: 0 | CN12: 0 | CO12: 0 | CP12: 0 | CQ12: 0 | CR12: 0 | CS12: 0 | CT12: 0 | CU12: 0 | CV12: 0 | CW12: 0 | CX12: 0 | CY12: 0 | CZ12: 0 | DA12: 0 | DB12: 0 | DC12: 0 | DD12: 0 | DE12: 0 | DF12: 0 | DG12: 0 | DH12: 0 | DI12: 0 | DJ12: 0 | DK12: 0 | DL12: 0 | DM12: 0 | DN12: 0 | DO12: 0 | DP12: 0 | DQ12: 0 | DR12: 0 | DS12: 0
A13: Рабочие станции разработчиков/аналитиков (high-end) | B13: руб. | C13: 3000000 | D13: 0 | E13: 0 | F13: 0 | G13: 0 | H13: 0 | I13: 0 | J13: 0 | K13: 0 | L13: 0 | M13: 0 | N13: 0 | O13: 0 | P13: 0 | Q13: 0 | R13: 0 | S13: 0 | T13: 0 | U13: 0 | V13: 0 | W13: 0 | X13: 0 | Y13: 0 | Z13: 0 | AA13: 0 | AB13: 0 | AC13: 0 | AD13: 0 | AE13: 0 | AF13: 0 | AG13: 0 | AH13: 0 | AI13: 0 | AJ13: 0 | AK13: 0 | AL13: 0 | AM13: 0 | AN13: 0 | AO13: 0 | AP13: 0 | AQ13: 0 | AR13: 0 | AS13: 0 | AT13: 0 | AU13: 0 | AV13: 0 | AW13: 0 | AX13: 0 | AY13: 0 | AZ13: 0 | BA13: 0 | BB13: 0 | BC13: 0 | BD13: 0 | BE13: 0 | BF13: 0 | BG13: 0 | BH13: 0 | BI13: 0 | BJ13: 0 | BK13: 0 | BL13: 0 | BM13: 0 | BN13: 0 | BO13: 0 | BP13: 0 | BQ13: 0 | BR13: 0 | BS13: 0 | BT13: 0 | BU13: 0 | BV13: 0 | BW13: 0 | BX13: 0 | BY13: 0 | BZ13: 0 | CA13: 0 | CB13: 0 | CC13: 0 | CD13: 0 | CE13: 0 | CF13: 0 | CG13: 0 | CH13: 0 | CI13: 0 | CJ13: 0 | CK13: 0 | CL13: 0 | CM13: 0 | CN13: 0 | CO13: 0 | CP13: 0 | CQ13: 0 | CR13: 0 | CS13: 0 | CT13: 0 | CU13: 0 | CV13: 0 | CW13: 0 | CX13: 0 | CY13: 0 | CZ13: 0 | DA13: 0 | DB13: 0 | DC13: 0 | DD13: 0 | DE13: 0 | DF13: 0 | DG13: 0 | DH13: 0 | DI13: 0 | DJ13: 0 | DK13: 0 | DL13: 0 | DM13: 0 | DN13: 0 | DO13: 0 | DP13: 0 | DQ13: 0 | DR13: 0 | DS13: 0
A14: Средства ИБ: межсетевые экраны, DLP, SIEM, HSM и др. | B14: руб. | C14: 2800000 | D14: 0 | E14: 0 | F14: 0 | G14: 0 | H14: 0 | I14: 0 | J14: 0 | K14: 0 | L14: 0 | M14: 0 | N14: 0 | O14: 0 | P14: 0 | Q14: 0 | R14: 0 | S14: 0 | T14: 0 | U14: 0 | V14: 0 | W14: 0 | X14: 0 | Y14: 0 | Z14: 0 | AA14: 0 | AB14: 0 | AC14: 0 | AD14: 0 | AE14: 0 | AF14: 0 | AG14: 0 | AH14: 0 | AI14: 0 | AJ14: 0 | AK14: 0 | AL14: 0 | AM14: 0 | AN14: 0 | AO14: 0 | AP14: 0 | AQ14: 0 | AR14: 0 | AS14: 0 | AT14: 0 | AU14: 0 | AV14: 0 | AW14: 0 | AX14: 0 | AY14: 0 | AZ14: 0 | BA14: 0 | BB14: 0 | BC14: 0 | BD14: 0 | BE14: 0 | BF14: 0 | BG14: 0 | BH14: 0 | BI14: 0 | BJ14: 0 | BK14: 0 | BL14: 0 | BM14: 0 | BN14: 0 | BO14: 0 | BP14: 0 | BQ14: 0 | BR14: 0 | BS14: 0 | BT14: 0 | BU14: 0 | BV14: 0 | BW14: 0 | BX14: 0 | BY14: 0 | BZ14: 0 | CA14: 0 | CB14: 0 | CC14: 0 | CD14: 0 | CE14: 0 | CF14: 0 | CG14: 0 | CH14: 0 | CI14: 0 | CJ14: 0 | CK14: 0 | CL14: 0 | CM14: 0 | CN14: 0 | CO14: 0 | CP14: 0 | CQ14: 0 | CR14: 0 | CS14: 0 | CT14: 0 | CU14: 0 | CV14: 0 | CW14: 0 | CX14: 0 | CY14: 0 | CZ14: 0 | DA14: 0 | DB14: 0 | DC14: 0 | DD14: 0 | DE14: 0 | DF14: 0 | DG14: 0 | DH14: 0 | DI14: 0 | DJ14: 0 | DK14: 0 | DL14: 0 | DM14: 0 | DN14: 0 | DO14: 0 | DP14: 0 | DQ14: 0 | DR14: 0 | DS14: 0
A15: Резервное копирование и отказоустойчивость (СХД+ПО) | B15: руб. | C15: 3600000 | D15: 0 | E15: 0 | F15: 0 | G15: 0 | H15: 0 | I15: 0 | J15: 0 | K15: 0 | L15: 0 | M15: 0 | N15: 0 | O15: 0 | P15: 0 | Q15: 0 | R15: 0 | S15: 0 | T15: 0 | U15: 0 | V15: 0 | W15: 0 | X15: 0 | Y15: 0 | Z15: 0 | AA15: 0 | AB15: 0 | AC15: 0 | AD15: 0 | AE15: 0 | AF15: 0 | AG15: 0 | AH15: 0 | AI15: 0 | AJ15: 0 | AK15: 0 | AL15: 0 | AM15: 0 | AN15: 0 | AO15: 0 | AP15: 0 | AQ15: 0 | AR15: 0 | AS15: 0 | AT15: 0 | AU15: 0 | AV15: 0 | AW15: 0 | AX15: 0 | AY15: 0 | AZ15: 0 | BA15: 0 | BB15: 0 | BC15: 0 | BD15: 0 | BE15: 0 | BF15: 0 | BG15: 0 | BH15: 0 | BI15: 0 | BJ15: 0 | BK15: 0 | BL15: 0 | BM15: 0 | BN15: 0 | BO15: 0 | BP15: 0 | BQ15: 0 | BR15: 0 | BS15: 0 | BT15: 0 | BU15: 0 | BV15: 0 | BW15: 0 | BX15: 0 | BY15: 0 | BZ15: 0 | CA15: 0 | CB15: 0 | CC15: 0 | CD15: 0 | CE15: 0 | CF15: 0 | CG15: 0 | CH15: 0 | CI15: 0 | CJ15: 0 | CK15: 0 | CL15: 0 | CM15: 0 | CN15: 0 | CO15: 0 | CP15: 0 | CQ15: 0 | CR15: 0 | CS15: 0 | CT15: 0 | CU15: 0 | CV15: 0 | CW15: 0 | CX15: 0 | CY15: 0 | CZ15: 0 | DA15: 0 | DB15: 0 | DC15: 0 | DD15: 0 | DE15: 0 | DF15: 0 | DG15: 0 | DH15: 0 | DI15: 0 | DJ15: 0 | DK15: 0 | DL15: 0 | DM15: 0 | DN15: 0 | DO15: 0 | DP15: 0 | DQ15: 0 | DR15: 0 | DS15: 0
A16: ИБП и инфраструктура питания/охлаждения для серверной стойки (~1 стойка) | B16: руб. | C16: 2000000 | D16: 0 | E16: 0 | F16: 0 | G16: 0 | H16: 0 | I16: 0 | J16: 0 | K16: 0 | L16: 0 | M16: 0 | N16: 0 | O16: 0 | P16: 0 | Q16: 0 | R16: 0 | S16: 0 | T16: 0 | U16: 0 | V16: 0 | W16: 0 | X16: 0 | Y16: 0 | Z16: 0 | AA16: 0 | AB16: 0 | AC16: 0 | AD16: 0 | AE16: 0 | AF16: 0 | AG16: 0 | AH16: 0 | AI16: 0 | AJ16: 0 | AK16: 0 | AL16: 0 | AM16: 0 | AN16: 0 | AO16: 0 | AP16: 0 | AQ16: 0 | AR16: 0 | AS16: 0 | AT16: 0 | AU16: 0 | AV16: 0 | AW16: 0 | AX16: 0 | AY16: 0 | AZ16: 0 | BA16: 0 | BB16: 0 | BC16: 0 | BD16: 0 | BE16: 0 | BF16: 0 | BG16: 0 | BH16: 0 | BI16: 0 | BJ16: 0 | BK16: 0 | BL16: 0 | BM16: 0 | BN16: 0 | BO16: 0 | BP16: 0 | BQ16: 0 | BR16: 0 | BS16: 0 | BT16: 0 | BU16: 0 | BV16: 0 | BW16: 0 | BX16: 0 | BY16: 0 | BZ16: 0 | CA16: 0 | CB16: 0 | CC16: 0 | CD16: 0 | CE16: 0 | CF16: 0 | CG16: 0 | CH16: 0 | CI16: 0 | CJ16: 0 | CK16: 0 | CL16: 0 | CM16: 0 | CN16: 0 | CO16: 0 | CP16: 0 | CQ16: 0 | CR16: 0 | CS16: 0 | CT16: 0 | CU16: 0 | CV16: 0 | CW16: 0 | CX16: 0 | CY16: 0 | CZ16: 0 | DA16: 0 | DB16: 0 | DC16: 0 | DD16: 0 | DE16: 0 | DF16: 0 | DG16: 0 | DH16: 0 | DI16: 0 | DJ16: 0 | DK16: 0 | DL16: 0 | DM16: 0 | DN16: 0 | DO16: 0 | DP16: 0 | DQ16: 0 | DR16: 0 | DS16: 0
A17: Итого основных средств | C17: =SUM(C9:C16) -> 65500000 | D17: =SUM(D9:D16) -> 0 | E17: =SUM(E9:E16) -> 0 | F17: =SUM(F9:F16) -> 0 | G17: =SUM(G9:G16) -> 0 | H17: =SUM(H9:H16) -> 0 | I17: =SUM(I9:I16) -> 0 | J17: =SUM(J9:J16) -> 0 | ... DS17: =SUM(DS9:DS16) -> 0
A18: Периферия для рабочих мест разработчиков (мониторы, клавиатуры и т.д.) | B18: руб. | C18: =SUM(D18:DS18) -> 0 | D18: 0 | E18: 0 | F18: 0 | G18: 0 | H18: 0 | I18: 0 | J18: 0 | K18: 0 | L18: 0 | M18: 0 | N18: 0 | O18: 0 | P18: 0 | Q18: 0 | R18: 0 | S18: 0 | T18: 0 | U18: 0 | V18: 0 | W18: 0 | X18: 0 | Y18: 0 | Z18: 0 | AA18: 0 | AB18: 0 | AC18: 0 | AD18: 0 | AE18: 0 | AF18: 0 | AG18: 0 | AH18: 0 | AI18: 0 | AJ18: 0 | AK18: 0 | AL18: 0 | AM18: 0 | AN18: 0 | AO18: 0 | AP18: 0 | AQ18: 0 | AR18: 0 | AS18: 0 | AT18: 0 | AU18: 0 | AV18: 0 | AW18: 0 | AX18: 0 | AY18: 0 | AZ18: 0 | BA18: 0 | BB18: 0 | BC18: 0 | BD18: 0 | BE18: 0 | BF18: 0 | BG18: 0 | BH18: 0 | BI18: 0 | BJ18: 0 | BK18: 0 | BL18: 0 | BM18: 0 | BN18: 0 | BO18: 0 | BP18: 0 | BQ18: 0 | BR18: 0 | BS18: 0 | BT18: 0 | BU18: 0 | BV18: 0 | BW18: 0 | BX18: 0 | BY18: 0 | BZ18: 0 | CA18: 0 | CB18: 0 | CC18: 0 | CD18: 0 | CE18: 0 | CF18: 0 | CG18: 0 | CH18: 0 | CI18: 0 | CJ18: 0 | CK18: 0 | CL18: 0 | CM18: 0 | CN18: 0 | CO18: 0 | CP18: 0 | CQ18: 0 | CR18: 0 | CS18: 0 | CT18: 0 | CU18: 0 | CV18: 0 | CW18: 0 | CX18: 0 | CY18: 0 | CZ18: 0 | DA18: 0 | DB18: 0 | DC18: 0 | DD18: 0 | DE18: 0 | DF18: 0 | DG18: 0 | DH18: 0 | DI18: 0 | DJ18: 0 | DK18: 0 | DL18: 0 | DM18: 0 | DN18: 0 | DO18: 0 | DP18: 0 | DQ18: 0 | DR18: 0 | DS18: 0
A19: Мелкое сетевое оборудование (патч-панели, кабели) и аксессуары для серверной стойки (~стойка) | B19: руб. | C19: =SUM(D19:DS19) -> 0 | D19: 0 | E19: 0 | F19: 0 | G19: 0 | H19: 0 | I19: 0 | J19: 0 | K19: 0 | L19: 0 | M19: 0 | N19: 0 | O19: 0 | P19: 0 | Q19: 0 | R19: 0 | S19: 0 | T19: 0 | U19: 0 | V19: 0 | W19: 0 | X19: 0 | Y19: 0 | Z19: 0 | AA19: 0 | AB19: 0 | AC19: 0 | AD19: 0 | AE19: 0 | AF19: 0 | AG19: 0 | AH19: 0 | AI19: 0 | AJ19: 0 | AK19: 0 | AL19: 0 | AM19: 0 | AN19: 0 | AO19: 0 | AP19: 0 | AQ19: 0 | AR19: 0 | AS19: 0 | AT19: 0 | AU19: 0 | AV19: 0 | AW19: 0 | AX19: 0 | AY19: 0 | AZ19: 0 | BA19: 0 | BB19: 0 | BC19: 0 | BD19: 0 | BE19: 0 | BF19: 0 | BG19: 0 | BH19: 0 | BI19: 0 | BJ19: 0 | BK19: 0 | BL19: 0 | BM19: 0 | BN19: 0 | BO19: 0 | BP19: 0 | BQ19: 0 | BR19: 0 | BS19: 0 | BT19: 0 | BU19: 0 | BV19: 0 | BW19: 0 | BX19: 0 | BY19: 0 | BZ19: 0 | CA19: 0 | CB19: 0 | CC19: 0 | CD19: 0 | CE19: 0 | CF19: 0 | CG19: 0 | CH19: 0 | CI19: 0 | CJ19: 0 | CK19: 0 | CL19: 0 | CM19: 0 | CN19: 0 | CO19: 0 | CP19: 0 | CQ19: 0 | CR19: 0 | CS19: 0 | CT19: 0 | CU19: 0 | CV19: 0 | CW19: 0 | CX19: 0 | CY19: 0 | CZ19: 0 | DA19: 0 | DB19: 0 | DC19: 0 | DD19: 0 | DE19: 0 | DF19: 0 | DG19: 0 | DH19: 0 | DI19: 0 | DJ19: 0 | DK19: 0 | DL19: 0 | DM19: 0 | DN19: 0 | DO19: 0 | DP19: 0 | DQ19: 0 | DR19: 0 | DS19: 0
A20: Итого (мелкое оборудование): | C20: =C18+C19 -> 0 | D20: =D18+D19 -> 0 | E20: =E18+E19 -> 0 | F20: =F18+F19 -> 0 | G20: =G18+G19 -> 0 | H20: =H18+H19 -> 0 | I20: =I18+I19 -> 0 | J20: =J18+J19 -> 0 | ... DS20: =DS18+DS19 -> 0
A21: Итого: | B21: руб. | C21: =SUM(D21:DS21) -> 0 | D21: =SUM(D8+D17+D20) -> 0 | E21: =SUM(E8+E17+E20) -> 0 | F21: =SUM(F8+F17+F20) -> 0 | G21: =SUM(G8+G17+G20) -> 0 | H21: =SUM(H8+H17+H20) -> 0 | I21: =SUM(I8+I17+I20) -> 0 | J21: =SUM(J8+J17+J20) -> 0 | K21: =SUM(K8+K17+K20) -> 0 | ... DS21: =SUM(DS8+DS17+DS20) -> 0
A22: https://www.audit-it.ru/ifrs/terms/items/capex.html

Sheet Операционные затраты
B2: Операционные затраты
B4: Операционные затраты
E5: 1 год | Q5: 2 год | AC5: 3 год | AO5: 4 год | BA5: 5 год | BM5: 6 год | BY5: 7 год | CK5: 8 год | CW5: 9 год | DI5: 10 год
B6: Наименование затрат | C6: Ед. из. | D6: Сумма | E6: 1 | F6: 2 | G6: 3 | H6: 4 | I6: 5 | J6: 6 | K6: 7 | L6: 8 | M6: 9 | N6: 10 | O6: 11 | P6: 12 | Q6: 1 | R6: 2 | S6: 3 | T6: 4 | U6: 5 | V6: 6 | W6: 7 | X6: 8 | Y6: 9 | Z6: 10 | AA6: 11 | AB6: 12 | AC6: 1 | AD6: 2 | AE6: 3 | AF6: 4 | AG6: 5 | AH6: 6 | AI6: 7 | AJ6: 8 | AK6: 9 | AL6: 10 | AM6: 11 | AN6: 12 | AO6: 1 | AP6: 2 | AQ6: 3 | AR6: 4 | AS6: 5 | AT6: 6 | AU6: 7 | AV6: 8 | AW6: 9 | AX6: 10 | AY6: 11 | AZ6: 12 | BA6: 1 | BB6: 2 | BC6: 3 | BD6: 4 | BE6: 5 | BF6: 6 | BG6: 7 | BH6: 8 | BI6: 9 | BJ6: 10 | BK6: 11 | BL6: 12 | BM6: 1 | BN6: 2 | BO6: 3 | BP6: 4 | BQ6: 5 | BR6: 6 | BS6: 7 | BT6: 8 | BU6: 9 | BV6: 10 | BW6: 11 | BX6: 12 | BY6: 1 | BZ6: 2 | CA6: 3 | CB6: 4 | CC6: 5 | CD6: 6 | CE6: 7 | CF6: 8 | CG6: 9 | CH6: 10 | CI6: 11 | CJ6: 12 | CK6: 1 | CL6: 2 | CM6: 3 | CN6: 4 | CO6: 5 | CP6: 6 | CQ6: 7 | CR6: 8 | CS6: 9 | CT6: 10 | CU6: 11 | CV6: 12 | CW6: 1 | CX6: 2 | CY6: 3 | CZ6: 4 | DA6: 5 | DB6: 6 | DC6: 7 | DD6: 8 | DE6: 9 | DF6: 10 | DG6: 11 | DH6: 12 | DI6: 1 | DJ6: 2 | DK6: 3 | DL6: 4 | DM6: 5 | DN6: 6 | DO6: 7 | DP6: 8 | DQ6: 9 | DR6: 10 | DS6: 11 | DT6: 12 | DV6: Итого за 1 год: | DW6: Итого за 2 год: | DX6: Итого за 3 год: | DY6: Итого за 4 год: | DZ6: Итого за 5 год: | EA6: Итого за 6 год: | EB6: Итого за 7 год: | EC6: Итого за 8 год: | ED6: Итого за 9 год: | EE6: Итого за 10 год:
E7: 1 | F7: 2 | G7: 3 | H7: 4 | I7: 5 | J7: 6 | K7: 7 | L7: 8 | M7: 9 | N7: 10 | O7: 11 | P7: 12 | Q7: 13 | R7: 14 | S7: 15 | T7: 16 | U7: 17 | V7: 18 | W7: 19 | X7: 20 | Y7: 21 | Z7: 22 | AA7: 23 | AB7: 24 | AC7: 25 | AD7: 26 | AE7: 27 | AF7: 28 | AG7: 29 | AH7: 30 | AI7: 31 | AJ7: 32 | AK7: 33 | AL7: 34 | AM7: 35 | AN7: 36 | AO7: 1 | AP7: 2 | AQ7: 3 | AR7: 4 | AS7: 5 | AT7: 6 | AU7: 7 | AV7: 8 | AW7: 9 | AX7: 10 | AY7: 11 | AZ7: 12 | BA7: 13 | BB7: 14 | BC7: 15 | BD7: 16 | BE7: 17 | BF7: 18 | BG7: 19 | BH7: 20 | BI7: 21 | BJ7: 22 | BK7: 23 | BL7: 24 | BM7: 25 | BN7: 26 | BO7: 27 | BP7: 28 | BQ7: 29 | BR7: 30 | BS7: 31 | BT7: 32 | BU7: 33 | BV7: 34 | BW7: 35 | BX7: 36 | BY7: 1 | BZ7: 2 | CA7: 3 | CB7: 4 | CC7: 5 | CD7: 6 | CE7: 7 | CF7: 8 | CG7: 9 | CH7: 10 | CI7: 11 | CJ7: 12 | CK7: 13 | CL7: 14 | CM7: 15 | CN7: 16 | CO7: 17 | CP7: 18 | CQ7: 19 | CR7: 20 | CS7: 21 | CT7: 22 | CU7: 23 | CV7: 24 | CW7: 25 | CX7: 26 | CY7: 27 | CZ7: 28 | DA7: 29 | DB7: 30 | DC7: 31 | DD7: 32 | DE7: 33 | DF7: 34 | DG7: 35 | DH7: 36 | DI7: 1 | DJ7: 2 | DK7: 3 | DL7: 4 | DM7: 5 | DN7: 6 | DO7: 7 | DP7: 8 | DQ7: 9 | DR7: 10 | DS7: 11 | DT7: 12
B8: 1.Текущие затраты | DV8: =SUM(E8:P8) -> 0 | DW8: =SUM(F8:Q8) -> 0 | DX8: =SUM(G8:R8) -> 0 | DY8: =SUM(H8:S8) -> 0 | DZ8: =SUM(I8:T8) -> 0 | EA8: =SUM(J8:U8) -> 0 | EB8: =SUM(K8:V8) -> 0 | EC8: =SUM(L8:W8) -> 0 | ... EE8: =SUM(N8:Y8) -> 0
B9: До внедрения мер | E9: 0 | F9: 0 | G9: 0 | H9: 0 | I9: 0 | J9: 0 | K9: 0 | L9: 0 | M9: 0 | N9: 0 | O9: 0 | P9: 0 | Q9: =Q20+'Экономический эффект'!Q15+50000000+Q15+Q16 -> 1.1389077e+09 | R9: =R20+'Экономический эффект'!R15+50000000+R15+R16 -> 1.1426978e+09 | S9: =S20+'Экономический эффект'!S15+50000000+S15+S16 -> 1.1465568e+09 | T9: =T20+'Экономический эффект'!T15+50000000+T15+T16 -> 1.1504861e+09 | U9: =U20+'Экономический эффект'!U15+50000000+U15+U16 -> 1.1544869e+09 | V9: =V20+'Экономический эффект'!V15+50000000+V15+V16 -> 1.1585608e+09 | W9: =W20+'Экономический эффект'!W15+50000000+W15+W16 -> 1.1627091e+09 | X9: =X20+'Экономический эффект'!X15+50000000+X15+X16 -> 1.1669334e+09 | ... DT9: =DT20+'Экономический эффект'!DT15+50000000+DT15+DT16 -> 2.4411101e+09 | DV9: -2 | DW9: =SUM(F9:Q9) -> 1.1389077e+09 | DX9: =SUM(G9:R9) -> 2.2816055e+09 | DY9: =SUM(H9:S9) -> 3.4281623e+09 | DZ9: =SUM(I9:T9) -> 4.5786483e+09 | EA9: =SUM(J9:U9) -> 5.7331352e+09 | EB9: =SUM(K9:V9) -> 6.891696e+09 | EC9: =SUM(L9:W9) -> 8.0544051e+09 | ED9: =SUM(M9:X9) -> 9.2213385e+09 | EE9: =SUM(N9:Y9) -> 1.0392574e+10
B10: Сопровождение | C10: руб. | D10: =SUM(E10:DT10) -> 7000006.5 | E10: 0 | F10: 0 | G10: 0 | H10: 0 | I10: 0 | J10: 0 | K10: 0 | L10: 0 | M10: 0 | N10: 0 | O10: 0 | P10: 7 | Q10: 64814.81 | R10: 64814.81 | S10: 64814.81 | T10: 64814.81 | U10: 64814.81 | V10: 64814.81 | W10: 64814.81 | X10: 64814.81 | Y10: 64814.81 | Z10: 64814.81 | AA10: 64814.81 | AB10: 64814.81 | AC10: 64814.81 | AD10: 64814.81 | AE10: 64814.81 | AF10: 64814.81 | AG10: 64814.81 | AH10: 64814.81 | AI10: 64814.81 | AJ10: 64814.81 | AK10: 64814.81 | AL10: 64814.81 | AM10: 64814.81 | AN10: 64814.81 | AO10: 64814.81 | AP10: 64814.81 | AQ10: 64814.81 | AR10: 64814.81 | AS10: 64814.81 | AT10: 64814.81 | AU10: 64814.81 | AV10: 64814.81 | AW10: 64814.81 | AX10: 64814.81 | AY10: 64814.81 | AZ10: 64814.81 | BA10: 64814.81 | BB10: 64814.81 | BC10: 64814.81 | BD10: 64814.81 | BE10: 64814.81 | BF10: 64814.81 | BG10: 64814.81 | BH10: 64814.81 | BI10: 64814.81 | BJ10: 64814.81 | BK10: 64814.81 | BL10: 64814.81 | BM10: 64814.81 | BN10: 64814.81 | BO10: 64814.81 | BP10: 64814.81 | BQ10: 64814.81 | BR10: 64814.81 | BS10: 64814.81 | BT10: 64814.81 | BU10: 64814.81 | BV10: 64814.81 | BW10: 64814.81 | BX10: 64814.81 | BY10: 64814.81 | BZ10: 64814.81 | CA10: 64814.81 | CB10: 64814.81 | CC10: 64814.81 | CD10: 64814.81 | CE10: 64814.81 | CF10: 64814.81 | CG10: 64814.81 | CH10: 64814.81 | CI10: 64814.81 | CJ10: 64814.81 | CK10: 64814.81 | CL10: 64814.81 | CM10: 64814.81 | CN10: 64814.81 | CO10: 64814.81 | CP10: 64814.81 | CQ10: 64814.81 | CR10: 64814.81 | CS10: 64814.81 | CT10: 64814.81 | CU10: 64814.81 | CV10: 64814.81 | CW10: 64814.81 | CX10: 64814.81 | CY10: 64814.81 | CZ10: 64814.81 | DA10: 64814.81 | DB10: 64814.81 | DC10: 64814.81 | DD10: 64814.81 | DE10: 64814.81 | DF10: 64814.81 | DG10: 64814.81 | DH10: 64814.81 | DI10: 64814.81 | DJ10: 64814.81 | DK10: 64814.81 | DL10: 64814.81 | DM10: 64814.81 | DN10: 64814.81 | DO10: 64814.81 | DP10: 64814.81 | DQ10: 64814.81 | DR10: 64814.81 | DS10: 64814.81 | DT10: 64814.81 | DV10: 0 | DW10: =SUM(F10:Q10) -> 64821.81 | DX10: =SUM(G10:R10) -> 129636.62 | DY10: =SUM(H10:S10) -> 194451.43 | DZ10: =SUM(I10:T10) -> 259266.24 | EA10: =SUM(J10:U10) -> 324081.05 | EB10: =SUM(K10:V10) -> 388895.86 | EC10: =SUM(L10:W10) -> 453710.67 | ED10: =SUM(M10:X10) -> 518525.48 | EE10: =SUM(N10:Y10) -> 583340.29
B11: Поддержка пользователей | C11: руб. | D11: =SUM(E11:DT11) -> 3000000.2 | E11: 0 | F11: 0 | G11: 0 | H11: 0 | I11: 0 | J11: 0 | K11: 0 | L11: 0 | M11: 0 | N11: 0 | O11: 0 | P11: 0 | Q11: 27777.78 | R11: 27777.78 | S11: 27777.78 | T11: 27777.78 | U11: 27777.78 | V11: 27777.78 | W11: 27777.78 | X11: 27777.78 | Y11: 27777.78 | Z11: 27777.78 | AA11: 27777.78 | AB11: 27777.78 | AC11: 27777.78 | AD11: 27777.78 | AE11: 27777.78 | AF11: 27777.78 | AG11: 27777.78 | AH11: 27777.78 | AI11: 27777.78 | AJ11: 27777.78 | AK11: 27777.78 | AL11: 27777.78 | AM11: 27777.78 | AN11: 27777.78 | AO11: 27777.78 | AP11: 27777.78 | AQ11: 27777.78 | AR11: 27777.78 | AS11: 27777.78 | AT11: 27777.78 | AU11: 27777.78 | AV11: 27777.78 | AW11: 27777.78 | AX11: 27777.78 | AY11: 27777.78 | AZ11: 27777.78 | BA11: 27777.78 | BB11: 27777.78 | BC11: 27777.78 | BD11: 27777.78 | BE11: 27777.78 | BF11: 27777.78 | BG11: 27777.78 | BH11: 27777.78 | BI11: 27777.78 | BJ11: 27777.78 | BK11: 27777.78 | BL11: 27777.78 | BM11: 27777.78 | BN11: 27777.78 | BO11: 27777.78 | BP11: 27777.78 | BQ11: 27777.78 | BR11: 27777.78 | BS11: 27777.78 | BT11: 27777.78 | BU11: 27777.78 | BV11: 27777.78 | BW11: 27777.78 | BX11: 27777.78 | BY11: 27777.78 | BZ11: 27777.78 | CA11: 27777.78 | CB11: 27777.78 | CC11: 27777.78 | CD11: 27777.78 | CE11: 27777.78 | CF11: 27777.78 | CG11: 27777.78 | CH11: 27777.78 | CI11: 27777.78 | CJ11: 27777.78 | CK11: 27777.78 | CL11: 27777.78 | CM11: 27777.78 | CN11: 27777.78 | CO11: 27777.78 | CP11: 27777.78 | CQ11: 27777.78 | CR11: 27777.78 | CS11: 27777.78 | CT11: 27777.78 | CU11: 27777.78 | CV11: 27777.78 | CW11: 27777.78 | CX11: 27777.78 | CY11: 27777.78 | CZ11: 27777.78 | DA11: 27777.78 | DB11: 27777.78 | DC11: 27777.78 | DD11: 27777.78 | DE11: 27777.78 | DF11: 27777.78 | DG11: 27777.78 | DH11: 27777.78 | DI11: 27777.78 | DJ11: 27777.78 | DK11: 27777.78 | DL11: 27777.78 | DM11: 27777.78 | DN11: 27777.78 | DO11: 27777.78 | DP11: 27777.78 | DQ11: 27777.78 | DR11: 27777.78 | DS11: 27777.78 | DT11: 27777.78 | DV11: =SUM(E11:P11) -> 0 | DW11: =SUM(F11:Q11) -> 27777.78 | DX11: =SUM(G11:R11) -> 55555.56 | DY11: =SUM(H11:S11) -> 83333.34 | DZ11: =SUM(I11:T11) -> 111111.12 | EA11: =SUM(J11:U11) -> 138888.9 | EB11: =SUM(K11:V11) -> 166666.68 | EC11: =SUM(L11:W11) -> 194444.46 | ... EE11: =SUM(N11:Y11) -> 250000.02
B12: Обучение и коммуникации | C12: руб. | D12: =SUM(E12:DT12) -> 2000000.2 | E12: 0 | F12: 0 | G12: 0 | H12: 0 | I12: 0 | J12: 0 | K12: 0 | L12: 0 | M12: 0 | N12: 0 | O12: 0 | P12: 0 | Q12: 18518.52 | R12: 18518.52 | S12: 18518.52 | T12: 18518.52 | U12: 18518.52 | V12: 18518.52 | W12: 18518.52 | X12: 18518.52 | Y12: 18518.52 | Z12: 18518.52 | AA12: 18518.52 | AB12: 18518.52 | AC12: 18518.52 | AD12: 18518.52 | AE12: 18518.52 | AF12: 18518.52 | AG12: 18518.52 | AH12: 18518.52 | AI12: 18518.52 | AJ12: 18518.52 | AK12: 18518.52 | AL12: 18518.52 | AM12: 18518.52 | AN12: 18518.52 | AO12: 18518.52 | AP12: 18518.52 | AQ12: 18518.52 | AR12: 18518.52 | AS12: 18518.52 | AT12: 18518.52 | AU12: 18518.52 | AV12: 18518.52 | AW12: 18518.52 | AX12: 18518.52 | AY12: 18518.52 | AZ12: 18518.52 | BA12: 18518.52 | BB12: 18518.52 | BC12: 18518.52 | BD12: 18518.52 | BE12: 18518.52 | BF12: 18518.52 | BG12: 18518.52 | BH12: 18518.52 | BI12: 18518.52 | BJ12: 18518.52 | BK12: 18518.52 | BL12: 18518.52 | BM12: 18518.52 | BN12: 18518.52 | BO12: 18518.52 | BP12: 18518.52 | BQ12: 18518.52 | BR12: 18518.52 | BS12: 18518.52 | BT12: 18518.52 | BU12: 18518.52 | BV12: 18518.52 | BW12: 18518.52 | BX12: 18518.52 | BY12: 18518.52 | BZ12: 18518.52 | CA12: 18518.52 | CB12: 18518.52 | CC12: 18518.52 | CD12: 18518.52 | CE12: 18518.52 | CF12: 18518.52 | CG12: 18518.52 | CH12: 18518.52 | CI12: 18518.52 | CJ12: 18518.52 | CK12: 18518.52 | CL12: 18518.52 | CM12: 18518.52 | CN12: 18518.52 | CO12: 18518.52 | CP12: 18518.52 | CQ12: 18518.52 | CR12: 18518.52 | CS12: 18518.52 | CT12: 18518.52 | CU12: 18518.52 | CV12: 18518.52 | CW12: 18518.52 | CX12: 18518.52 | CY12: 18518.52 | CZ12: 18518.52 | DA12: 18518.52 | DB12: 18518.52 | DC12: 18518.52 | DD12: 18518.52 | DE12: 18518.52 | DF12: 18518.52 | DG12: 18518.52 | DH12: 18518.52 | DI12: 18518.52 | DJ12: 18518.52 | DK12: 18518.52 | DL12: 18518.52 | DM12: 18518.52 | DN12: 18518.52 | DO12: 18518.52 | DP12: 18518.52 | DQ12: 18518.52 | DR12: 18518.52 | DS12: 18518.52 | DT12: 18518.52 | DV12: =SUM(E12:P12) -> 0 | DW12: =SUM(F12:Q12) -> 18518.52 | DX12: =SUM(G12:R12) -> 37037.04 | DY12: =SUM(H12:S12) -> 55555.56 | DZ12: =SUM(I12:T12) -> 74074.08 | EA12: =SUM(J12:U12) -> 92592.6 | EB12: =SUM(K12:V12) -> 111111.12 | EC12: =SUM(L12:W12) -> 129629.64 | ... EE12: =SUM(N12:Y12) -> 166666.68
B13: Юридическое сопровождение | C13: руб. | D13: =SUM(E13:DT13) -> 1000000.1 | E13: 0 | F13: 0 | G13: 0 | H13: 0 | I13: 0 | J13: 0 | K13: 0 | L13: 0 | M13: 0 | N13: 0 | O13: 0 | P13: 0 | Q13: 9259.26 | R13: 9259.26 | S13: 9259.26 | T13: 9259.26 | U13: 9259.26 | V13: 9259.26 | W13: 9259.26 | X13: 9259.26 | Y13: 9259.26 | Z13: 9259.26 | AA13: 9259.26 | AB13: 9259.26 | AC13: 9259.26 | AD13: 9259.26 | AE13: 9259.26 | AF13: 9259.26 | AG13: 9259.26 | AH13: 9259.26 | AI13: 9259.26 | AJ13: 9259.26 | AK13: 9259.26 | AL13: 9259.26 | AM13: 9259.26 | AN13: 9259.26 | AO13: 9259.26 | AP13: 9259.26 | AQ13: 9259.26 | AR13: 9259.26 | AS13: 9259.26 | AT13: 9259.26 | AU13: 9259.26 | AV13: 9259.26 | AW13: 9259.26 | AX13: 9259.26 | AY13: 9259.26 | AZ13: 9259.26 | BA13: 9259.26 | BB13: 9259.26 | BC13: 9259.26 | BD13: 9259.26 | BE13: 9259.26 | BF13: 9259.26 | BG13: 9259.26 | BH13: 9259.26 | BI13: 9259.26 | BJ13: 9259.26 | BK13: 9259.26 | BL13: 9259.26 | BM13: 9259.26 | BN13: 9259.26 | BO13: 9259.26 | BP13: 9259.26 | BQ13: 9259.26 | BR13: 9259.26 | BS13: 9259.26 | BT13: 9259.26 | BU13: 9259.26 | BV13: 9259.26 | BW13: 9259.26 | BX13: 9259.26 | BY13: 9259.26 | BZ13: 9259.26 | CA13: 9259.26 | CB13: 9259.26 | CC13: 9259.26 | CD13: 9259.26 | CE13: 9259.26 | CF13: 9259.26 | CG13: 9259.26 | CH13: 9259.26 | CI13: 9259.26 | CJ13: 9259.26 | CK13: 9259.26 | CL13: 9259.26 | CM13: 9259.26 | CN13: 9259.26 | CO13: 9259.26 | CP13: 9259.26 | CQ13: 9259.26 | CR13: 9259.26 | CS13: 9259.26 | CT13: 9259.26 | CU13: 9259.26 | CV13: 9259.26 | CW13: 9259.26 | CX13: 9259.26 | CY13: 9259.26 | CZ13: 9259.26 | DA13: 9259.26 | DB13: 9259.26 | DC13: 9259.26 | DD13: 9259.26 | DE13: 9259.26 | DF13: 9259.26 | DG13: 9259.26 | DH13: 9259.26 | DI13: 9259.26 | DJ13: 9259.26 | DK13: 9259.26 | DL13: 9259.26 | DM13: 9259.26 | DN13: 9259.26 | DO13: 9259.26 | DP13: 9259.26 | DQ13: 9259.26 | DR13: 9259.26 | DS13: 9259.26 | DT13: 9259.26 | DV13: =SUM(E13:P13) -> 0 | DW13: =SUM(F13:Q13) -> 9259.26 | DX13: =SUM(G13:R13) -> 18518.52 | DY13: =SUM(H13:S13) -> 27777.78 | DZ13: =SUM(I13:T13) -> 37037.04 | EA13: =SUM(J13:U13) -> 46296.3 | EB13: =SUM(K13:V13) -> 55555.56 | EC13: =SUM(L13:W13) -> 64814.82 | ... EE13: =SUM(N13:Y13) -> 83333.34
B14: Административные расходы | C14: руб. | D14: =SUM(E14:DT14) -> 1000000.1 | E14: 0 | F14: 0 | G14: 0 | H14: 0 | I14: 0 | J14: 0 | K14: 0 | L14: 0 | M14: 0 | N14: 0 | O14: 0 | P14: 0 | Q14: 9259.26 | R14: 9259.26 | S14: 9259.26 | T14: 9259.26 | U14: 9259.26 | V14: 9259.26 | W14: 9259.26 | X14: 9259.26 | Y14: 9259.26 | Z14: 9259.26 | AA14: 9259.26 | AB14: 9259.26 | AC14: 9259.26 | AD14: 9259.26 | AE14: 9259.26 | AF14: 9259.26 | AG14: 9259.26 | AH14: 9259.26 | AI14: 9259.26 | AJ14: 9259.26 | AK14: 9259.26 | AL14: 9259.26 | AM14: 9259.26 | AN14: 9259.26 | AO14: 9259.26 | AP14: 9259.26 | AQ14: 9259.26 | AR14: 9259.26 | AS14: 9259.26 | AT14: 9259.26 | AU14: 9259.26 | AV14: 9259.26 | AW14: 9259.26 | AX14: 9259.26 | AY14: 9259.26 | AZ14: 9259.26 | BA14: 9259.26 | BB14: 9259.26 | BC14: 9259.26 | BD14: 9259.26 | BE14: 9259.26 | BF14: 9259.26 | BG14: 9259.26 | BH14: 9259.26 | BI14: 9259.26 | BJ14: 9259.26 | BK14: 9259.26 | BL14: 9259.26 | BM14: 9259.26 | BN14: 9259.26 | BO14: 9259.26 | BP14: 9259.26 | BQ14: 9259.26 | BR14: 9259.26 | BS14: 9259.26 | BT14: 9259.26 | BU14: 9259.26 | BV14: 9259.26 | BW14: 9259.26 | BX14: 9259.26 | BY14: 9259.26 | BZ14: 9259.26 | CA14: 9259.26 | CB14: 9259.26 | CC14: 9259.26 | CD14: 9259.26 | CE14: 9259.26 | CF14: 9259.26 | CG14: 9259.26 | CH14: 9259.26 | CI14: 9259.26 | CJ14: 9259.26 | CK14: 9259.26 | CL14: 9259.26 | CM14: 9259.26 | CN14: 9259.26 | CO14: 9259.26 | CP14: 9259.26 | CQ14: 9259.26 | CR14: 9259.26 | CS14: 9259.26 | CT14: 9259.26 | CU14: 9259.26 | CV14: 9259.26 | CW14: 9259.26 | CX14: 9259.26 | CY14: 9259.26 | CZ14: 9259.26 | DA14: 9259.26 | DB14: 9259.26 | DC14: 9259.26 | DD14: 9259.26 | DE14: 9259.26 | DF14: 9259.26 | DG14: 9259.26 | DH14: 9259.26 | DI14: 9259.26 | DJ14: 9259.26 | DK14: 9259.26 | DL14: 9259.26 | DM14: 9259.26 | DN14: 9259.26 | DO14: 9259.26 | DP14: 9259.26 | DQ14: 9259.26 | DR14: 9259.26 | DS14: 9259.26 | DT14: 9259.26 | DV14: =SUM(E14:P14) -> 0 | DW14: =SUM(F14:Q14) -> 9259.26 | DX14: =SUM(G14:R14) -> 18518.52 | DY14: =SUM(H14:S14) -> 27777.78 | DZ14: =SUM(I14:T14) -> 37037.04 | EA14: =SUM(J14:U14) -> 46296.3 | EB14: =SUM(K14:V14) -> 55555.56 | EC14: =SUM(L14:W14) -> 64814.82 | ... EE14: =SUM(N14:Y14) -> 83333.34
B15: Написание и поддержание ПО | D15: =SUM(E15:DT15) -> 7560000 | E15: 0 | F15: 0 | G15: 0 | H15: 0 | I15: 0 | J15: 0 | K15: 0 | L15: 0 | M15: 0 | N15: 0 | O15: 0 | P15: 0 | Q15: 50000 | R15: 50000 | S15: 50000 | T15: 50000 | U15: 50000 | V15: 50000 | W15: 50000 | X15: 50000 | Y15: 50000 | Z15: 50000 | AA15: 50000 | AB15: 50000 | AC15: 55000 | AD15: 55000 | AE15: 55000 | AF15: 55000 | AG15: 55000 | AH15: 55000 | AI15: 55000 | AJ15: 55000 | AK15: 55000 | AL15: 55000 | AM15: 55000 | AN15: 55000 | AO15: 60000 | AP15: 60000 | AQ15: 60000 | AR15: 60000 | AS15: 60000 | AT15: 60000 | AU15: 60000 | AV15: 60000 | AW15: 60000 | AX15: 60000 | AY15: 60000 | AZ15: 60000 | BA15: 65000 | BB15: 65000 | BC15: 65000 | BD15: 65000 | BE15: 65000 | BF15: 65000 | BG15: 65000 | BH15: 65000 | BI15: 65000 | BJ15: 65000 | BK15: 65000 | BL15: 65000 | BM15: 70000 | BN15: 70000 | BO15: 70000 | BP15: 70000 | BQ15: 70000 | BR15: 70000 | BS15: 70000 | BT15: 70000 | BU15: 70000 | BV15: 70000 | BW15: 70000 | BX15: 70000 | BY15: 75000 | BZ15: 75000 | CA15: 75000 | CB15: 75000 | CC15: 75000 | CD15: 75000 | CE15: 75000 | CF15: 75000 | CG15: 75000 | CH15: 75000 | CI15: 75000 | CJ15: 75000 | CK15: 80000 | CL15: 80000 | CM15: 80000 | CN15: 80000 | CO15: 80000 | CP15: 80000 | CQ15: 80000 | CR15: 80000 | CS15: 80000 | CT15: 80000 | CU15: 80000 | CV15: 80000 | CW15: 85000 | CX15: 85000 | CY15: 85000 | CZ15: 85000 | DA15: 85000 | DB15: 85000 | DC15: 85000 | DD15: 85000 | DE15: 85000 | DF15: 85000 | DG15: 85000 | DH15: 85000 | DI15: 90000 | DJ15: 90000 | DK15: 90000 | DL15: 90000 | DM15: 90000 | DN15: 90000 | DO15: 90000 | DP15: 90000 | DQ15: 90000 | DR15: 90000 | DS15: 90000 | DT15: 90000
B16: Снижение быстродействия ПО | D16: =SUM(E16:DT16) -> 37800000 | E16: 0 | F16: 0 | G16: 0 | H16: 0 | I16: 0 | J16: 0 | K16: 0 | L16: 0 | M16: 0 | N16: 0 | O16: 0 | P16: 0 | Q16: 350000 | R16: 350000 | S16: 350000 | T16: 350000 | U16: 350000 | V16: 350000 | W16: 350000 | X16: 350000 | Y16: 350000 | Z16: 350000 | AA16: 350000 | AB16: 350000 | AC16: 350000 | AD16: 350000 | AE16: 350000 | AF16: 350000 | AG16: 350000 | AH16: 350000 | AI16: 350000 | AJ16: 350000 | AK16: 350000 | AL16: 350000 | AM16: 350000 | AN16: 350000 | AO16: 350000 | AP16: 350000 | AQ16: 350000 | AR16: 350000 | AS16: 350000 | AT16: 350000 | AU16: 350000 | AV16: 350000 | AW16: 350000 | AX16: 350000 | AY16: 350000 | AZ16: 350000 | BA16: 350000 | BB16: 350000 | BC16: 350000 | BD16: 350000 | BE16: 350000 | BF16: 350000 | BG16: 350000 | BH16: 350000 | BI16: 350000 | BJ16: 350000 | BK16: 350000 | BL16: 350000 | BM16: 350000 | BN16: 350000 | BO16: 350000 | BP16: 350000 | BQ16: 350000 | BR16: 350000 | BS16: 350000 | BT16: 350000 | BU16: 350000 | BV16: 350000 | BW16: 350000 | BX16: 350000 | BY16: 350000 | BZ16: 350000 | CA16: 350000 | CB16: 350000 | CC16: 350000 | CD16: 350000 | CE16: 350000 | CF16: 350000 | CG16: 350000 | CH16: 350000 | CI16: 350000 | CJ16: 350000 | CK16: 350000 | CL16: 350000 | CM16: 350000 | CN16: 350000 | CO16: 350000 | CP16: 350000 | CQ16: 350000 | CR16: 350000 | CS16: 350000 | CT16: 350000 | CU16: 350000 | CV16: 350000 | CW16: 350000 | CX16: 350000 | CY16: 350000 | CZ16: 350000 | DA16: 350000 | DB16: 350000 | DC16: 350000 | DD16: 350000 | DE16: 350000 | DF16: 350000 | DG16: 350000 | DH16: 350000 | DI16: 350000 | DJ16: 350000 | DK16: 350000 | DL16: 350000 | DM16: 350000 | DN16: 350000 | DO16: 350000 | DP16: 350000 | DQ16: 350000 | DR16: 350000 | DS16: 350000 | DT16: 350000
B17: Адаптация, обучение, подбор песронала на начальных позициях | C17: руб. | D17: =SUM(E17:DT17) -> 5400000000 | E17: 0 | F17: 0 | G17: 0 | H17: 0 | I17: 0 | J17: 0 | K17: 0 | L17: 0 | M17: 0 | N17: 0 | O17: 0 | P17: 0 | Q17: 50000000 | R17: 50000000 | S17: 50000000 | T17: 50000000 | U17: 50000000 | V17: 50000000 | W17: 50000000 | X17: 50000000 | Y17: 50000000 | Z17: 50000000 | AA17: 50000000 | AB17: 50000000 | AC17: 50000000 | AD17: 50000000 | AE17: 50000000 | AF17: 50000000 | AG17: 50000000 | AH17: 50000000 | AI17: 50000000 | AJ17: 50000000 | AK17: 50000000 | AL17: 50000000 | AM17: 50000000 | AN17: 50000000 | AO17: 50000000 | AP17: 50000000 | AQ17: 50000000 | AR17: 50000000 | AS17: 50000000 | AT17: 50000000 | AU17: 50000000 | AV17: 50000000 | AW17: 50000000 | AX17: 50000000 | AY17: 50000000 | AZ17: 50000000 | BA17: 50000000 | BB17: 50000000 | BC17: 50000000 | BD17: 50000000 | BE17: 50000000 | BF17: 50000000 | BG17: 50000000 | BH17: 50000000 | BI17: 50000000 | BJ17: 50000000 | BK17: 50000000 | BL17: 50000000 | BM17: 50000000 | BN17: 50000000 | BO17: 50000000 | BP17: 50000000 | BQ17: 50000000 | BR17: 50000000 | BS17: 50000000 | BT17: 50000000 | BU17: 50000000 | BV17: 50000000 | BW17: 50000000 | BX17: 50000000 | BY17: 50000000 | BZ17: 50000000 | CA17: 50000000 | CB17: 50000000 | CC17: 50000000 | CD17: 50000000 | CE17: 50000000 | CF17: 50000000 | CG17: 50000000 | CH17: 50000000 | CI17: 50000000 | CJ17: 50000000 | CK17: 50000000 | CL17: 50000000 | CM17: 50000000 | CN17: 50000000 | CO17: 50000000 | CP17: 50000000 | CQ17: 50000000 | CR17: 50000000 | CS17: 50000000 | CT17: 50000000 | CU17: 50000000 | CV17: 50000000 | CW17: 50000000 | CX17: 50000000 | CY17: 50000000 | CZ17: 50000000 | DA17: 50000000 | DB17: 50000000 | DC17: 50000000 | DD17: 50000000 | DE17: 50000000 | DF17: 50000000 | DG17: 50000000 | DH17: 50000000 | DI17: 50000000 | DJ17: 50000000 | DK17: 50000000 | DL17: 50000000 | DM17: 50000000 | DN17: 50000000 | DO17: 50000000 | DP17: 50000000 | DQ17: 50000000 | DR17: 50000000 | DS17: 50000000 | DT17: 50000000 | DV17: =SUM(E17:P17) -> 0 | DW17: =SUM(F17:Q17) -> 50000000 | DX17: =SUM(G17:R17) -> 100000000 | DY17: =SUM(H17:S17) -> 150000000 | DZ17: =SUM(I17:T17) -> 200000000 | EA17: =SUM(J17:U17) -> 250000000 | EB17: =SUM(K17:V17) -> 300000000 | EC17: =SUM(L17:W17) -> 350000000 | ... EE17: =SUM(N17:Y17) -> 450000000
B18: Подписки и сервисы | C18: руб. | D18: =SUM(E18:DT18) -> 3000000.2 | E18: ='Приложение (затраты)'!D6 -> 0 | F18: 0 | G18: ='Приложение (затраты)'!F6 -> 0 | H18: 0 | I18: ='Приложение (затраты)'!H6 -> 0 | J18: 0 | K18: ='Приложение (затраты)'!J6 -> 0 | L18: 0 | M18: ='Приложение (затраты)'!L6 -> 0 | N18: 0 | O18: ='Приложение (затраты)'!N6 -> 0 | P18: 0 | Q18: 27777.78 | R18: 27777.78 | S18: 27777.78 | T18: 27777.78 | U18: 27777.78 | V18: 27777.78 | W18: 27777.78 | X18: 27777.78 | Y18: 27777.78 | Z18: 27777.78 | AA18: 27777.78 | AB18: 27777.78 | AC18: 27777.78 | AD18: 27777.78 | AE18: 27777.78 | AF18: 27777.78 | AG18: 27777.78 | AH18: 27777.78 | AI18: 27777.78 | AJ18: 27777.78 | AK18: 27777.78 | AL18: 27777.78 | AM18: 27777.78 | AN18: 27777.78 | AO18: 27777.78 | AP18: 27777.78 | AQ18: 27777.78 | AR18: 27777.78 | AS18: 27777.78 | AT18: 27777.78 | AU18: 27777.78 | AV18: 27777.78 | AW18: 27777.78 | AX18: 27777.78 | AY18: 27777.78 | AZ18: 27777.78 | BA18: 27777.78 | BB18: 27777.78 | BC18: 27777.78 | BD18: 27777.78 | BE18: 27777.78 | BF18: 27777.78 | BG18: 27777.78 | BH18: 27777.78 | BI18: 27777.78 | BJ18: 27777.78 | BK18: 27777.78 | BL18: 27777.78 | BM18: 27777.78 | BN18: 27777.78 | BO18: 27777.78 | BP18: 27777.78 | BQ18: 27777.78 | BR18: 27777.78 | BS18: 27777.78 | BT18: 27777.78 | BU18: 27777.78 | BV18: 27777.78 | BW18: 27777.78 | BX18: 27777.78 | BY18: 27777.78 | BZ18: 27777.78 | CA18: 27777.78 | CB18: 27777.78 | CC18: 27777.78 | CD18: 27777.78 | CE18: 27777.78 | CF18: 27777.78 | CG18: 27777.78 | CH18: 27777.78 | CI18: 27777.78 | CJ18: 27777.78 | CK18: 27777.78 | CL18: 27777.78 | CM18: 27777.78 | CN18: 27777.78 | CO18: 27777.78 | CP18: 27777.78 | CQ18: 27777.78 | CR18: 27777.78 | CS18: 27777.78 | CT18: 27777.78 | CU18: 27777.78 | CV18: 27777.78 | CW18: 27777.78 | CX18: 27777.78 | CY18: 27777.78 | CZ18: 27777.78 | DA18: 27777.78 | DB18: 27777.78 | DC18: 27777.78 | DD18: 27777.78 | DE18: 27777.78 | DF18: 27777.78 | DG18: 27777.78 | DH18: 27777.78 | DI18: 27777.78 | DJ18: 27777.78 | DK18: 27777.78 | DL18: 27777.78 | DM18: 27777.78 | DN18: 27777.78 | DO18: 27777.78 | DP18: 27777.78 | DQ18: 27777.78 | DR18: 27777.78 | DS18: 27777.78 | DT18: 27777.78 | DV18: =SUM(E21:P21) -> 1200000000 | DW18: =SUM(F21:Q21) -> 1200000000 | DX18: =SUM(G21:R21) -> 1200000000 | DY18: =SUM(H21:S21) -> 1200000000 | DZ18: =SUM(I21:T21) -> 1200000000 | EA18: =SUM(J21:U21) -> 1200000000 | EB18: =SUM(K21:V21) -> 1200000000 | EC18: =SUM(L21:W21) -> 1200000000 | ... EE18: =SUM(N21:Y21) -> 1200000000
B19: Коммунальные услуги | E19: 803333333 | F19: 803333333 | G19: 803333333 | H19: 803333333 | I19: 803333333 | J19: 803333333 | K19: 803333333 | L19: 803333333 | M19: 803333333 | N19: 803333333 | O19: 803333333 | P19: 803333333 | Q19: 803333333 | R19: 803333333 | S19: 803333333 | T19: 803333333 | U19: 803333333 | V19: 803333333 | W19: 803333333 | X19: 803333333 | Y19: 803333333 | Z19: 803333333 | AA19: 803333333 | AB19: 803333333 | AC19: 803333333 | AD19: 803333333 | AE19: 803333333 | AF19: 803333333 | AG19: 803333333 | AH19: 803333333 | AI19: 803333333 | AJ19: 803333333 | AK19: 803333333 | AL19: 803333333 | AM19: 803333333 | AN19: 803333333 | AO19: 803333333 | AP19: 803333333 | AQ19: 803333333 | AR19: 803333333 | AS19: 803333333 | AT19: 803333333 | AU19: 803333333 | AV19: 803333333 | AW19: 803333333 | AX19: 803333333 | AY19: 803333333 | AZ19: 803333333 | BA19: 803333333 | BB19: 803333333 | BC19: 803333333 | BD19: 803333333 | BE19: 803333333 | BF19: 803333333 | BG19: 803333333 | BH19: 803333333 | BI19: 803333333 | BJ19: 803333333 | BK19: 803333333 | BL19: 803333333 | BM19: 803333333 | BN19: 803333333 | BO19: 803333333 | BP19: 803333333 | BQ19: 803333333 | BR19: 803333333 | BS19: 803333333 | BT19: 803333333 | BU19: 803333333 | BV19: 803333333 | BW19: 803333333 | BX19: 803333333 | BY19: 803333333 | BZ19: 803333333 | CA19: 803333333 | CB19: 803333333 | CC19: 803333333 | CD19: 803333333 | CE19: 803333333 | CF19: 803333333 | CG19: 803333333 | CH19: 803333333 | CI19: 803333333 | CJ19: 803333333 | CK19: 803333333 | CL19: 803333333 | CM19: 803333333 | CN19: 803333333 | CO19: 803333333 | CP19: 803333333 | CQ19: 803333333 | CR19: 803333333 | CS19: 803333333 | CT19: 803333333 | CU19: 803333333 | CV19: 803333333 | CW19: 803333333 | CX19: 803333333 | CY19: 803333333 | CZ19: 803333333 | DA19: 803333333 | DB19: 803333333 | DC19: 803333333 | DD19: 803333333 | DE19: 803333333 | DF19: 803333333 | DG19: 803333333 | DH19: 803333333 | DI19: 803333333 | DJ19: 803333333 | DK19: 803333333 | DL19: 803333333 | DM19: 803333333 | DN19: 803333333 | DO19: 803333333 | DP19: 803333333 | DQ19: 803333333 | DR19: 803333333 | DS19: 803333333 | DT19: 803333333
B20: Итого: | D20: =SUM(D11:D18) -> 5.45536e+09 | E20: =SUM(E11:E19) -> 803333333 | F20: =SUM(F11:F19) -> 803333333 | G20: =SUM(G11:G19) -> 803333333 | H20: =SUM(H11:H19) -> 803333333 | I20: =SUM(I11:I19) -> 803333333 | J20: =SUM(J11:J19) -> 803333333 | K20: =SUM(K11:K19) -> 803333333 | L20: =SUM(L11:L19) -> 803333333 | ... DT20: =SUM(DT11:DT19) -> 8.5386593e+08 | DV20: =SUM(E20:P20) -> 9639999996 | DW20: =SUM(F20:Q20) -> 9.6904926e+09 | DX20: =SUM(G20:R20) -> 9.7409852e+09 | DY20: =SUM(H20:S20) -> 9.7914778e+09 | DZ20: =SUM(I20:T20) -> 9.8419704e+09 | EA20: =SUM(J20:U20) -> 9.892463e+09 | EB20: =SUM(K20:V20) -> 9.9429556e+09 | EC20: =SUM(L20:W20) -> 9.9934481e+09 | ... EE20: =SUM(N20:Y20) -> 1.0094433e+10
B21: 1.2.Прочие расходы | E21: 100000000 | F21: 100000000 | G21: 100000000 | H21: 100000000 | I21: 100000000 | J21: 100000000 | K21: 100000000 | L21: 100000000 | M21: 100000000 | N21: 100000000 | O21: 100000000 | P21: 100000000 | Q21: 100000000 | R21: 100000000 | S21: 100000000 | T21: 100000000 | U21: 100000000 | V21: 100000000 | W21: 100000000 | X21: 100000000 | Y21: 100000000 | Z21: 100000000 | AA21: 100000000 | AB21: 100000000 | AC21: 100000000 | AD21: 100000000 | AE21: 100000000 | AF21: 100000000 | AG21: 100000000 | AH21: 100000000 | AI21: 100000000 | AJ21: 100000000 | AK21: 100000000 | AL21: 100000000 | AM21: 100000000 | AN21: 100000000 | AO21: 100000000 | AP21: 100000000 | AQ21: 100000000 | AR21: 100000000 | AS21: 100000000 | AT21: 100000000 | AU21: 100000000 | AV21: 100000000 | AW21: 100000000 | AX21: 100000000 | AY21: 100000000 | AZ21: 100000000 | BA21: 100000000 | BB21: 100000000 | BC21: 100000000 | BD21: 100000000 | BE21: 100000000 | BF21: 100000000 | BG21: 100000000 | BH21: 100000000 | BI21: 100000000 | BJ21: 100000000 | BK21: 100000000 | BL21: 100000000 | BM21: 100000000 | BN21: 100000000 | BO21: 100000000 | BP21: 100000000 | BQ21: 100000000 | BR21: 100000000 | BS21: 100000000 | BT21: 100000000 | BU21: 100000000 | BV21: 100000000 | BW21: 100000000 | BX21: 100000000 | BY21: 100000000 | BZ21: 100000000 | CA21: 100000000 | CB21: 100000000 | CC21: 100000000 | CD21: 100000000 | CE21: 100000000 | CF21: 100000000 | CG21: 100000000 | CH21: 100000000 | CI21: 100000000 | CJ21: 100000000 | CK21: 100000000 | CL21: 100000000 | CM21: 100000000 | CN21: 100000000 | CO21: 100000000 | CP21: 100000000 | CQ21: 100000000 | CR21: 100000000 | CS21: 100000000 | CT21: 100000000 | CU21: 100000000 | CV21: 100000000 | CW21: 100000000 | CX21: 100000000 | CY21: 100000000 | CZ21: 100000000 | DA21: 100000000 | DB21: 100000000 | DC21: 100000000 | DD21: 100000000 | DE21: 100000000 | DF21: 100000000 | DG21: 100000000 | DH21: 100000000 | DI21: 100000000 | DJ21: 100000000 | DK21: 100000000 | DL21: 100000000 | DM21: 100000000 | DN21: 100000000 | DO21: 100000000 | DP21: 100000000 | DQ21: 100000000 | DR21: 100000000 | DS21: 100000000 | DT21: 100000000 | DV21: =SUM(E21:P21) -> 1200000000 | DW21: =SUM(F21:Q21) -> 1200000000 | DX21: =SUM(G21:R21) -> 1200000000 | DY21: =SUM(H21:S21) -> 1200000000 | DZ21: =SUM(I21:T21) -> 1200000000 | EA21: =SUM(J21:U21) -> 1200000000 | EB21: =SUM(K21:V21) -> 1200000000 | EC21: =SUM(L21:W21) -> 1200000000 | ... EE21: =SUM(N21:Y21) -> 1200000000
B22: Управленческие | E22: =E23 -> 171666 | F22: =F23 -> 171666 | G22: =G23 -> 171666 | H22: =H23 -> 171666 | I22: =I23 -> 171666 | J22: =J23 -> 171666 | K22: =K23 -> 171666 | L22: =L23 -> 171666 | ... DT22: =DT23 -> 0
B23: Руководитель проекта | C23: руб. | D23: =SUM(E23:DT23) -> 2059992 | E23: 171666 | F23: 171666 | G23: 171666 | H23: 171666 | I23: 171666 | J23: 171666 | K23: 171666 | L23: 171666 | M23: 171666 | N23: 171666 | O23: 171666 | P23: 171666 | Q23: 0 | R23: 0 | S23: 0 | T23: 0 | U23: 0 | V23: 0 | W23: 0 | X23: 0 | Y23: 0 | Z23: 0 | AA23: 0 | AB23: 0 | AC23: 0 | AD23: 0 | AE23: 0 | AF23: 0 | AG23: 0 | AH23: 0 | AI23: 0 | AJ23: 0 | AK23: 0 | AL23: 0 | AM23: 0 | AN23: 0 | AO23: 0 | AP23: 0 | AQ23: 0 | AR23: 0 | AS23: 0 | AT23: 0 | AU23: 0 | AV23: 0 | AW23: 0 | AX23: 0 | AY23: 0 | AZ23: 0 | BA23: 0 | BB23: 0 | BC23: 0 | BD23: 0 | BE23: 0 | BF23: 0 | BG23: 0 | BH23: 0 | BI23: 0 | BJ23: 0 | BK23: 0 | BL23: 0 | BM23: 0 | BN23: 0 | BO23: 0 | BP23: 0 | BQ23: 0 | BR23: 0 | BS23: 0 | BT23: 0 | BU23: 0 | BV23: 0 | BW23: 0 | BX23: 0 | BY23: 0 | BZ23: 0 | CA23: 0 | CB23: 0 | CC23: 0 | CD23: 0 | CE23: 0 | CF23: 0 | CG23: 0 | CH23: 0 | CI23: 0 | CJ23: 0 | CK23: 0 | CL23: 0 | CM23: 0 | CN23: 0 | CO23: 0 | CP23: 0 | CQ23: 0 | CR23: 0 | CS23: 0 | CT23: 0 | CU23: 0 | CV23: 0 | CW23: 0 | CX23: 0 | CY23: 0 | CZ23: 0 | DA23: 0 | DB23: 0 | DC23: 0 | DD23: 0 | DE23: 0 | DF23: 0 | DG23: 0 | DH23: 0 | DI23: 0 | DJ23: 0 | DK23: 0 | DL23: 0 | DM23: 0 | DN23: 0 | DO23: 0 | DP23: 0 | DQ23: 0 | DR23: 0 | DS23: 0 | DT23: 0 | DV23: =SUM(E23:P23) -> 2059992 | DW23: =SUM(Q23:AB23) -> 0 | DX23: =SUM(AC23:AN23) -> 0 | DY23: =SUM(AO23:AZ23) -> 0 | DZ23: =SUM(BA23:BL23) -> 0 | EA23: =SUM(BM23:BX23) -> 0 | EB23: =SUM(BY23:CJ23) -> 0 | EC23: =SUM(CK23:CV23) -> 0 | ED23: =SUM(CW23:DH23) -> 0 | EE23: =SUM(DI23:DT23) -> 0
B24: Коммерческие | D24: =SUM(D25:D36) -> 0 | E24: =SUM(E25:E36) -> 600000000 | F24: =SUM(F25:F36) -> 600000000 | G24: =SUM(G25:G36) -> 600000000 | H24: =SUM(H25:H36) -> 600000000 | I24: =SUM(I25:I36) -> 600000000 | J24: =SUM(J25:J36) -> 600000000 | K24: =SUM(K25:K36) -> 600000000 | ... DT24: =SUM(DT25:DT36) -> 600000000
B25: Заработные платы | E25: 600000000 | F25: 600000000 | G25: 600000000 | H25: 600000000 | I25: 600000000 | J25: 600000000 | K25: 600000000 | L25: 600000000 | M25: 600000000 | N25: 600000000 | O25: 600000000 | P25: 600000000 | Q25: 600000000 | R25: 600000000 | S25: 600000000 | T25: 600000000 | U25: 600000000 | V25: 600000000 | W25: 600000000 | X25: 600000000 | Y25: 600000000 | Z25: 600000000 | AA25: 600000000 | AB25: 600000000 | AC25: 600000000 | AD25: 600000000 | AE25: 600000000 | AF25: 600000000 | AG25: 600000000 | AH25: 600000000 | AI25: 600000000 | AJ25: 600000000 | AK25: 600000000 | AL25: 600000000 | AM25: 600000000 | AN25: 600000000 | AO25: 600000000 | AP25: 600000000 | AQ25: 600000000 | AR25: 600000000 | AS25: 600000000 | AT25: 600000000 | AU25: 600000000 | AV25: 600000000 | AW25: 600000000 | AX25: 600000000 | AY25: 600000000 | AZ25: 600000000 | BA25: 600000000 | BB25: 600000000 | BC25: 600000000 | BD25: 600000000 | BE25: 600000000 | BF25: 600000000 | BG25: 600000000 | BH25: 600000000 | BI25: 600000000 | BJ25: 600000000 | BK25: 600000000 | BL25: 600000000 | BM25: 600000000 | BN25: 600000000 | BO25: 600000000 | BP25: 600000000 | BQ25: 600000000 | BR25: 600000000 | BS25: 600000000 | BT25: 600000000 | BU25: 600000000 | BV25: 600000000 | BW25: 600000000 | BX25: 600000000 | BY25: 600000000 | BZ25: 600000000 | CA25: 600000000 | CB25: 600000000 | CC25: 600000000 | CD25: 600000000 | CE25: 600000000 | CF25: 600000000 | CG25: 600000000 | CH25: 600000000 | CI25: 600000000 | CJ25: 600000000 | CK25: 600000000 | CL25: 600000000 | CM25: 600000000 | CN25: 600000000 | CO25: 600000000 | CP25: 600000000 | CQ25: 600000000 | CR25: 600000000 | CS25: 600000000 | CT25: 600000000 | CU25: 600000000 | CV25: 600000000 | CW25: 600000000 | CX25: 600000000 | CY25: 600000000 | CZ25: 600000000 | DA25: 600000000 | DB25: 600000000 | DC25: 600000000 | DD25: 600000000 | DE25: 600000000 | DF25: 600000000 | DG25: 600000000 | DH25: 600000000 | DI25: 600000000 | DJ25: 600000000 | DK25: 600000000 | DL25: 600000000 | DM25: 600000000 | DN25: 600000000 | DO25: 600000000 | DP25: 600000000 | DQ25: 600000000 | DR25: 600000000 | DS25: 600000000 | DT25: 600000000
D37: =SUM(D23:D36) -> 2059992 | E37: =SUM(E20,E23:E36,E21) -> 2103504999 | F37: =SUM(F20,F23:F36,F21) -> 2103504999 | G37: =SUM(G20,G23:G36,G21) -> 2103504999 | H37: =SUM(H20,H23:H36,H21) -> 2103504999 | I37: =SUM(I20,I23:I36,I21) -> 2103504999 | J37: =SUM(J20,J23:J36,J21) -> 2103504999 | K37: =SUM(K20,K23:K36,K21) -> 2103504999 | L37: =SUM(L20,L23:L36,L21) -> 2103504999 | ... DT37: =SUM(DT20,DT23:DT36,DT21) -> 2.1538659e+09 | DV37: =SUM(E37:P37) -> 25242059988 | DW37: =SUM(Q37:AB37) -> 2.5845911e+10 | DX37: =SUM(AC37:AN37) -> 2.5845971e+10 | DY37: =SUM(AO37:AZ37) -> 2.5846031e+10 | DZ37: =SUM(BA37:BL37) -> 2.5846091e+10 | EA37: =SUM(BM37:BX37) -> 2.5846151e+10 | EB37: =SUM(BY37:CJ37) -> 2.5846211e+10 | EC37: =SUM(CK37:CV37) -> 2.5846271e+10 | ED37: =SUM(CW37:DH37) -> 2.5846331e+10 | EE37: =SUM(DI37:DT37) -> 2.5846391e+10
B38: Приложение (затраты)'!A1

Sheet Налоги и сборы до
B1: Налоги и сборы, до
E2: 1 год | Q2: 2 год | AC2: 3 год | AO2: 4 год | BA2: 5 год | BM2: 6 год | BY2: 7 год | CK2: 8 год | CW2: 9 год | DI2: 10 год
B3: Наименование | C3: Ед. из. (кв./ руб.) | D3: Сумма | E3: 1 | F3: 2 | G3: 3 | H3: 4 | I3: 5 | J3: 6 | K3: 7 | L3: 8 | M3: 9 | N3: 10 | O3: 11 | P3: 12 | Q3: 1 | R3: 2 | S3: 3 | T3: 4 | U3: 5 | V3: 6 | W3: 7 | X3: 8 | Y3: 9 | Z3: 10 | AA3: 11 | AB3: 12 | AC3: 1 | AD3: 2 | AE3: 3 | AF3: 4 | AG3: 5 | AH3: 6 | AI3: 7 | AJ3: 8 | AK3: 9 | AL3: 10 | AM3: 11 | AN3: 12 | AO3: 1 | AP3: 2 | AQ3: 3 | AR3: 4 | AS3: 5 | AT3: 6 | AU3: 7 | AV3: 8 | AW3: 9 | AX3: 10 | AY3: 11 | AZ3: 12 | BA3: 1 | BB3: 2 | BC3: 3 | BD3: 4 | BE3: 5 | BF3: 6 | BG3: 7 | BH3: 8 | BI3: 9 | BJ3: 10 | BK3: 11 | BL3: 12 | BM3: 1 | BN3: 2 | BO3: 3 | BP3: 4 | BQ3: 5 | BR3: 6 | BS3: 7 | BT3: 8 | BU3: 9 | BV3: 10 | BW3: 11 | BX3: 12 | BY3: 1 | BZ3: 2 | CA3: 3 | CB3: 4 | CC3: 5 | CD3: 6 | CE3: 7 | CF3: 8 | CG3: 9 | CH3: 10 | CI3: 11 | CJ3: 12 | CK3: 1 | CL3: 2 | CM3: 3 | CN3: 4 | CO3: 5 | CP3: 6 | CQ3: 7 | CR3: 8 | CS3: 9 | CT3: 10 | CU3: 11 | CV3: 12 | CW3: 1 | CX3: 2 | CY3: 3 | CZ3: 4 | DA3: 5 | DB3: 6 | DC3: 7 | DD3: 8 | DE3: 9 | DF3: 10 | DG3: 11 | DH3: 12 | DI3: 1 | DJ3: 2 | DK3: 3 | DL3: 4 | DM3: 5 | DN3: 6 | DO3: 7 | DP3: 8 | DQ3: 9 | DR3: 10 | DS3: 11 | DT3: 12
E4: 1 | F4: 2 | G4: 3 | H4: 4 | I4: 5 | J4: 6 | K4: 7 | L4: 8 | M4: 9 | N4: 10 | O4: 11 | P4: 12 | Q4: 13 | R4: 14 | S4: 15 | T4: 16 | U4: 17 | V4: 18 | W4: 19 | X4: 20 | Y4: 21 | Z4: 22 | AA4: 23 | AB4: 24 | AC4: 25 | AD4: 26 | AE4: 27 | AF4: 28 | AG4: 29 | AH4: 30 | AI4: 31 | AJ4: 32 | AK4: 33 | AL4: 34 | AM4: 35 | AN4: 36 | AO4: 1 | AP4: 2 | AQ4: 3 | AR4: 4 | AS4: 5 | AT4: 6 | AU4: 7 | AV4: 8 | AW4: 9 | AX4: 10 | AY4: 11 | AZ4: 12 | BA4: 13 | BB4: 14 | BC4: 15 | BD4: 16 | BE4: 17 | BF4: 18 | BG4: 19 | BH4: 20 | BI4: 21 | BJ4: 22 | BK4: 23 | BL4: 24 | BM4: 25 | BN4: 26 | BO4: 27 | BP4: 28 | BQ4: 29 | BR4: 30 | BS4: 31 | BT4: 32 | BU4: 33 | BV4: 34 | BW4: 35 | BX4: 36 | BY4: 1 | BZ4: 2 | CA4: 3 | CB4: 4 | CC4: 5 | CD4: 6 | CE4: 7 | CF4: 8 | CG4: 9 | CH4: 10 | CI4: 11 | CJ4: 12 | CK4: 13 | CL4: 14 | CM4: 15 | CN4: 16 | CO4: 17 | CP4: 18 | CQ4: 19 | CR4: 20 | CS4: 21 | CT4: 22 | CU4: 23 | CV4: 24 | CW4: 25 | CX4: 26 | CY4: 27 | CZ4: 28 | DA4: 29 | DB4: 30 | DC4: 31 | DD4: 32 | DE4: 33 | DF4: 34 | DG4: 35 | DH4: 36 | DI4: 1 | DJ4: 2 | DK4: 3 | DL4: 4 | DM4: 5 | DN4: 6 | DO4: 7 | DP4: 8 | DQ4: 9 | DR4: 10 | DS4: 11 | DT4: 12
B5: ОСНО налог на прибыль | C5: руб. | D5: =SUM(E5:DT5) -> 4.1007228e+12 | E5: ='Выручка, до'!D9*'Исходные данные'!F14 -> 4.5639268e+09 | F5: ='Выручка, до'!E9*'Исходные данные'!G14 -> 4.6822261e+09 | G5: ='Выручка, до'!F9*'Исходные данные'!H14 -> 4.8037446e+09 | H5: ='Выручка, до'!G9*'Исходные данные'!I14 -> 4.9285738e+09 | I5: ='Выручка, до'!H9*'Исходные данные'!J14 -> 5.0568077e+09 | J5: ='Выручка, до'!I9*'Исходные данные'!K14 -> 5.188543e+09 | K5: ='Выручка, до'!J9*'Исходные данные'!L14 -> 5.3238794e+09 | L5: ='Выручка, до'!K9*'Исходные данные'!M14 -> 5.4629195e+09 | ... DT5: ='Выручка, до'!DS9*'Исходные данные'!DU14 -> 1.1807033e+11
B6: Налог на доходы физических лиц (НДФЛ) | C6: руб. | D6: =SUM(E6:DT6) -> 1.0661879e+13 | E6: ='Выручка, до'!D9*'Исходные данные'!F16 -> 1.186621e+10 | F6: ='Выручка, до'!E9*'Исходные данные'!G16 -> 1.2173788e+10 | G6: ='Выручка, до'!F9*'Исходные данные'!H16 -> 1.2489736e+10 | H6: ='Выручка, до'!G9*'Исходные данные'!I16 -> 1.2814292e+10 | I6: ='Выручка, до'!H9*'Исходные данные'!J16 -> 1.31477e+10 | J6: ='Выручка, до'!I9*'Исходные данные'!K16 -> 1.3490212e+10 | K6: ='Выручка, до'!J9*'Исходные данные'!L16 -> 1.3842086e+10 | L6: ='Выручка, до'!K9*'Исходные данные'!M16 -> 1.4203591e+10 | ... DT6: ='Выручка, до'!DS9*'Исходные данные'!DU16 -> 3.0698285e+11
B7: НДС | C7: руб. | D7: =SUM(E7:DT7) -> 1.4762602e+13 | E7: ='Выручка, до'!D9*'Исходные данные'!F17 -> 1.6430136e+10 | F7: ='Выручка, до'!E9*'Исходные данные'!G17 -> 1.6856014e+10 | G7: ='Выручка, до'!F9*'Исходные данные'!H17 -> 1.7293481e+10 | H7: ='Выручка, до'!G9*'Исходные данные'!I17 -> 1.7742866e+10 | I7: ='Выручка, до'!H9*'Исходные данные'!J17 -> 1.8204508e+10 | J7: ='Выручка, до'!I9*'Исходные данные'!K17 -> 1.8678755e+10 | K7: ='Выручка, до'!J9*'Исходные данные'!L17 -> 1.9165966e+10 | L7: ='Выручка, до'!K9*'Исходные данные'!M17 -> 1.966651e+10 | ... DT7: ='Выручка, до'!DS9*'Исходные данные'!DU17 -> 4.2505317e+11
B8: Налог наа имущество | C8: руб. | D8: =SUM(E8:DT8) -> 6.2728196e+11 | E8: ='Исходные данные'!F15*'Амортизация, до'!I22 -> 6.1396976e+09 | F8: ='Исходные данные'!G15*'Амортизация, до'!J22 -> 6.1226428e+09 | G8: ='Исходные данные'!H15*'Амортизация, до'!K22 -> 6.1056353e+09 | H8: ='Исходные данные'!I15*'Амортизация, до'!L22 -> 6.0886751e+09 | I8: ='Исходные данные'!J15*'Амортизация, до'!M22 -> 6.071762e+09 | J8: ='Исходные данные'!K15*'Амортизация, до'!N22 -> 6.0548958e+09 | K8: ='Исходные данные'!L15*'Амортизация, до'!O22 -> 6.0380765e+09 | L8: ='Исходные данные'!M15*'Амортизация, до'!P22 -> 6.021304e+09 | ... DT8: ='Исходные данные'!DU15*'Амортизация, до'!DX22 -> 4.4094825e+09
B9: Страховой сбор | C9: руб. | D9: =SUM(E9:DT9) -> 5.4721566e+09 | E9: ='Исходные данные'!F22 -> 45613047 | F9: ='Исходные данные'!G22 -> 45613047 | G9: ='Исходные данные'!H22 -> 45613047 | H9: ='Исходные данные'!I22 -> 45613047 | I9: ='Исходные данные'!J22 -> 45613047 | J9: ='Исходные данные'!K22 -> 45613047 | K9: ='Исходные данные'!L22 -> 45613047 | L9: ='Исходные данные'!M22 -> 45613047 | ... DT9: ='Исходные данные'!DU22 -> 45600000
B10: Итого: | C10: руб. | D10: =SUM(E10:DT10) -> 3.0157958e+13 | E10: =SUM(E5:E9) -> 3.9045583e+10 | F10: =SUM(F5:F9) -> 3.9880283e+10 | G10: =SUM(G5:G9) -> 4.073821e+10 | H10: =SUM(H5:H9) -> 4.162002e+10 | I10: =SUM(I5:I9) -> 4.252639e+10 | J10: =SUM(J5:J9) -> 4.3458018e+10 | K10: =SUM(K5:K9) -> 4.4415621e+10 | L10: =SUM(L5:L9) -> 4.5399937e+10 | ... DT10: =SUM(DT5:DT9) -> 8.5456142e+11
B11: Приложение (налоги и взносы)'!A1

Sheet Бухбаланс до
A1: Бухгалтерский баланс | G1: 1 год | S1: 2 год | AE1: 3 год | AQ1: 4 год | BC1: 5 год | BO1: 6 год | CA1: 7 год | CM1: 8 год | CY1: 9 год | DK1: 10 год
G2: 1 | H2: 2 | I2: 3 | J2: 4 | K2: 5 | L2: 6 | M2: 7 | N2: 8 | O2: 9 | P2: 10 | Q2: 11 | R2: 12 | S2: 1 | T2: 2 | U2: 3 | V2: 4 | W2: 5 | X2: 6 | Y2: 7 | Z2: 8 | AA2: 9 | AB2: 10 | AC2: 11 | AD2: 12 | AE2: 1 | AF2: 2 | AG2: 3 | AH2: 4 | AI2: 5 | AJ2: 6 | AK2: 7 | AL2: 8 | AM2: 9 | AN2: 10 | AO2: 11 | AP2: 12 | AQ2: 1 | AR2: 2 | AS2: 3 | AT2: 4 | AU2: 5 | AV2: 6 | AW2: 7 | AX2: 8 | AY2: 9 | AZ2: 10 | BA2: 11 | BB2: 12 | BC2: 1 | BD2: 2 | BE2: 3 | BF2: 4 | BG2: 5 | BH2: 6 | BI2: 7 | BJ2: 8 | BK2: 9 | BL2: 10 | BM2: 11 | BN2: 12 | BO2: 1 | BP2: 2 | BQ2: 3 | BR2: 4 | BS2: 5 | BT2: 6 | BU2: 7 | BV2: 8 | BW2: 9 | BX2: 10 | BY2: 11 | BZ2: 12 | CA2: 1 | CB2: 2 | CC2: 3 | CD2: 4 | CE2: 5 | CF2: 6 | CG2: 7 | CH2: 8 | CI2: 9 | CJ2: 10 | CK2: 11 | CL2: 12 | CM2: 1 | CN2: 2 | CO2: 3 | CP2: 4 | CQ2: 5 | CR2: 6 | CS2: 7 | CT2: 8 | CU2: 9 | CV2: 10 | CW2: 11 | CX2: 12 | CY2: 1 | CZ2: 2 | DA2: 3 | DB2: 4 | DC2: 5 | DD2: 6 | DE2: 7 | DF2: 8 | DG2: 9 | DH2: 10 | DI2: 11 | DJ2: 12 | DK2: 1 | DL2: 2 | DM2: 3 | DN2: 4 | DO2: 5 | DP2: 6 | DQ2: 7 | DR2: 8 | DS2: 9 | DT2: 10 | DU2: 11 | DV2: 12
A3: Наименование показателя | B3: Код | C3: Ед. из. | D3: 1 год | E3: 2 год | F3: 3 год | G3: 1 | H3: 2 | I3: 3 | J3: 4 | K3: 5 | L3: 6 | M3: 7 | N3: 8 | O3: 9 | P3: 10 | Q3: 11 | R3: 12 | S3: 13 | T3: 14 | U3: 15 | V3: 16 | W3: 17 | X3: 18 | Y3: 19 | Z3: 20 | AA3: 21 | AB3: 22 | AC3: 23 | AD3: 24 | AE3: 25 | AF3: 26 | AG3: 27 | AH3: 28 | AI3: 29 | AJ3: 30 | AK3: 31 | AL3: 32 | AM3: 33 | AN3: 34 | AO3: 35 | AP3: 36 | AQ3: 1 | AR3: 2 | AS3: 3 | AT3: 4 | AU3: 5 | AV3: 6 | AW3: 7 | AX3: 8 | AY3: 9 | AZ3: 10 | BA3: 11 | BB3: 12 | BC3: 13 | BD3: 14 | BE3: 15 | BF3: 16 | BG3: 17 | BH3: 18 | BI3: 19 | BJ3: 20 | BK3: 21 | BL3: 22 | BM3: 23 | BN3: 24 | BO3: 25 | BP3: 26 | BQ3: 27 | BR3: 28 | BS3: 29 | BT3: 30 | BU3: 31 | BV3: 32 | BW3: 33 | BX3: 34 | BY3: 35 | BZ3: 36 | CA3: 1 | CB3: 2 | CC3: 3 | CD3: 4 | CE3: 5 | CF3: 6 | CG3: 7 | CH3: 8 | CI3: 9 | CJ3: 10 | CK3: 11 | CL3: 12 | CM3: 13 | CN3: 14 | CO3: 15 | CP3: 16 | CQ3: 17 | CR3: 18 | CS3: 19 | CT3: 20 | CU3: 21 | CV3: 22 | CW3: 23 | CX3: 24 | CY3: 25 | CZ3: 26 | DA3: 27 | DB3: 28 | DC3: 29 | DD3: 30 | DE3: 31 | DF3: 32 | DG3: 33 | DH3: 34 | DI3: 35 | DJ3: 36 | DK3: 1 | DL3: 2 | DM3: 3 | DN3: 4 | DO3: 5 | DP3: 6 | DQ3: 7 | DR3: 8 | DS3: 9 | DT3: 10 | DU3: 11 | DV3: 12
A4: АКТИВ
A5: I. ВНЕОБОРОТНЫЕ АКТИВЫ
A6: Нематериальные активы | B6: 1110 | C6: руб. | D6: =SUM(G6:R6) -> 0 | E6: =SUM(S6:AD6) -> 0 | F6: =SUM(AE6:AP6) -> 0 | G6: 0 | H6: 0 | I6: 0 | J6: 0 | K6: 0 | L6: 0 | M6: 0 | N6: 0 | O6: 0 | P6: 0 | Q6: 0 | R6: 0 | S6: 0 | T6: 0 | U6: 0 | V6: 0 | W6: 0 | X6: 0 | Y6: 0 | Z6: 0 | AA6: 0 | AB6: 0 | AC6: 0 | AD6: 0 | AE6: 0 | AF6: 0 | AG6: 0 | AH6: 0 | AI6: 0 | AJ6: 0 | AK6: 0 | AL6: 0 | AM6: 0 | AN6: 0 | AO6: 0 | AP6: 0 | AQ6: 0 | AR6: 0 | AS6: 0 | AT6: 0 | AU6: 0 | AV6: 0 | AW6: 0 | AX6: 0 | AY6: 0 | AZ6: 0 | BA6: 0 | BB6: 0 | BC6: 0 | BD6: 0 | BE6: 0 | BF6: 0 | BG6: 0 | BH6: 0 | BI6: 0 | BJ6: 0 | BK6: 0 | BL6: 0 | BM6: 0 | BN6: 0 | BO6: 0 | BP6: 0 | BQ6: 0 | BR6: 0 | BS6: 0 | BT6: 0 | BU6: 0 | BV6: 0 | BW6: 0 | BX6: 0 | BY6: 0 | BZ6: 0 | CA6: 0 | CB6: 0 | CC6: 0 | CD6: 0 | CE6: 0 | CF6: 0 | CG6: 0 | CH6: 0 | CI6: 0 | CJ6: 0 | CK6: 0 | CL6: 0 | CM6: 0 | CN6: 0 | CO6: 0 | CP6: 0 | CQ6: 0 | CR6: 0 | CS6: 0 | CT6: 0 | CU6: 0 | CV6: 0 | CW6: 0 | CX6: 0 | CY6: 0 | CZ6: 0 | DA6: 0 | DB6: 0 | DC6: 0 | DD6: 0 | DE6: 0 | DF6: 0 | DG6: 0 | DH6: 0 | DI6: 0 | DJ6: 0 | DK6: 0 | DL6: 0 | DM6: 0 | DN6: 0 | DO6: 0 | DP6: 0 | DQ6: 0 | DR6: 0 | DS6: 0 | DT6: 0 | DU6: 0 | DV6: 0
A7: Результаты исследований и разработок | B7: 1120 | C7: руб. | D7: =SUM(G7:R7) -> 0 | E7: =SUM(S7:AD7) -> 0 | F7: =SUM(AE7:AP7) -> 0 | G7: 0 | H7: 0 | I7: 0 | J7: 0 | K7: 0 | L7: 0 | M7: 0 | N7: 0 | O7: 0 | P7: 0 | Q7: 0 | R7: 0 | S7: 0 | T7: 0 | U7: 0 | V7: 0 | W7: 0 | X7: 0 | Y7: 0 | Z7: 0 | AA7: 0 | AB7: 0 | AC7: 0 | AD7: 0 | AE7: 0 | AF7: 0 | AG7: 0 | AH7: 0 | AI7: 0 | AJ7: 0 | AK7: 0 | AL7: 0 | AM7: 0 | AN7: 0 | AO7: 0 | AP7: 0 | AQ7: 0 | AR7: 0 | AS7: 0 | AT7: 0 | AU7: 0 | AV7: 0 | AW7: 0 | AX7: 0 | AY7: 0 | AZ7: 0 | BA7: 0 | BB7: 0 | BC7: 0 | BD7: 0 | BE7: 0 | BF7: 0 | BG7: 0 | BH7: 0 | BI7: 0 | BJ7: 0 | BK7: 0 | BL7: 0 | BM7: 0 | BN7: 0 | BO7: 0 | BP7: 0 | BQ7: 0 | BR7: 0 | BS7: 0 | BT7: 0 | BU7: 0 | BV7: 0 | BW7: 0 | BX7: 0 | BY7: 0 | BZ7: 0 | CA7: 0 | CB7: 0 | CC7: 0 | CD7: 0 | CE7: 0 | CF7: 0 | CG7: 0 | CH7: 0 | CI7: 0 | CJ7: 0 | CK7: 0 | CL7: 0 | CM7: 0 | CN7: 0 | CO7: 0 | CP7: 0 | CQ7: 0 | CR7: 0 | CS7: 0 | CT7: 0 | CU7: 0 | CV7: 0 | CW7: 0 | CX7: 0 | CY7: 0 | CZ7: 0 | DA7: 0 | DB7: 0 | DC7: 0 | DD7: 0 | DE7: 0 | DF7: 0 | DG7: 0 | DH7: 0 | DI7: 0 | DJ7: 0 | DK7: 0 | DL7: 0 | DM7: 0 | DN7: 0 | DO7: 0 | DP7: 0 | DQ7: 0 | DR7: 0 | DS7: 0 | DT7: 0 | DU7: 0 | DV7: 0
A8: Нематериальные поисковые активы | B8: 1130 | C8: руб. | D8: =SUM(G8:R8) -> 0 | E8: =SUM(S8:AD8) -> 0 | F8: =SUM(AE8:AP8) -> 0 | G8: 0 | H8: 0 | I8: 0 | J8: 0 | K8: 0 | L8: 0 | M8: 0 | N8: 0 | O8: 0 | P8: 0 | Q8: 0 | R8: 0 | S8: 0 | T8: 0 | U8: 0 | V8: 0 | W8: 0 | X8: 0 | Y8: 0 | Z8: 0 | AA8: 0 | AB8: 0 | AC8: 0 | AD8: 0 | AE8: 0 | AF8: 0 | AG8: 0 | AH8: 0 | AI8: 0 | AJ8: 0 | AK8: 0 | AL8: 0 | AM8: 0 | AN8: 0 | AO8: 0 | AP8: 0 | AQ8: 0 | AR8: 0 | AS8: 0 | AT8: 0 | AU8: 0 | AV8: 0 | AW8: 0 | AX8: 0 | AY8: 0 | AZ8: 0 | BA8: 0 | BB8: 0 | BC8: 0 | BD8: 0 | BE8: 0 | BF8: 0 | BG8: 0 | BH8: 0 | BI8: 0 | BJ8: 0 | BK8: 0 | BL8: 0 | BM8: 0 | BN8: 0 | BO8: 0 | BP8: 0 | BQ8: 0 | BR8: 0 | BS8: 0 | BT8: 0 | BU8: 0 | BV8: 0 | BW8: 0 | BX8: 0 | BY8: 0 | BZ8: 0 | CA8: 0 | CB8: 0 | CC8: 0 | CD8: 0 | CE8: 0 | CF8: 0 | CG8: 0 | CH8: 0 | CI8: 0 | CJ8: 0 | CK8: 0 | CL8: 0 | CM8: 0 | CN8: 0 | CO8: 0 | CP8: 0 | CQ8: 0 | CR8: 0 | CS8: 0 | CT8: 0 | CU8: 0 | CV8: 0 | CW8: 0 | CX8: 0 | CY8: 0 | CZ8: 0 | DA8: 0 | DB8: 0 | DC8: 0 | DD8: 0 | DE8: 0 | DF8: 0 | DG8: 0 | DH8: 0 | DI8: 0 | DJ8: 0 | DK8: 0 | DL8: 0 | DM8: 0 | DN8: 0 | DO8: 0 | DP8: 0 | DQ8: 0 | DR8: 0 | DS8: 0 | DT8: 0 | DU8: 0 | DV8: 0
A9: Материальные поисковые активы | B9: 1140 | C9: руб. | D9: =SUM(G9:R9) -> 0 | E9: =SUM(S9:AD9) -> 0 | F9: =SUM(AE9:AP9) -> 0 | G9: 0 | H9: 0 | I9: 0 | J9: 0 | K9: 0 | L9: 0 | M9: 0 | N9: 0 | O9: 0 | P9: 0 | Q9: 0 | R9: 0 | S9: 0 | T9: 0 | U9: 0 | V9: 0 | W9: 0 | X9: 0 | Y9: 0 | Z9: 0 | AA9: 0 | AB9: 0 | AC9: 0 | AD9: 0 | AE9: 0 | AF9: 0 | AG9: 0 | AH9: 0 | AI9: 0 | AJ9: 0 | AK9: 0 | AL9: 0 | AM9: 0 | AN9: 0 | AO9: 0 | AP9: 0 | AQ9: 0 | AR9: 0 | AS9: 0 | AT9: 0 | AU9: 0 | AV9: 0 | AW9: 0 | AX9: 0 | AY9: 0 | AZ9: 0 | BA9: 0 | BB9: 0 | BC9: 0 | BD9: 0 | BE9: 0 | BF9: 0 | BG9: 0 | BH9: 0 | BI9: 0 | BJ9: 0 | BK9: 0 | BL9: 0 | BM9: 0 | BN9: 0 | BO9: 0 | BP9: 0 | BQ9: 0 | BR9: 0 | BS9: 0 | BT9: 0 | BU9: 0 | BV9: 0 | BW9: 0 | BX9: 0 | BY9: 0 | BZ9: 0 | CA9: 0 | CB9: 0 | CC9: 0 | CD9: 0 | CE9: 0 | CF9: 0 | CG9: 0 | CH9: 0 | CI9: 0 | CJ9: 0 | CK9: 0 | CL9: 0 | CM9: 0 | CN9: 0 | CO9: 0 | CP9: 0 | CQ9: 0 | CR9: 0 | CS9: 0 | CT9: 0 | CU9: 0 | CV9: 0 | CW9: 0 | CX9: 0 | CY9: 0 | CZ9: 0 | DA9: 0 | DB9: 0 | DC9: 0 | DD9: 0 | DE9: 0 | DF9: 0 | DG9: 0 | DH9: 0 | DI9: 0 | DJ9: 0 | DK9: 0 | DL9: 0 | DM9: 0 | DN9: 0 | DO9: 0 | DP9: 0 | DQ9: 0 | DR9: 0 | DS9: 0 | DT9: 0 | DU9: 0 | DV9: 0
A10: Основные средства | B10: 1150 | C10: руб. | D10: =SUM(G10:R10) -> 35520000000000 | E10: =SUM(S10:AD10) -> 35520000000000 | F10: =SUM(AE10:AP10) -> 35520000000000 | G10: ='Амортизация, до'!I18 -> 2960000000000 | H10: ='Амортизация, до'!J18 -> 2960000000000 | I10: ='Амортизация, до'!K18 -> 2960000000000 | J10: ='Амортизация, до'!L18 -> 2960000000000 | K10: ='Амортизация, до'!M18 -> 2960000000000 | L10: ='Амортизация, до'!N18 -> 2960000000000 | M10: ='Амортизация, до'!O18 -> 2960000000000 | N10: ='Амортизация, до'!P18 -> 2960000000000 | ... DV10: ='Амортизация, до'!DX18 -> 2960000000000
A11: Доходные вложения в материальные ценности | B11: 1160 | C11: руб. | D11: =SUM(G11:R11) -> 0 | E11: =SUM(S11:AD11) -> 0 | F11: =SUM(AE11:AP11) -> 0 | G11: 0 | H11: 0 | I11: 0 | J11: 0 | K11: 0 | L11: 0 | M11: 0 | N11: 0 | O11: 0 | P11: 0 | Q11: 0 | R11: 0 | S11: 0 | T11: 0 | U11: 0 | V11: 0 | W11: 0 | X11: 0 | Y11: 0 | Z11: 0 | AA11: 0 | AB11: 0 | AC11: 0 | AD11: 0 | AE11: 0 | AF11: 0 | AG11: 0 | AH11: 0 | AI11: 0 | AJ11: 0 | AK11: 0 | AL11: 0 | AM11: 0 | AN11: 0 | AO11: 0 | AP11: 0 | AQ11: 0 | AR11: 0 | AS11: 0 | AT11: 0 | AU11: 0 | AV11: 0 | AW11: 0 | AX11: 0 | AY11: 0 | AZ11: 0 | BA11: 0 | BB11: 0 | BC11: 0 | BD11: 0 | BE11: 0 | BF11: 0 | BG11: 0 | BH11: 0 | BI11: 0 | BJ11: 0 | BK11: 0 | BL11: 0 | BM11: 0 | BN11: 0 | BO11: 0 | BP11: 0 | BQ11: 0 | BR11: 0 | BS11: 0 | BT11: 0 | BU11: 0 | BV11: 0 | BW11: 0 | BX11: 0 | BY11: 0 | BZ11: 0 | CA11: 0 | CB11: 0 | CC11: 0 | CD11: 0 | CE11: 0 | CF11: 0 | CG11: 0 | CH11: 0 | CI11: 0 | CJ11: 0 | CK11: 0 | CL11: 0 | CM11: 0 | CN11: 0 | CO11: 0 | CP11: 0 | CQ11: 0 | CR11: 0 | CS11: 0 | CT11: 0 | CU11: 0 | CV11: 0 | CW11: 0 | CX11: 0 | CY11: 0 | CZ11: 0 | DA11: 0 | DB11: 0 | DC11: 0 | DD11: 0 | DE11: 0 | DF11: 0 | DG11: 0 | DH11: 0 | DI11: 0 | DJ11: 0 | DK11: 0 | DL11: 0 | DM11: 0 | DN11: 0 | DO11: 0 | DP11: 0 | DQ11: 0 | DR11: 0 | DS11: 0 | DT11: 0 | DU11: 0 | DV11: 0
A12: Финансовые вложения | B12: 1170 | C12: руб. | D12: =SUM(G12:R12) -> 0 | E12: =SUM(S12:AD12) -> 0 | F12: =SUM(AE12:AP12) -> 0 | G12: 0 | H12: 0 | I12: 0 | J12: 0 | K12: 0 | L12: 0 | M12: 0 | N12: 0 | O12: 0 | P12: 0 | Q12: 0 | R12: 0 | S12: 0 | T12: 0 | U12: 0 | V12: 0 | W12: 0 | X12: 0 | Y12: 0 | Z12: 0 | AA12: 0 | AB12: 0 | AC12: 0 | AD12: 0 | AE12: 0 | AF12: 0 | AG12: 0 | AH12: 0 | AI12: 0 | AJ12: 0 | AK12: 0 | AL12: 0 | AM12: 0 | AN12: 0 | AO12: 0 | AP12: 0 | AQ12: 0 | AR12: 0 | AS12: 0 | AT12: 0 | AU12: 0 | AV12: 0 | AW12: 0 | AX12: 0 | AY12: 0 | AZ12: 0 | BA12: 0 | BB12: 0 | BC12: 0 | BD12: 0 | BE12: 0 | BF12: 0 | BG12: 0 | BH12: 0 | BI12: 0 | BJ12: 0 | BK12: 0 | BL12: 0 | BM12: 0 | BN12: 0 | BO12: 0 | BP12: 0 | BQ12: 0 | BR12: 0 | BS12: 0 | BT12: 0 | BU12: 0 | BV12: 0 | BW12: 0 | BX12: 0 | BY12: 0 | BZ12: 0 | CA12: 0 | CB12: 0 | CC12: 0 | CD12: 0 | CE12: 0 | CF12: 0 | CG12: 0 | CH12: 0 | CI12: 0 | CJ12: 0 | CK12: 0 | CL12: 0 | CM12: 0 | CN12: 0 | CO12: 0 | CP12: 0 | CQ12: 0 | CR12: 0 | CS12: 0 | CT12: 0 | CU12: 0 | CV12: 0 | CW12: 0 | CX12: 0 | CY12: 0 | CZ12: 0 | DA12: 0 | DB12: 0 | DC12: 0 | DD12: 0 | DE12: 0 | DF12: 0 | DG12: 0 | DH12: 0 | DI12: 0 | DJ12: 0 | DK12: 0 | DL12: 0 | DM12: 0 | DN12: 0 | DO12: 0 | DP12: 0 | DQ12: 0 | DR12: 0 | DS12: 0 | DT12: 0 | DU12: 0 | DV12: 0
A13: Отложенные налоговые активы | B13: 1180 | C13: руб. | D13: =SUM(G13:R13) -> 0 | E13: =SUM(S13:AD13) -> 0 | F13: =SUM(AE13:AP13) -> 0 | G13: 0 | H13: 0 | I13: 0 | J13: 0 | K13: 0 | L13: 0 | M13: 0 | N13: 0 | O13: 0 | P13: 0 | Q13: 0 | R13: 0 | S13: 0 | T13: 0 | U13: 0 | V13: 0 | W13: 0 | X13: 0 | Y13: 0 | Z13: 0 | AA13: 0 | AB13: 0 | AC13: 0 | AD13: 0 | AE13: 0 | AF13: 0 | AG13: 0 | AH13: 0 | AI13: 0 | AJ13: 0 | AK13: 0 | AL13: 0 | AM13: 0 | AN13: 0 | AO13: 0 | AP13: 0 | AQ13: 0 | AR13: 0 | AS13: 0 | AT13: 0 | AU13: 0 | AV13: 0 | AW13: 0 | AX13: 0 | AY13: 0 | AZ13: 0 | BA13: 0 | BB13: 0 | BC13: 0 | BD13: 0 | BE13: 0 | BF13: 0 | BG13: 0 | BH13: 0 | BI13: 0 | BJ13: 0 | BK13: 0 | BL13: 0 | BM13: 0 | BN13: 0 | BO13: 0 | BP13: 0 | BQ13: 0 | BR13: 0 | BS13: 0 | BT13: 0 | BU13: 0 | BV13: 0 | BW13: 0 | BX13: 0 | BY13: 0 | BZ13: 0 | CA13: 0 | CB13: 0 | CC13: 0 | CD13: 0 | CE13: 0 | CF13: 0 | CG13: 0 | CH13: 0 | CI13: 0 | CJ13: 0 | CK13: 0 | CL13: 0 | CM13: 0 | CN13: 0 | CO13: 0 | CP13: 0 | CQ13: 0 | CR13: 0 | CS13: 0 | CT13: 0 | CU13: 0 | CV13: 0 | CW13: 0 | CX13: 0 | CY13: 0 | CZ13: 0 | DA13: 0 | DB13: 0 | DC13: 0 | DD13: 0 | DE13: 0 | DF13: 0 | DG13: 0 | DH13: 0 | DI13: 0 | DJ13: 0 | DK13: 0 | DL13: 0 | DM13: 0 | DN13: 0 | DO13: 0 | DP13: 0 | DQ13: 0 | DR13: 0 | DS13: 0 | DT13: 0 | DU13: 0 | DV13: 0
A14: Прочие внеоборотные активы | B14: 1190 | C14: руб. | D14: =SUM(G14:R14) -> 0 | E14: =SUM(S14:AD14) -> 0 | F14: =SUM(AE14:AP14) -> 0 | G14: 0 | H14: 0 | I14: 0 | J14: 0 | K14: 0 | L14: 0 | M14: 0 | N14: 0 | O14: 0 | P14: 0 | Q14: 0 | R14: 0 | S14: 0 | T14: 0 | U14: 0 | V14: 0 | W14: 0 | X14: 0 | Y14: 0 | Z14: 0 | AA14: 0 | AB14: 0 | AC14: 0 | AD14: 0 | AE14: 0 | AF14: 0 | AG14: 0 | AH14: 0 | AI14: 0 | AJ14: 0 | AK14: 0 | AL14: 0 | AM14: 0 | AN14: 0 | AO14: 0 | AP14: 0 | AQ14: 0 | AR14: 0 | AS14: 0 | AT14: 0 | AU14: 0 | AV14: 0 | AW14: 0 | AX14: 0 | AY14: 0 | AZ14: 0 | BA14: 0 | BB14: 0 | BC14: 0 | BD14: 0 | BE14: 0 | BF14: 0 | BG14: 0 | BH14: 0 | BI14: 0 | BJ14: 0 | BK14: 0 | BL14: 0 | BM14: 0 | BN14: 0 | BO14: 0 | BP14: 0 | BQ14: 0 | BR14: 0 | BS14: 0 | BT14: 0 | BU14: 0 | BV14: 0 | BW14: 0 | BX14: 0 | BY14: 0 | BZ14: 0 | CA14: 0 | CB14: 0 | CC14: 0 | CD14: 0 | CE14: 0 | CF14: 0 | CG14: 0 | CH14: 0 | CI14: 0 | CJ14: 0 | CK14: 0 | CL14: 0 | CM14: 0 | CN14: 0 | CO14: 0 | CP14: 0 | CQ14: 0 | CR14: 0 | CS14: 0 | CT14: 0 | CU14: 0 | CV14: 0 | CW14: 0 | CX14: 0 | CY14: 0 | CZ14: 0 | DA14: 0 | DB14: 0 | DC14: 0 | DD14: 0 | DE14: 0 | DF14: 0 | DG14: 0 | DH14: 0 | DI14: 0 | DJ14: 0 | DK14: 0 | DL14: 0 | DM14: 0 | DN14: 0 | DO14: 0 | DP14: 0 | DQ14: 0 | DR14: 0 | DS14: 0 | DT14: 0 | DU14: 0 | DV14: 0
A15: Итого по разделу I | B15: 1100 | C15: руб. | D15: =SUM(D6:D14) -> 35520000000000 | E15: =SUM(E6:E14) -> 35520000000000 | F15: =SUM(F6:F14) -> 35520000000000 | G15: =SUM(G6:G14) -> 2960000000000 | H15: =SUM(H6:H14) -> 2960000000000 | I15: =SUM(I6:I14) -> 2960000000000 | J15: =SUM(J6:J14) -> 2960000000000 | K15: =SUM(K6:K14) -> 2960000000000 | ... DV15: =SUM(DV6:DV14) -> 2960000000000
A16: II. ОБОРОТНЫЕ АКТИВЫ
A17: Запасы | B17: 1210 | C17: руб. | D17: =SUM(G17:R17) -> 0 | E17: =SUM(S17:AD17) -> 0 | F17: =SUM(AE17:AP17) -> 0 | G17: 0 | H17: 0 | I17: 0 | J17: 0 | K17: 0 | L17: 0 | M17: 0 | N17: 0 | O17: 0 | P17: 0 | Q17: 0 | R17: 0 | S17: 0 | T17: 0 | U17: 0 | V17: 0 | W17: 0 | X17: 0 | Y17: 0 | Z17: 0 | AA17: 0 | AB17: 0 | AC17: 0 | AD17: 0 | AE17: 0 | AF17: 0 | AG17: 0 | AH17: 0 | AI17: 0 | AJ17: 0 | AK17: 0 | AL17: 0 | AM17: 0 | AN17: 0 | AO17: 0 | AP17: 0 | AQ17: 0 | AR17: 0 | AS17: 0 | AT17: 0 | AU17: 0 | AV17: 0 | AW17: 0 | AX17: 0 | AY17: 0 | AZ17: 0 | BA17: 0 | BB17: 0 | BC17: 0 | BD17: 0 | BE17: 0 | BF17: 0 | BG17: 0 | BH17: 0 | BI17: 0 | BJ17: 0 | BK17: 0 | BL17: 0 | BM17: 0 | BN17: 0 | BO17: 0 | BP17: 0 | BQ17: 0 | BR17: 0 | BS17: 0 | BT17: 0 | BU17: 0 | BV17: 0 | BW17: 0 | BX17: 0 | BY17: 0 | BZ17: 0 | CA17: 0 | CB17: 0 | CC17: 0 | CD17: 0 | CE17: 0 | CF17: 0 | CG17: 0 | CH17: 0 | CI17: 0 | CJ17: 0 | CK17: 0 | CL17: 0 | CM17: 0 | CN17: 0 | CO17: 0 | CP17: 0 | CQ17: 0 | CR17: 0 | CS17: 0 | CT17: 0 | CU17: 0 | CV17: 0 | CW17: 0 | CX17: 0 | CY17: 0 | CZ17: 0 | DA17: 0 | DB17: 0 | DC17: 0 | DD17: 0 | DE17: 0 | DF17: 0 | DG17: 0 | DH17: 0 | DI17: 0 | DJ17: 0 | DK17: 0 | DL17: 0 | DM17: 0 | DN17: 0 | DO17: 0 | DP17: 0 | DQ17: 0 | DR17: 0 | DS17: 0 | DT17: 0 | DU17: 0 | DV17: 0
A18: Налог на добавленную стоимость по приобретенным ценностям | B18: 1220 | C18: руб. | D18: =SUM(G18:R18) -> 0 | E18: =SUM(S18:AD18) -> 0 | F18: =SUM(AE18:AP18) -> 0 | G18: 0 | H18: 0 | I18: 0 | J18: 0 | K18: 0 | L18: 0 | M18: 0 | N18: 0 | O18: 0 | P18: 0 | Q18: 0 | R18: 0 | S18: 0 | T18: 0 | U18: 0 | V18: 0 | W18: 0 | X18: 0 | Y18: 0 | Z18: 0 | AA18: 0 | AB18: 0 | AC18: 0 | AD18: 0 | AE18: 0 | AF18: 0 | AG18: 0 | AH18: 0 | AI18: 0 | AJ18: 0 | AK18: 0 | AL18: 0 | AM18: 0 | AN18: 0 | AO18: 0 | AP18: 0 | AQ18: 0 | AR18: 0 | AS18: 0 | AT18: 0 | AU18: 0 | AV18: 0 | AW18: 0 | AX18: 0 | AY18: 0 | AZ18: 0 | BA18: 0 | BB18: 0 | BC18: 0 | BD18: 0 | BE18: 0 | BF18: 0 | BG18: 0 | BH18: 0 | BI18: 0 | BJ18: 0 | BK18: 0 | BL18: 0 | BM18: 0 | BN18: 0 | BO18: 0 | BP18: 0 | BQ18: 0 | BR18: 0 | BS18: 0 | BT18: 0 | BU18: 0 | BV18: 0 | BW18: 0 | BX18: 0 | BY18: 0 | BZ18: 0 | CA18: 0 | CB18: 0 | CC18: 0 | CD18: 0 | CE18: 0 | CF18: 0 | CG18: 0 | CH18: 0 | CI18: 0 | CJ18: 0 | CK18: 0 | CL18: 0 | CM18: 0 | CN18: 0 | CO18: 0 | CP18: 0 | CQ18: 0 | CR18: 0 | CS18: 0 | CT18: 0 | CU18: 0 | CV18: 0 | CW18: 0 | CX18: 0 | CY18: 0 | CZ18: 0 | DA18: 0 | DB18: 0 | DC18: 0 | DD18: 0 | DE18: 0 | DF18: 0 | DG18: 0 | DH18: 0 | DI18: 0 | DJ18: 0 | DK18: 0 | DL18: 0 | DM18: 0 | DN18: 0 | DO18: 0 | DP18: 0 | DQ18: 0 | DR18: 0 | DS18: 0 | DT18: 0 | DU18: 0 | DV18: 0
A19: Дебиторская задолженность | B19: 1230 | C19: руб. | D19: =SUM(G19:R19) -> 8.973817e+13 | E19: =SUM(S19:AD19) -> 1.0050918e+15 | F19: =SUM(AE19:AP19) -> 1.0216555e+15 | G19: ='Отчет о фин. рез до'!E21 -> 9.1278535e+10 | H19: ='Отчет о фин. рез до'!F21 -> 1.8492306e+11 | I19: ='Отчет о фин. рез до'!G21 -> 2.8099795e+11 | J19: ='Отчет о фин. рез до'!H21 -> 3.7956943e+11 | K19: ='Отчет о фин. рез до'!I21 -> 4.8070558e+11 | L19: ='Отчет о фин. рез до'!J21 -> 5.8447644e+11 | M19: ='Отчет о фин. рез до'!K21 -> 6.9095403e+11 | N19: ='Отчет о фин. рез до'!L21 -> 8.0021242e+11 | ... DV19: ='Отчет о фин. рез до'!DT21 -> 5.0686689e+13
A20: Финансовые вложения (за исключением денежных эквивалентов) | B20: 1240 | C20: руб. | D20: =SUM(G20:R20) -> 0 | E20: =SUM(S20:AD20) -> 0 | F20: =SUM(AE20:AP20) -> 0 | G20: 0 | H20: 0 | I20: 0 | J20: 0 | K20: 0 | L20: 0 | M20: 0 | N20: 0 | O20: 0 | P20: 0 | Q20: 0 | R20: 0 | S20: 0 | T20: 0 | U20: 0 | V20: 0 | W20: 0 | X20: 0 | Y20: 0 | Z20: 0 | AA20: 0 | AB20: 0 | AC20: 0 | AD20: 0 | AE20: 0 | AF20: 0 | AG20: 0 | AH20: 0 | AI20: 0 | AJ20: 0 | AK20: 0 | AL20: 0 | AM20: 0 | AN20: 0 | AO20: 0 | AP20: 0 | AQ20: 0 | AR20: 0 | AS20: 0 | AT20: 0 | AU20: 0 | AV20: 0 | AW20: 0 | AX20: 0 | AY20: 0 | AZ20: 0 | BA20: 0 | BB20: 0 | BC20: 0 | BD20: 0 | BE20: 0 | BF20: 0 | BG20: 0 | BH20: 0 | BI20: 0 | BJ20: 0 | BK20: 0 | BL20: 0 | BM20: 0 | BN20: 0 | BO20: 0 | BP20: 0 | BQ20: 0 | BR20: 0 | BS20: 0 | BT20: 0 | BU20: 0 | BV20: 0 | BW20: 0 | BX20: 0 | BY20: 0 | BZ20: 0 | CA20: 0 | CB20: 0 | CC20: 0 | CD20: 0 | CE20: 0 | CF20: 0 | CG20: 0 | CH20: 0 | CI20: 0 | CJ20: 0 | CK20: 0 | CL20: 0 | CM20: 0 | CN20: 0 | CO20: 0 | CP20: 0 | CQ20: 0 | CR20: 0 | CS20: 0 | CT20: 0 | CU20: 0 | CV20: 0 | CW20: 0 | CX20: 0 | CY20: 0 | CZ20: 0 | DA20: 0 | DB20: 0 | DC20: 0 | DD20: 0 | DE20: 0 | DF20: 0 | DG20: 0 | DH20: 0 | DI20: 0 | DJ20: 0 | DK20: 0 | DL20: 0 | DM20: 0 | DN20: 0 | DO20: 0 | DP20: 0 | DQ20: 0 | DR20: 0 | DS20: 0 | DT20: 0 | DU20: 0 | DV20: 0
A21: Денежные средства и денежные эквиваленты | B21: 1250 | C21: руб. | D21: =SUM(G21:R21) -> 0 | E21: =SUM(S21:AD21) -> 0 | F21: =SUM(AE21:AP21) -> 0 | G21: =G27 -> 0 | H21: =H27 -> 0 | I21: =I27 -> 0 | J21: =J27 -> 0 | K21: =K27 -> 0 | L21: =L27 -> 0 | M21: =M27 -> 0 | N21: =N27 -> 0 | ... DV21: =DV27 -> 10000
A22: Прочие оборотные активы | B22: 1260 | C22: руб. | D22: =SUM(G22:R22) -> 0 | E22: =SUM(S22:AD22) -> 0 | F22: =SUM(AE22:AP22) -> 0 | G22: 0 | H22: 0 | I22: 0 | J22: 0 | K22: 0 | L22: 0 | M22: 0 | N22: 0 | O22: 0 | P22: 0 | Q22: 0 | R22: 0 | S22: 0 | T22: 0 | U22: 0 | V22: 0 | W22: 0 | X22: 0 | Y22: 0 | Z22: 0 | AA22: 0 | AB22: 0 | AC22: 0 | AD22: 0 | AE22: 0 | AF22: 0 | AG22: 0 | AH22: 0 | AI22: 0 | AJ22: 0 | AK22: 0 | AL22: 0 | AM22: 0 | AN22: 0 | AO22: 0 | AP22: 0 | AQ22: 0 | AR22: 0 | AS22: 0 | AT22: 0 | AU22: 0 | AV22: 0 | AW22: 0 | AX22: 0 | AY22: 0 | AZ22: 0 | BA22: 0 | BB22: 0 | BC22: 0 | BD22: 0 | BE22: 0 | BF22: 0 | BG22: 0 | BH22: 0 | BI22: 0 | BJ22: 0 | BK22: 0 | BL22: 0 | BM22: 0 | BN22: 0 | BO22: 0 | BP22: 0 | BQ22: 0 | BR22: 0 | BS22: 0 | BT22: 0 | BU22: 0 | BV22: 0 | BW22: 0 | BX22: 0 | BY22: 0 | BZ22: 0 | CA22: 0 | CB22: 0 | CC22: 0 | CD22: 0 | CE22: 0 | CF22: 0 | CG22: 0 | CH22: 0 | CI22: 0 | CJ22: 0 | CK22: 0 | CL22: 0 | CM22: 0 | CN22: 0 | CO22: 0 | CP22: 0 | CQ22: 0 | CR22: 0 | CS22: 0 | CT22: 0 | CU22: 0 | CV22: 0 | CW22: 0 | CX22: 0 | CY22: 0 | CZ22: 0 | DA22: 0 | DB22: 0 | DC22: 0 | DD22: 0 | DE22: 0 | DF22: 0 | DG22: 0 | DH22: 0 | DI22: 0 | DJ22: 0 | DK22: 0 | DL22: 0 | DM22: 0 | DN22: 0 | DO22: 0 | DP22: 0 | DQ22: 0 | DR22: 0 | DS22: 0 | DT22: 0 | DU22: 0 | DV22: 0
A23: Итого по разделу II | B23: 1200 | C23: руб. | D23: =SUM(G23:R23) -> 8.973817e+13 | E23: =SUM(S23:AD23) -> 1.0050918e+15 | F23: =SUM(AE23:AP23) -> 1.0216555e+15 | G23: =SUM(G17:G22) -> 9.1278535e+10 | H23: =SUM(H17:H22) -> 1.8492306e+11 | I23: =SUM(I17:I22) -> 2.8099795e+11 | J23: =SUM(J17:J22) -> 3.7956943e+11 | K23: =SUM(K17:K22) -> 4.8070558e+11 | L23: =SUM(L17:L22) -> 5.8447644e+11 | M23: =SUM(M17:M22) -> 6.9095403e+11 | N23: =SUM(N17:N22) -> 8.0021242e+11 | ... DV23: =SUM(DV17:DV22) -> 5.0686689e+13
A24: БАЛАНС | B24: 1600 | C24: руб. | D24: =D15+D23 -> 1.2525817e+14 | E24: =E15+E23 -> 1.0406118e+15 | F24: =F15+F23 -> 1.0571755e+15 | G24: =G15+G23 -> 3.0512785e+12 | H24: =H15+H23 -> 3.1449231e+12 | I24: =I15+I23 -> 3.2409979e+12 | J24: =J15+J23 -> 3.3395694e+12 | K24: =K15+K23 -> 3.4407056e+12 | ... DV24: =DV15+DV23 -> 5.3646689e+13
A25: ПАССИВ
A26: III. КАПИТАЛ И РЕЗЕРВЫ 6
A27: Уставный капитал (складочный капитал, уставный фонд, вклады товарищей) | B27: 1310 | C27: руб. | D27: 10000 | E27: 10000 | F27: 10000 | G27: 0 | H27: 0 | I27: 0 | J27: 0 | K27: 0 | L27: 0 | M27: 0 | N27: 0 | O27: 0 | P27: 0 | Q27: 0 | R27: 0 | S27: 0 | T27: 0 | U27: 0 | V27: 0 | W27: 0 | X27: 0 | Y27: 0 | Z27: 0 | AA27: 0 | AB27: 0 | AC27: 0 | AD27: 0 | AE27: 0 | AF27: 0 | AG27: 0 | AH27: 0 | AI27: 0 | AJ27: 0 | AK27: 0 | AL27: 0 | AM27: 0 | AN27: 0 | AO27: 0 | AP27: 0 | AQ27: 10000 | AR27: 10000 | AS27: 10000 | AT27: 10000 | AU27: 10000 | AV27: 10000 | AW27: 10000 | AX27: 10000 | AY27: 10000 | AZ27: 10000 | BA27: 10000 | BB27: 10000 | BC27: 10000 | BD27: 10000 | BE27: 10000 | BF27: 10000 | BG27: 10000 | BH27: 10000 | BI27: 10000 | BJ27: 10000 | BK27: 10000 | BL27: 10000 | BM27: 10000 | BN27: 10000 | BO27: 10000 | BP27: 10000 | BQ27: 10000 | BR27: 10000 | BS27: 10000 | BT27: 10000 | BU27: 10000 | BV27: 10000 | BW27: 10000 | BX27: 10000 | BY27: 10000 | BZ27: 10000 | CA27: 10000 | CB27: 10000 | CC27: 10000 | CD27: 10000 | CE27: 10000 | CF27: 10000 | CG27: 10000 | CH27: 10000 | CI27: 10000 | CJ27: 10000 | CK27: 10000 | CL27: 10000 | CM27: 10000 | CN27: 10000 | CO27: 10000 | CP27: 10000 | CQ27: 10000 | CR27: 10000 | CS27: 10000 | CT27: 10000 | CU27: 10000 | CV27: 10000 | CW27: 10000 | CX27: 10000 | CY27: 10000 | CZ27: 10000 | DA27: 10000 | DB27: 10000 | DC27: 10000 | DD27: 10000 | DE27: 10000 | DF27: 10000 | DG27: 10000 | DH27: 10000 | DI27: 10000 | DJ27: 10000 | DK27: 10000 | DL27: 10000 | DM27: 10000 | DN27: 10000 | DO27: 10000 | DP27: 10000 | DQ27: 10000 | DR27: 10000 | DS27: 10000 | DT27: 10000 | DU27: 10000 | DV27: 10000
A28: Собственные акции, выкупленные у акционеров | B28: 1320 | C28: руб. | D28: =SUM(G28:R28) -> 0 | E28: =SUM(S28:AD28) -> 0 | F28: =SUM(AE28:AP28) -> 0 | G28: 0 | H28: 0 | I28: 0 | J28: 0 | K28: 0 | L28: 0 | M28: 0 | N28: 0 | O28: 0 | P28: 0 | Q28: 0 | R28: 0 | S28: 0 | T28: 0 | U28: 0 | V28: 0 | W28: 0 | X28: 0 | Y28: 0 | Z28: 0 | AA28: 0 | AB28: 0 | AC28: 0 | AD28: 0 | AE28: 0 | AF28: 0 | AG28: 0 | AH28: 0 | AI28: 0 | AJ28: 0 | AK28: 0 | AL28: 0 | AM28: 0 | AN28: 0 | AO28: 0 | AP28: 0 | AQ28: 0 | AR28: 0 | AS28: 0 | AT28: 0 | AU28: 0 | AV28: 0 | AW28: 0 | AX28: 0 | AY28: 0 | AZ28: 0 | BA28: 0 | BB28: 0 | BC28: 0 | BD28: 0 | BE28: 0 | BF28: 0 | BG28: 0 | BH28: 0 | BI28: 0 | BJ28: 0 | BK28: 0 | BL28: 0 | BM28: 0 | BN28: 0 | BO28: 0 | BP28: 0 | BQ28: 0 | BR28: 0 | BS28: 0 | BT28: 0 | BU28: 0 | BV28: 0 | BW28: 0 | BX28: 0 | BY28: 0 | BZ28: 0 | CA28: 0 | CB28: 0 | CC28: 0 | CD28: 0 | CE28: 0 | CF28: 0 | CG28: 0 | CH28: 0 | CI28: 0 | CJ28: 0 | CK28: 0 | CL28: 0 | CM28: 0 | CN28: 0 | CO28: 0 | CP28: 0 | CQ28: 0 | CR28: 0 | CS28: 0 | CT28: 0 | CU28: 0 | CV28: 0 | CW28: 0 | CX28: 0 | CY28: 0 | CZ28: 0 | DA28: 0 | DB28: 0 | DC28: 0 | DD28: 0 | DE28: 0 | DF28: 0 | DG28: 0 | DH28: 0 | DI28: 0 | DJ28: 0 | DK28: 0 | DL28: 0 | DM28: 0 | DN28: 0 | DO28: 0 | DP28: 0 | DQ28: 0 | DR28: 0 | DS28: 0 | DT28: 0 | DU28: 0 | DV28: 0
A29: Переоценка внеоборотных активов | B29: 1340 | C29: руб. | D29: =SUM(G29:R29) -> 0 | E29: =SUM(S29:AD29) -> 0 | F29: =SUM(AE29:AP29) -> 0 | G29: 0 | H29: 0 | I29: 0 | J29: 0 | K29: 0 | L29: 0 | M29: 0 | N29: 0 | O29: 0 | P29: 0 | Q29: 0 | R29: 0 | S29: 0 | T29: 0 | U29: 0 | V29: 0 | W29: 0 | X29: 0 | Y29: 0 | Z29: 0 | AA29: 0 | AB29: 0 | AC29: 0 | AD29: 0 | AE29: 0 | AF29: 0 | AG29: 0 | AH29: 0 | AI29: 0 | AJ29: 0 | AK29: 0 | AL29: 0 | AM29: 0 | AN29: 0 | AO29: 0 | AP29: 0 | AQ29: 0 | AR29: 0 | AS29: 0 | AT29: 0 | AU29: 0 | AV29: 0 | AW29: 0 | AX29: 0 | AY29: 0 | AZ29: 0 | BA29: 0 | BB29: 0 | BC29: 0 | BD29: 0 | BE29: 0 | BF29: 0 | BG29: 0 | BH29: 0 | BI29: 0 | BJ29: 0 | BK29: 0 | BL29: 0 | BM29: 0 | BN29: 0 | BO29: 0 | BP29: 0 | BQ29: 0 | BR29: 0 | BS29: 0 | BT29: 0 | BU29: 0 | BV29: 0 | BW29: 0 | BX29: 0 | BY29: 0 | BZ29: 0 | CA29: 0 | CB29: 0 | CC29: 0 | CD29: 0 | CE29: 0 | CF29: 0 | CG29: 0 | CH29: 0 | CI29: 0 | CJ29: 0 | CK29: 0 | CL29: 0 | CM29: 0 | CN29: 0 | CO29: 0 | CP29: 0 | CQ29: 0 | CR29: 0 | CS29: 0 | CT29: 0 | CU29: 0 | CV29: 0 | CW29: 0 | CX29: 0 | CY29: 0 | CZ29: 0 | DA29: 0 | DB29: 0 | DC29: 0 | DD29: 0 | DE29: 0 | DF29: 0 | DG29: 0 | DH29: 0 | DI29: 0 | DJ29: 0 | DK29: 0 | DL29: 0 | DM29: 0 | DN29: 0 | DO29: 0 | DP29: 0 | DQ29: 0 | DR29: 0 | DS29: 0 | DT29: 0 | DU29: 0 | DV29: 0
A30: Добавочный капитал (без переоценки) | B30: 1350 | C30: руб. | D30: =SUM(G30:R30) -> 0 | E30: =SUM(S30:AD30) -> 0 | F30: =SUM(AE30:AP30) -> 0 | G30: 0 | H30: 0 | I30: 0 | J30: 0 | K30: 0 | L30: 0 | M30: 0 | N30: 0 | O30: 0 | P30: 0 | Q30: 0 | R30: 0 | S30: 0 | T30: 0 | U30: 0 | V30: 0 | W30: 0 | X30: 0 | Y30: 0 | Z30: 0 | AA30: 0 | AB30: 0 | AC30: 0 | AD30: 0 | AE30: 0 | AF30: 0 | AG30: 0 | AH30: 0 | AI30: 0 | AJ30: 0 | AK30: 0 | AL30: 0 | AM30: 0 | AN30: 0 | AO30: 0 | AP30: 0 | AQ30: 0 | AR30: 0 | AS30: 0 | AT30: 0 | AU30: 0 | AV30: 0 | AW30: 0 | AX30: 0 | AY30: 0 | AZ30: 0 | BA30: 0 | BB30: 0 | BC30: 0 | BD30: 0 | BE30: 0 | BF30: 0 | BG30: 0 | BH30: 0 | BI30: 0 | BJ30: 0 | BK30: 0 | BL30: 0 | BM30: 0 | BN30: 0 | BO30: 0 | BP30: 0 | BQ30: 0 | BR30: 0 | BS30: 0 | BT30: 0 | BU30: 0 | BV30: 0 | BW30: 0 | BX30: 0 | BY30: 0 | BZ30: 0 | CA30: 0 | CB30: 0 | CC30: 0 | CD30: 0 | CE30: 0 | CF30: 0 | CG30: 0 | CH30: 0 | CI30: 0 | CJ30: 0 | CK30: 0 | CL30: 0 | CM30: 0 | CN30: 0 | CO30: 0 | CP30: 0 | CQ30: 0 | CR30: 0 | CS30: 0 | CT30: 0 | CU30: 0 | CV30: 0 | CW30: 0 | CX30: 0 | CY30: 0 | CZ30: 0 | DA30: 0 | DB30: 0 | DC30: 0 | DD30: 0 | DE30: 0 | DF30: 0 | DG30: 0 | DH30: 0 | DI30: 0 | DJ30: 0 | DK30: 0 | DL30: 0 | DM30: 0 | DN30: 0 | DO30: 0 | DP30: 0 | DQ30: 0 | DR30: 0 | DS30: 0 | DT30: 0 | DU30: 0 | DV30: 0
A31: Резервный капитал | B31: 1360 | C31: руб. | D31: =SUM(G31:R31) -> 35520000000000 | E31: =SUM(S31:AD31) -> 35520000000000 | F31: =SUM(AE31:AP31) -> 35520000000000 | G31: ='Амортизация, до'!I18 -> 2960000000000 | H31: ='Амортизация, до'!J18 -> 2960000000000 | I31: ='Амортизация, до'!K18 -> 2960000000000 | J31: ='Амортизация, до'!L18 -> 2960000000000 | K31: ='Амортизация, до'!M18 -> 2960000000000 | L31: ='Амортизация, до'!N18 -> 2960000000000 | M31: ='Амортизация, до'!O18 -> 2960000000000 | N31: ='Амортизация, до'!P18 -> 2960000000000 | ... DV31: ='Амортизация, до'!DX18 -> 2960000000000
A32: Нераспределенная прибыль (непокрытый убыток) | B32: 1370 | C32: руб. | D32: =SUM(G32:R32) -> 8.973817e+13 | E32: =SUM(S32:AD32) -> 1.0050918e+15 | F32: =SUM(AE32:AP32) -> 1.0216555e+15 | G32: ='Отчет о фин. рез до'!E21 -> 9.1278535e+10 | H32: ='Отчет о фин. рез до'!F21 -> 1.8492306e+11 | I32: ='Отчет о фин. рез до'!G21 -> 2.8099795e+11 | J32: ='Отчет о фин. рез до'!H21 -> 3.7956943e+11 | K32: ='Отчет о фин. рез до'!I21 -> 4.8070558e+11 | L32: ='Отчет о фин. рез до'!J21 -> 5.8447644e+11 | M32: ='Отчет о фин. рез до'!K21 -> 6.9095403e+11 | N32: ='Отчет о фин. рез до'!L21 -> 8.0021242e+11 | ... DV32: ='Отчет о фин. рез до'!DT21 -> 5.0686689e+13
A33: Итого по разделу III | B33: 1300 | C33: руб. | D33: =SUM(D27:D32) -> 1.2525817e+14 | E33: =SUM(E27:E32) -> 1.0406118e+15 | F33: =SUM(F27:F32) -> 1.0571755e+15 | G33: =SUM(G27:G32) -> 3.0512785e+12 | H33: =SUM(H27:H32) -> 3.1449231e+12 | I33: =SUM(I27:I32) -> 3.2409979e+12 | J33: =SUM(J27:J32) -> 3.3395694e+12 | K33: =SUM(K27:K32) -> 3.4407056e+12 | ... DV33: =SUM(DV27:DV32) -> 5.3646689e+13
A34: IV. ДОЛГОСРОЧНЫЕ ОБЯЗАТЕЛЬСТВА
A35: Заемные средства | B35: 1410 | C35: руб. | D35: =SUM(G35:R35) -> 0 | E35: =SUM(S35:AD35) -> 0 | F35: =SUM(AE35:AP35) -> 0 | G35: 0 | H35: 0 | I35: 0 | J35: 0 | K35: 0 | L35: 0 | M35: 0 | N35: 0 | O35: 0 | P35: 0 | Q35: 0 | R35: 0 | S35: 0 | T35: 0 | U35: 0 | V35: 0 | W35: 0 | X35: 0 | Y35: 0 | Z35: 0 | AA35: 0 | AB35: 0 | AC35: 0 | AD35: 0 | AE35: 0 | AF35: 0 | AG35: 0 | AH35: 0 | AI35: 0 | AJ35: 0 | AK35: 0 | AL35: 0 | AM35: 0 | AN35: 0 | AO35: 0 | AP35: 0 | AQ35: 0 | AR35: 0 | AS35: 0 | AT35: 0 | AU35: 0 | AV35: 0 | AW35: 0 | AX35: 0 | AY35: 0 | AZ35: 0 | BA35: 0 | BB35: 0 | BC35: 0 | BD35: 0 | BE35: 0 | BF35: 0 | BG35: 0 | BH35: 0 | BI35: 0 | BJ35: 0 | BK35: 0 | BL35: 0 | BM35: 0 | BN35: 0 | BO35: 0 | BP35: 0 | BQ35: 0 | BR35: 0 | BS35: 0 | BT35: 0 | BU35: 0 | BV35: 0 | BW35: 0 | BX35: 0 | BY35: 0 | BZ35: 0 | CA35: 0 | CB35: 0 | CC35: 0 | CD35: 0 | CE35: 0 | CF35: 0 | CG35: 0 | CH35: 0 | CI35: 0 | CJ35: 0 | CK35: 0 | CL35: 0 | CM35: 0 | CN35: 0 | CO35: 0 | CP35: 0 | CQ35: 0 | CR35: 0 | CS35: 0 | CT35: 0 | CU35: 0 | CV35: 0 | CW35: 0 | CX35: 0 | CY35: 0 | CZ35: 0 | DA35: 0 | DB35: 0 | DC35: 0 | DD35: 0 | DE35: 0 | DF35: 0 | DG35: 0 | DH35: 0 | DI35: 0 | DJ35: 0 | DK35: 0 | DL35: 0 | DM35: 0 | DN35: 0 | DO35: 0 | DP35: 0 | DQ35: 0 | DR35: 0 | DS35: 0 | DT35: 0 | DU35: 0 | DV35: 0
A36: Отложенные налоговые обязательства | B36: 1420 | C36: руб. | D36: =SUM(G36:R36) -> 0 | E36: =SUM(S36:AD36) -> 0 | F36: =SUM(AE36:AP36) -> 0 | G36: 0 | H36: 0 | I36: 0 | J36: 0 | K36: 0 | L36: 0 | M36: 0 | N36: 0 | O36: 0 | P36: 0 | Q36: 0 | R36: 0 | S36: 0 | T36: 0 | U36: 0 | V36: 0 | W36: 0 | X36: 0 | Y36: 0 | Z36: 0 | AA36: 0 | AB36: 0 | AC36: 0 | AD36: 0 | AE36: 0 | AF36: 0 | AG36: 0 | AH36: 0 | AI36: 0 | AJ36: 0 | AK36: 0 | AL36: 0 | AM36: 0 | AN36: 0 | AO36: 0 | AP36: 0 | AQ36: 0 | AR36: 0 | AS36: 0 | AT36: 0 | AU36: 0 | AV36: 0 | AW36: 0 | AX36: 0 | AY36: 0 | AZ36: 0 | BA36: 0 | BB36: 0 | BC36: 0 | BD36: 0 | BE36: 0 | BF36: 0 | BG36: 0 | BH36: 0 | BI36: 0 | BJ36: 0 | BK36: 0 | BL36: 0 | BM36: 0 | BN36: 0 | BO36: 0 | BP36: 0 | BQ36: 0 | BR36: 0 | BS36: 0 | BT36: 0 | BU36: 0 | BV36: 0 | BW36: 0 | BX36: 0 | BY36: 0 | BZ36: 0 | CA36: 0 | CB36: 0 | CC36: 0 | CD36: 0 | CE36: 0 | CF36: 0 | CG36: 0 | CH36: 0 | CI36: 0 | CJ36: 0 | CK36: 0 | CL36: 0 | CM36: 0 | CN36: 0 | CO36: 0 | CP36: 0 | CQ36: 0 | CR36: 0 | CS36: 0 | CT36: 0 | CU36: 0 | CV36: 0 | CW36: 0 | CX36: 0 | CY36: 0 | CZ36: 0 | DA36: 0 | DB36: 0 | DC36: 0 | DD36: 0 | DE36: 0 | DF36: 0 | DG36: 0 | DH36: 0 | DI36: 0 | DJ36: 0 | DK36: 0 | DL36: 0 | DM36: 0 | DN36: 0 | DO36: 0 | DP36: 0 | DQ36: 0 | DR36: 0 | DS36: 0 | DT36: 0 | DU36: 0 | DV36: 0
A37: Оценочные обязательства | B37: 1430 | C37: руб. | D37: =SUM(G37:R37) -> 0 | E37: =SUM(S37:AD37) -> 0 | F37: =SUM(AE37:AP37) -> 0 | G37: 0 | H37: 0 | I37: 0 | J37: 0 | K37: 0 | L37: 0 | M37: 0 | N37: 0 | O37: 0 | P37: 0 | Q37: 0 | R37: 0 | S37: 0 | T37: 0 | U37: 0 | V37: 0 | W37: 0 | X37: 0 | Y37: 0 | Z37: 0 | AA37: 0 | AB37: 0 | AC37: 0 | AD37: 0 | AE37: 0 | AF37: 0 | AG37: 0 | AH37: 0 | AI37: 0 | AJ37: 0 | AK37: 0 | AL37: 0 | AM37: 0 | AN37: 0 | AO37: 0 | AP37: 0 | AQ37: 0 | AR37: 0 | AS37: 0 | AT37: 0 | AU37: 0 | AV37: 0 | AW37: 0 | AX37: 0 | AY37: 0 | AZ37: 0 | BA37: 0 | BB37: 0 | BC37: 0 | BD37: 0 | BE37: 0 | BF37: 0 | BG37: 0 | BH37: 0 | BI37: 0 | BJ37: 0 | BK37: 0 | BL37: 0 | BM37: 0 | BN37: 0 | BO37: 0 | BP37: 0 | BQ37: 0 | BR37: 0 | BS37: 0 | BT37: 0 | BU37: 0 | BV37: 0 | BW37: 0 | BX37: 0 | BY37: 0 | BZ37: 0 | CA37: 0 | CB37: 0 | CC37: 0 | CD37: 0 | CE37: 0 | CF37: 0 | CG37: 0 | CH37: 0 | CI37: 0 | CJ37: 0 | CK37: 0 | CL37: 0 | CM37: 0 | CN37: 0 | CO37: 0 | CP37: 0 | CQ37: 0 | CR37: 0 | CS37: 0 | CT37: 0 | CU37: 0 | CV37: 0 | CW37: 0 | CX37: 0 | CY37: 0 | CZ37: 0 | DA37: 0 | DB37: 0 | DC37: 0 | DD37: 0 | DE37: 0 | DF37: 0 | DG37: 0 | DH37: 0 | DI37: 0 | DJ37: 0 | DK37: 0 | DL37: 0 | DM37: 0 | DN37: 0 | DO37: 0 | DP37: 0 | DQ37: 0 | DR37: 0 | DS37: 0 | DT37: 0 | DU37: 0 | DV37: 0
A38: Прочие обязательства | B38: 1450 | C38: руб. | D38: =SUM(G38:R38) -> 0 | E38: =SUM(S38:AD38) -> 0 | F38: =SUM(AE38:AP38) -> 0 | G38: 0 | H38: 0 | I38: 0 | J38: 0 | K38: 0 | L38: 0 | M38: 0 | N38: 0 | O38: 0 | P38: 0 | Q38: 0 | R38: 0 | S38: 0 | T38: 0 | U38: 0 | V38: 0 | W38: 0 | X38: 0 | Y38: 0 | Z38: 0 | AA38: 0 | AB38: 0 | AC38: 0 | AD38: 0 | AE38: 0 | AF38: 0 | AG38: 0 | AH38: 0 | AI38: 0 | AJ38: 0 | AK38: 0 | AL38: 0 | AM38: 0 | AN38: 0 | AO38: 0 | AP38: 0 | AQ38: 0 | AR38: 0 | AS38: 0 | AT38: 0 | AU38: 0 | AV38: 0 | AW38: 0 | AX38: 0 | AY38: 0 | AZ38: 0 | BA38: 0 | BB38: 0 | BC38: 0 | BD38: 0 | BE38: 0 | BF38: 0 | BG38: 0 | BH38: 0 | BI38: 0 | BJ38: 0 | BK38: 0 | BL38: 0 | BM38: 0 | BN38: 0 | BO38: 0 | BP38: 0 | BQ38: 0 | BR38: 0 | BS38: 0 | BT38: 0 | BU38: 0 | BV38: 0 | BW38: 0 | BX38: 0 | BY38: 0 | BZ38: 0 | CA38: 0 | CB38: 0 | CC38: 0 | CD38: 0 | CE38: 0 | CF38: 0 | CG38: 0 | CH38: 0 | CI38: 0 | CJ38: 0 | CK38: 0 | CL38: 0 | CM38: 0 | CN38: 0 | CO38: 0 | CP38: 0 | CQ38: 0 | CR38: 0 | CS38: 0 | CT38: 0 | CU38: 0 | CV38: 0 | CW38: 0 | CX38: 0 | CY38: 0 | CZ38: 0 | DA38: 0 | DB38: 0 | DC38: 0 | DD38: 0 | DE38: 0 | DF38: 0 | DG38: 0 | DH38: 0 | DI38: 0 | DJ38: 0 | DK38: 0 | DL38: 0 | DM38: 0 | DN38: 0 | DO38: 0 | DP38: 0 | DQ38: 0 | DR38: 0 | DS38: 0 | DT38: 0 | DU38: 0 | DV38: 0
A39: Итого по разделу IV | B39: 1400 | C39: руб. | D39: =SUM(D35:D38) -> 0 | E39: =SUM(E35:E38) -> 0 | F39: =SUM(F35:F38) -> 0 | G39: =SUM(G35:G38) -> 0 | H39: =SUM(H35:H38) -> 0 | I39: =SUM(I35:I38) -> 0 | J39: =SUM(J35:J38) -> 0 | K39: =SUM(K35:K38) -> 0 | ... AO39: =SUM(AO35:AO38) -> 0 | AP39: 0 | AQ39: =SUM(AQ35:AQ38) -> 0 | AR39: =SUM(AR35:AR38) -> 0 | AS39: =SUM(AS35:AS38) -> 0 | AT39: =SUM(AT35:AT38) -> 0 | AU39: =SUM(AU35:AU38) -> 0 | AV39: =SUM(AV35:AV38) -> 0 | AW39: =SUM(AW35:AW38) -> 0 | AX39: =SUM(AX35:AX38) -> 0 | ... DV39: =SUM(DV35:DV38) -> 0
A40: V. КРАТКОСРОЧНЫЕ ОБЯЗАТЕЛЬСТВА
A41: Заемные средства | B41: 1510 | C41: руб. | D41: =SUM(G41:R41) -> 0 | E41: =SUM(S41:AD41) -> 0 | F41: =SUM(AE41:AP41) -> 0 | G41: 0 | H41: 0 | I41: 0 | J41: 0 | K41: 0 | L41: 0 | M41: 0 | N41: 0 | O41: 0 | P41: 0 | Q41: 0 | R41: 0 | S41: 0 | T41: 0 | U41: 0 | V41: 0 | W41: 0 | X41: 0 | Y41: 0 | Z41: 0 | AA41: 0 | AB41: 0 | AC41: 0 | AD41: 0 | AE41: 0 | AF41: 0 | AG41: 0 | AH41: 0 | AI41: 0 | AJ41: 0 | AK41: 0 | AL41: 0 | AM41: 0 | AN41: 0 | AO41: 0 | AP41: 0 | AQ41: 0 | AR41: 0 | AS41: 0 | AT41: 0 | AU41: 0 | AV41: 0 | AW41: 0 | AX41: 0 | AY41: 0 | AZ41: 0 | BA41: 0 | BB41: 0 | BC41: 0 | BD41: 0 | BE41: 0 | BF41: 0 | BG41: 0 | BH41: 0 | BI41: 0 | BJ41: 0 | BK41: 0 | BL41: 0 | BM41: 0 | BN41: 0 | BO41: 0 | BP41: 0 | BQ41: 0 | BR41: 0 | BS41: 0 | BT41: 0 | BU41: 0 | BV41: 0 | BW41: 0 | BX41: 0 | BY41: 0 | BZ41: 0 | CA41: 0 | CB41: 0 | CC41: 0 | CD41: 0 | CE41: 0 | CF41: 0 | CG41: 0 | CH41: 0 | CI41: 0 | CJ41: 0 | CK41: 0 | CL41: 0 | CM41: 0 | CN41: 0 | CO41: 0 | CP41: 0 | CQ41: 0 | CR41: 0 | CS41: 0 | CT41: 0 | CU41: 0 | CV41: 0 | CW41: 0 | CX41: 0 | CY41: 0 | CZ41: 0 | DA41: 0 | DB41: 0 | DC41: 0 | DD41: 0 | DE41: 0 | DF41: 0 | DG41: 0 | DH41: 0 | DI41: 0 | DJ41: 0 | DK41: 0 | DL41: 0 | DM41: 0 | DN41: 0 | DO41: 0 | DP41: 0 | DQ41: 0 | DR41: 0 | DS41: 0 | DT41: 0 | DU41: 0 | DV41: 0
A42: Кредиторская задолженность | B42: 1520 | C42: руб. | D42: =SUM(G42:R42) -> 0 | E42: =SUM(S42:AD42) -> 0 | F42: =SUM(AE42:AP42) -> 0 | G42: 0 | H42: 0 | I42: 0 | J42: 0 | K42: 0 | L42: 0 | M42: 0 | N42: 0 | O42: 0 | P42: 0 | Q42: 0 | R42: 0 | S42: 0 | T42: 0 | U42: 0 | V42: 0 | W42: 0 | X42: 0 | Y42: 0 | Z42: 0 | AA42: 0 | AB42: 0 | AC42: 0 | AD42: 0 | AE42: 0 | AF42: 0 | AG42: 0 | AH42: 0 | AI42: 0 | AJ42: 0 | AK42: 0 | AL42: 0 | AM42: 0 | AN42: 0 | AO42: 0 | AP42: 0 | AQ42: 0 | AR42: 0 | AS42: 0 | AT42: 0 | AU42: 0 | AV42: 0 | AW42: 0 | AX42: 0 | AY42: 0 | AZ42: 0 | BA42: 0 | BB42: 0 | BC42: 0 | BD42: 0 | BE42: 0 | BF42: 0 | BG42: 0 | BH42: 0 | BI42: 0 | BJ42: 0 | BK42: 0 | BL42: 0 | BM42: 0 | BN42: 0 | BO42: 0 | BP42: 0 | BQ42: 0 | BR42: 0 | BS42: 0 | BT42: 0 | BU42: 0 | BV42: 0 | BW42: 0 | BX42: 0 | BY42: 0 | BZ42: 0 | CA42: 0 | CB42: 0 | CC42: 0 | CD42: 0 | CE42: 0 | CF42: 0 | CG42: 0 | CH42: 0 | CI42: 0 | CJ42: 0 | CK42: 0 | CL42: 0 | CM42: 0 | CN42: 0 | CO42: 0 | CP42: 0 | CQ42: 0 | CR42: 0 | CS42: 0 | CT42: 0 | CU42: 0 | CV42: 0 | CW42: 0 | CX42: 0 | CY42: 0 | CZ42: 0 | DA42: 0 | DB42: 0 | DC42: 0 | DD42: 0 | DE42: 0 | DF42: 0 | DG42: 0 | DH42: 0 | DI42: 0 | DJ42: 0 | DK42: 0 | DL42: 0 | DM42: 0 | DN42: 0 | DO42: 0 | DP42: 0 | DQ42: 0 | DR42: 0 | DS42: 0 | DT42: 0 | DU42: 0 | DV42: 0
A43: Доходы будущих периодов | B43: 1530 | C43: руб. | D43: =SUM(G43:R43) -> 0 | E43: =SUM(S43:AD43) -> 0 | F43: =SUM(AE43:AP43) -> 0 | G43: 0 | H43: 0 | I43: 0 | J43: 0 | K43: 0 | L43: 0 | M43: 0 | N43: 0 | O43: 0 | P43: 0 | Q43: 0 | R43: 0 | S43: 0 | T43: 0 | U43: 0 | V43: 0 | W43: 0 | X43: 0 | Y43: 0 | Z43: 0 | AA43: 0 | AB43: 0 | AC43: 0 | AD43: 0 | AE43: 0 | AF43: 0 | AG43: 0 | AH43: 0 | AI43: 0 | AJ43: 0 | AK43: 0 | AL43: 0 | AM43: 0 | AN43: 0 | AO43: 0 | AP43: 0 | AQ43: 0 | AR43: 0 | AS43: 0 | AT43: 0 | AU43: 0 | AV43: 0 | AW43: 0 | AX43: 0 | AY43: 0 | AZ43: 0 | BA43: 0 | BB43: 0 | BC43: 0 | BD43: 0 | BE43: 0 | BF43: 0 | BG43: 0 | BH43: 0 | BI43: 0 | BJ43: 0 | BK43: 0 | BL43: 0 | BM43: 0 | BN43: 0 | BO43: 0 | BP43: 0 | BQ43: 0 | BR43: 0 | BS43: 0 | BT43: 0 | BU43: 0 | BV43: 0 | BW43: 0 | BX43: 0 | BY43: 0 | BZ43: 0 | CA43: 0 | CB43: 0 | CC43: 0 | CD43: 0 | CE43: 0 | CF43: 0 | CG43: 0 | CH43: 0 | CI43: 0 | CJ43: 0 | CK43: 0 | CL43: 0 | CM43: 0 | CN43: 0 | CO43: 0 | CP43: 0 | CQ43: 0 | CR43: 0 | CS43: 0 | CT43: 0 | CU43: 0 | CV43: 0 | CW43: 0 | CX43: 0 | CY43: 0 | CZ43: 0 | DA43: 0 | DB43: 0 | DC43: 0 | DD43: 0 | DE43: 0 | DF43: 0 | DG43: 0 | DH43: 0 | DI43: 0 | DJ43: 0 | DK43: 0 | DL43: 0 | DM43: 0 | DN43: 0 | DO43: 0 | DP43: 0 | DQ43: 0 | DR43: 0 | DS43: 0 | DT43: 0 | DU43: 0 | DV43: 0
A44: Оценочные обязательства | B44: 1540 | C44: руб. | D44: =SUM(G44:R44) -> 0 | E44: =SUM(S44:AD44) -> 0 | F44: =SUM(AE44:AP44) -> 0 | G44: 0 | H44: 0 | I44: 0 | J44: 0 | K44: 0 | L44: 0 | M44: 0 | N44: 0 | O44: 0 | P44: 0 | Q44: 0 | R44: 0 | S44: 0 | T44: 0 | U44: 0 | V44: 0 | W44: 0 | X44: 0 | Y44: 0 | Z44: 0 | AA44: 0 | AB44: 0 | AC44: 0 | AD44: 0 | AE44: 0 | AF44: 0 | AG44: 0 | AH44: 0 | AI44: 0 | AJ44: 0 | AK44: 0 | AL44: 0 | AM44: 0 | AN44: 0 | AO44: 0 | AP44: 0 | AQ44: 0 | AR44: 0 | AS44: 0 | AT44: 0 | AU44: 0 | AV44: 0 | AW44: 0 | AX44: 0 | AY44: 0 | AZ44: 0 | BA44: 0 | BB44: 0 | BC44: 0 | BD44: 0 | BE44: 0 | BF44: 0 | BG44: 0 | BH44: 0 | BI44: 0 | BJ44: 0 | BK44: 0 | BL44: 0 | BM44: 0 | BN44: 0 | BO44: 0 | BP44: 0 | BQ44: 0 | BR44: 0 | BS44: 0 | BT44: 0 | BU44: 0 | BV44: 0 | BW44: 0 | BX44: 0 | BY44: 0 | BZ44: 0 | CA44: 0 | CB44: 0 | CC44: 0 | CD44: 0 | CE44: 0 | CF44: 0 | CG44: 0 | CH44: 0 | CI44: 0 | CJ44: 0 | CK44: 0 | CL44: 0 | CM44: 0 | CN44: 0 | CO44: 0 | CP44: 0 | CQ44: 0 | CR44: 0 | CS44: 0 | CT44: 0 | CU44: 0 | CV44: 0 | CW44: 0 | CX44: 0 | CY44: 0 | CZ44: 0 | DA44: 0 | DB44: 0 | DC44: 0 | DD44: 0 | DE44: 0 | DF44: 0 | DG44: 0 | DH44: 0 | DI44: 0 | DJ44: 0 | DK44: 0 | DL44: 0 | DM44: 0 | DN44: 0 | DO44: 0 | DP44: 0 | DQ44: 0 | DR44: 0 | DS44: 0 | DT44: 0 | DU44: 0 | DV44: 0
A45: Прочие обязательства | B45: 1550 | C45: руб. | D45: =SUM(G45:R45) -> 0 | E45: =SUM(S45:AD45) -> 0 | F45: =SUM(AE45:AP45) -> 0 | G45: 0 | H45: 0 | I45: 0 | J45: 0 | K45: 0 | L45: 0 | M45: 0 | N45: 0 | O45: 0 | P45: 0 | Q45: 0 | R45: 0 | S45: 0 | T45: 0 | U45: 0 | V45: 0 | W45: 0 | X45: 0 | Y45: 0 | Z45: 0 | AA45: 0 | AB45: 0 | AC45: 0 | AD45: 0 | AE45: 0 | AF45: 0 | AG45: 0 | AH45: 0 | AI45: 0 | AJ45: 0 | AK45: 0 | AL45: 0 | AM45: 0 | AN45: 0 | AO45: 0 | AP45: 0 | AQ45: 0 | AR45: 0 | AS45: 0 | AT45: 0 | AU45: 0 | AV45: 0 | AW45: 0 | AX45: 0 | AY45: 0 | AZ45: 0 | BA45: 0 | BB45: 0 | BC45: 0 | BD45: 0 | BE45: 0 | BF45: 0 | BG45: 0 | BH45: 0 | BI45: 0 | BJ45: 0 | BK45: 0 | BL45: 0 | BM45: 0 | BN45: 0 | BO45: 0 | BP45: 0 | BQ45: 0 | BR45: 0 | BS45: 0 | BT45: 0 | BU45: 0 | BV45: 0 | BW45: 0 | BX45: 0 | BY45: 0 | BZ45: 0 | CA45: 0 | CB45: 0 | CC45: 0 | CD45: 0 | CE45: 0 | CF45: 0 | CG45: 0 | CH45: 0 | CI45: 0 | CJ45: 0 | CK45: 0 | CL45: 0 | CM45: 0 | CN45: 0 | CO45: 0 | CP45: 0 | CQ45: 0 | CR45: 0 | CS45: 0 | CT45: 0 | CU45: 0 | CV45: 0 | CW45: 0 | CX45: 0 | CY45: 0 | CZ45: 0 | DA45: 0 | DB45: 0 | DC45: 0 | DD45: 0 | DE45: 0 | DF45: 0 | DG45: 0 | DH45: 0 | DI45: 0 | DJ45: 0 | DK45: 0 | DL45: 0 | DM45: 0 | DN45: 0 | DO45: 0 | DP45: 0 | DQ45: 0 | DR45: 0 | DS45: 0 | DT45: 0 | DU45: 0 | DV45: 0
A46: Итого по разделу V | B46: 1500 | C46: руб. | D46: =SUM(G46:R46) -> 0 | E46: =SUM(S46:AD46) -> 0 | F46: =SUM(AE46:AP46) -> 0 | G46: =SUM(G41:G45) -> 0 | H46: =SUM(H41:H45) -> 0 | I46: =SUM(I41:I45) -> 0 | J46: =SUM(J41:J45) -> 0 | K46: =SUM(K41:K45) -> 0 | L46: =SUM(L41:L45) -> 0 | M46: =SUM(M41:M45) -> 0 | N46: =SUM(N41:N45) -> 0 | ... DV46: =SUM(DV41:DV45) -> 0
A47: БАЛАНС | B47: 1700 | C47: руб. | D47: =D33+D39+D46 -> 1.2525817e+14 | E47: =E33+E39+E46 -> 1.0406118e+15 | F47: =F33+F39+F46 -> 1.0571755e+15 | G47: =G33+G39+G46 -> 3.0512785e+12 | H47: =H33+H39+H46 -> 3.1449231e+12 | I47: =I33+I39+I46 -> 3.2409979e+12 | J47: =J33+J39+J46 -> 3.3395694e+12 | K47: =K33+K39+K46 -> 3.4407056e+12 | ... DV47: =DV33+DV39+DV46 -> 5.3646689e+13
G49: =G24-G47 -> 0 | H49: =H24-H47 -> 0 | I49: =I24-I47 -> 0 | J49: =J24-J47 -> 0 | K49: =K24-K47 -> 0 | L49: =L24-L47 -> 0 | M49: =M24-M47 -> 0 | N49: =N24-N47 -> 0 | ... DV49: =DV24-DV47 -> 0

Sheet Отчет о фин. рез до
A1: Отчет о финансовых результатах | E1: 1 год | Q1: 2 год | AC1: 3 год | AO1: 4 год | BA1: 5 год | BM1: 6 год | BY1: 7 год | CK1: 8 год | CW1: 9 год | DI1: 10 год
E2: 1 | F2: 2 | G2: 3 | H2: 4 | I2: 5 | J2: 6 | K2: 7 | L2: 8 | M2: 9 | N2: 10 | O2: 11 | P2: 12 | Q2: 1 | R2: 2 | S2: 3 | T2: 4 | U2: 5 | V2: 6 | W2: 7 | X2: 8 | Y2: 9 | Z2: 10 | AA2: 11 | AB2: 12 | AC2: 1 | AD2: 2 | AE2: 3 | AF2: 4 | AG2: 5 | AH2: 6 | AI2: 7 | AJ2: 8 | AK2: 9 | AL2: 10 | AM2: 11 | AN2: 12 | AO2: 1 | AP2: 2 | AQ2: 3 | AR2: 4 | AS2: 5 | AT2: 6 | AU2: 7 | AV2: 8 | AW2: 9 | AX2: 10 | AY2: 11 | AZ2: 12 | BA2: 1 | BB2: 2 | BC2: 3 | BD2: 4 | BE2: 5 | BF2: 6 | BG2: 7 | BH2: 8 | BI2: 9 | BJ2: 10 | BK2: 11 | BL2: 12 | BM2: 1 | BN2: 2 | BO2: 3 | BP2: 4 | BQ2: 5 | BR2: 6 | BS2: 7 | BT2: 8 | BU2: 9 | BV2: 10 | BW2: 11 | BX2: 12 | BY2: 1 | BZ2: 2 | CA2: 3 | CB2: 4 | CC2: 5 | CD2: 6 | CE2: 7 | CF2: 8 | CG2: 9 | CH2: 10 | CI2: 11 | CJ2: 12 | CK2: 1 | CL2: 2 | CM2: 3 | CN2: 4 | CO2: 5 | CP2: 6 | CQ2: 7 | CR2: 8 | CS2: 9 | CT2: 10 | CU2: 11 | CV2: 12 | CW2: 1 | CX2: 2 | CY2: 3 | CZ2: 4 | DA2: 5 | DB2: 6 | DC2: 7 | DD2: 8 | DE2: 9 | DF2: 10 | DG2: 11 | DH2: 12 | DI2: 1 | DJ2: 2 | DK2: 3 | DL2: 4 | DM2: 5 | DN2: 6 | DO2: 7 | DP2: 8 | DQ2: 9 | DR2: 10 | DS2: 11 | DT2: 12
A3: Наименование показателя | B3: Код | C3: Ед. из. | D3: Сумма | E3: 1 | F3: 2 | G3: 3 | H3: 4 | I3: 5 | J3: 6 | K3: 7 | L3: 8 | M3: 9 | N3: 10 | O3: 11 | P3: 12 | Q3: 13 | R3: 14 | S3: 15 | T3: 16 | U3: 17 | V3: 18 | W3: 19 | X3: 20 | Y3: 21 | Z3: 22 | AA3: 23 | AB3: 24 | AC3: 25 | AD3: 26 | AE3: 27 | AF3: 28 | AG3: 29 | AH3: 30 | AI3: 31 | AJ3: 32 | AK3: 33 | AL3: 34 | AM3: 35 | AN3: 36 | AO3: 1 | AP3: 2 | AQ3: 3 | AR3: 4 | AS3: 5 | AT3: 6 | AU3: 7 | AV3: 8 | AW3: 9 | AX3: 10 | AY3: 11 | AZ3: 12 | BA3: 13 | BB3: 14 | BC3: 15 | BD3: 16 | BE3: 17 | BF3: 18 | BG3: 19 | BH3: 20 | BI3: 21 | BJ3: 22 | BK3: 23 | BL3: 24 | BM3: 25 | BN3: 26 | BO3: 27 | BP3: 28 | BQ3: 29 | BR3: 30 | BS3: 31 | BT3: 32 | BU3: 33 | BV3: 34 | BW3: 35 | BX3: 36 | BY3: 1 | BZ3: 2 | CA3: 3 | CB3: 4 | CC3: 5 | CD3: 6 | CE3: 7 | CF3: 8 | CG3: 9 | CH3: 10 | CI3: 11 | CJ3: 12 | CK3: 13 | CL3: 14 | CM3: 15 | CN3: 16 | CO3: 17 | CP3: 18 | CQ3: 19 | CR3: 20 | CS3: 21 | CT3: 22 | CU3: 23 | CV3: 24 | CW3: 25 | CX3: 26 | CY3: 27 | CZ3: 28 | DA3: 29 | DB3: 30 | DC3: 31 | DD3: 32 | DE3: 33 | DF3: 34 | DG3: 35 | DH3: 36 | DI3: 1 | DJ3: 2 | DK3: 3 | DL3: 4 | DM3: 5 | DN3: 6 | DO3: 7 | DP3: 8 | DQ3: 9 | DR3: 10 | DS3: 11 | DT3: 12
A4: Выручка | B4: 2110 | C4: руб. | D4: =SUM(E4:AN4) -> 8.6155843e+13 | E4: ='Выручка, до'!D9 -> 9.1278535e+10 | F4: ='Выручка, до'!E9 -> 9.3644521e+10 | G4: ='Выручка, до'!F9 -> 9.6074892e+10 | H4: ='Выручка, до'!G9 -> 9.8571476e+10 | I4: ='Выручка, до'!H9 -> 1.0113615e+11 | J4: ='Выручка, до'!I9 -> 1.0377086e+11 | K4: ='Выручка, до'!J9 -> 1.0647759e+11 | L4: ='Выручка, до'!K9 -> 1.0925839e+11 | ... O4: ='Выручка, до'!N9 -> 1.1806667e+11 | P4: ='Выручка, до'!C9 -> 8.2014455e+13 | Q4: ='Выручка, до'!D9 -> 9.1278535e+10 | R4: ='Выручка, до'!E9 -> 9.3644521e+10 | S4: ='Выручка, до'!F9 -> 9.6074892e+10 | T4: ='Выручка, до'!G9 -> 9.8571476e+10 | U4: ='Выручка, до'!H9 -> 1.0113615e+11 | V4: ='Выручка, до'!I9 -> 1.0377086e+11 | W4: ='Выручка, до'!J9 -> 1.0647759e+11 | ... DT4: ='Выручка, до'!DG9 -> 1.672578e+12
A5: Себестоимость продаж | B5: 2120 | C5: руб. | D5: =SUM(E5:AN5) -> 2.8535034e+10 | E5: 0 | F5: 0 | G5: 0 | H5: 0 | I5: 0 | J5: 0 | K5: 0 | L5: 0 | M5: 0 | N5: 0 | O5: 0 | P5: 0 | Q5: ='Операционные затраты'!Q9 -> 1.1389077e+09 | R5: ='Операционные затраты'!R9 -> 1.1426978e+09 | S5: ='Операционные затраты'!S9 -> 1.1465568e+09 | T5: ='Операционные затраты'!T9 -> 1.1504861e+09 | U5: ='Операционные затраты'!U9 -> 1.1544869e+09 | V5: ='Операционные затраты'!V9 -> 1.1585608e+09 | W5: ='Операционные затраты'!W9 -> 1.1627091e+09 | X5: ='Операционные затраты'!X9 -> 1.1669334e+09 | ... DT5: ='Операционные затраты'!DT9 -> 2.4411101e+09
A6: Валовая прибыль (убыток) | B6: 2100 | C6: руб. | D6: =SUM(E6:AN6) -> 8.6127308e+13 | E6: =E4-E5 -> 9.1278535e+10 | F6: =F4-F5 -> 9.3644521e+10 | G6: =G4-G5 -> 9.6074892e+10 | H6: =H4-H5 -> 9.8571476e+10 | I6: =I4-I5 -> 1.0113615e+11 | J6: =J4-J5 -> 1.0377086e+11 | K6: =K4-K5 -> 1.0647759e+11 | L6: =L4-L5 -> 1.0925839e+11 | ... DT6: =DT4-DT5 -> 1.6701369e+12
A7: Коммерческие расходы | B7: 2210 | C7: руб. | D7: =SUM(E7:AN7) -> 14400000000 | E7: 0 | F7: 0 | G7: 0 | H7: 0 | I7: 0 | J7: 0 | K7: 0 | L7: 0 | M7: 0 | N7: 0 | O7: 0 | P7: 0 | Q7: ='Операционные затраты'!Q24 -> 600000000 | R7: ='Операционные затраты'!R24 -> 600000000 | S7: ='Операционные затраты'!S24 -> 600000000 | T7: ='Операционные затраты'!T24 -> 600000000 | U7: ='Операционные затраты'!U24 -> 600000000 | V7: ='Операционные затраты'!V24 -> 600000000 | W7: ='Операционные затраты'!W24 -> 600000000 | X7: ='Операционные затраты'!X24 -> 600000000 | ... DT7: ='Операционные затраты'!DT24 -> 600000000
A8: Управленческие расходы | B8: 2220 | C8: руб. | D8: =SUM(E8:AN8) -> 0 | E8: 0 | F8: 0 | G8: 0 | H8: 0 | I8: 0 | J8: 0 | K8: 0 | L8: 0 | M8: 0 | N8: 0 | O8: 0 | P8: 0 | Q8: ='Операционные затраты'!Q22 -> 0 | R8: ='Операционные затраты'!R22 -> 0 | S8: ='Операционные затраты'!S22 -> 0 | T8: ='Операционные затраты'!T22 -> 0 | U8: ='Операционные затраты'!U22 -> 0 | V8: ='Операционные затраты'!V22 -> 0 | W8: ='Операционные затраты'!W22 -> 0 | X8: ='Операционные затраты'!X22 -> 0 | ... DT8: ='Операционные затраты'!DT22 -> 0
A9: Прибыль (убыток) от продаж | B9: 2200 | C9: руб. | D9: =SUM(E9:AN9) -> 8.6112908e+13 | E9: =E4-E5-E7-E8 -> 9.1278535e+10 | F9: =F4-F5-F7-F8 -> 9.3644521e+10 | G9: =G4-G5-G7-G8 -> 9.6074892e+10 | H9: =H4-H5-H7-H8 -> 9.8571476e+10 | I9: =I4-I5-I7-I8 -> 1.0113615e+11 | J9: =J4-J5-J7-J8 -> 1.0377086e+11 | K9: =K4-K5-K7-K8 -> 1.0647759e+11 | L9: =L4-L5-L7-L8 -> 1.0925839e+11 | ... DT9: =DT4-DT5-DT7-DT8 -> 1.6695369e+12
A10: Доходы от участия в других организациях | B10: 2310 | C10: руб. | D10: =SUM(E10:AN10) -> 0 | E10: 0 | F10: 0 | G10: 0 | H10: 0 | I10: 0 | J10: 0 | K10: 0 | L10: 0 | M10: 0 | N10: 0 | O10: 0 | P10: 0 | Q10: 0 | R10: 0 | S10: 0 | T10: 0 | U10: 0 | V10: 0 | W10: 0 | X10: 0 | Y10: 0 | Z10: 0 | AA10: 0 | AB10: 0 | AC10: 0 | AD10: 0 | AE10: 0 | AF10: 0 | AG10: 0 | AH10: 0 | AI10: 0 | AJ10: 0 | AK10: 0 | AL10: 0 | AM10: 0 | AN10: 0 | AO10: 0 | AP10: 0 | AQ10: 0 | AR10: 0 | AS10: 0 | AT10: 0 | AU10: 0 | AV10: 0 | AW10: 0 | AX10: 0 | AY10: 0 | AZ10: 0 | BA10: 0 | BB10: 0 | BC10: 0 | BD10: 0 | BE10: 0 | BF10: 0 | BG10: 0 | BH10: 0 | BI10: 0 | BJ10: 0 | BK10: 0 | BL10: 0 | BM10: 0 | BN10: 0 | BO10: 0 | BP10: 0 | BQ10: 0 | BR10: 0 | BS10: 0 | BT10: 0 | BU10: 0 | BV10: 0 | BW10: 0 | BX10: 0 | BY10: 0 | BZ10: 0 | CA10: 0 | CB10: 0 | CC10: 0 | CD10: 0 | CE10: 0 | CF10: 0 | CG10: 0 | CH10: 0 | CI10: 0 | CJ10: 0 | CK10: 0 | CL10: 0 | CM10: 0 | CN10: 0 | CO10: 0 | CP10: 0 | CQ10: 0 | CR10: 0 | CS10: 0 | CT10: 0 | CU10: 0 | CV10: 0 | CW10: 0 | CX10: 0 | CY10: 0 | CZ10: 0 | DA10: 0 | DB10: 0 | DC10: 0 | DD10: 0 | DE10: 0 | DF10: 0 | DG10: 0 | DH10: 0 | DI10: 0 | DJ10: 0 | DK10: 0 | DL10: 0 | DM10: 0 | DN10: 0 | DO10: 0 | DP10: 0 | DQ10: 0 | DR10: 0 | DS10: 0 | DT10: 0
A11: Проценты к получению | B11: 2320 | C11: руб. | D11: =SUM(E11:AN11) -> 0 | E11: 0 | F11: 0 | G11: 0 | H11: 0 | I11: 0 | J11: 0 | K11: 0 | L11: 0 | M11: 0 | N11: 0 | O11: 0 | P11: 0 | Q11: 0 | R11: 0 | S11: 0 | T11: 0 | U11: 0 | V11: 0 | W11: 0 | X11: 0 | Y11: 0 | Z11: 0 | AA11: 0 | AB11: 0 | AC11: 0 | AD11: 0 | AE11: 0 | AF11: 0 | AG11: 0 | AH11: 0 | AI11: 0 | AJ11: 0 | AK11: 0 | AL11: 0 | AM11: 0 | AN11: 0 | AO11: 0 | AP11: 0 | AQ11: 0 | AR11: 0 | AS11: 0 | AT11: 0 | AU11: 0 | AV11: 0 | AW11: 0 | AX11: 0 | AY11: 0 | AZ11: 0 | BA11: 0 | BB11: 0 | BC11: 0 | BD11: 0 | BE11: 0 | BF11: 0 | BG11: 0 | BH11: 0 | BI11: 0 | BJ11: 0 | BK11: 0 | BL11: 0 | BM11: 0 | BN11: 0 | BO11: 0 | BP11: 0 | BQ11: 0 | BR11: 0 | BS11: 0 | BT11: 0 | BU11: 0 | BV11: 0 | BW11: 0 | BX11: 0 | BY11: 0 | BZ11: 0 | CA11: 0 | CB11: 0 | CC11: 0 | CD11: 0 | CE11: 0 | CF11: 0 | CG11: 0 | CH11: 0 | CI11: 0 | CJ11: 0 | CK11: 0 | CL11: 0 | CM11: 0 | CN11: 0 | CO11: 0 | CP11: 0 | CQ11: 0 | CR11: 0 | CS11: 0 | CT11: 0 | CU11: 0 | CV11: 0 | CW11: 0 | CX11: 0 | CY11: 0 | CZ11: 0 | DA11: 0 | DB11: 0 | DC11: 0 | DD11: 0 | DE11: 0 | DF11: 0 | DG11: 0 | DH11: 0 | DI11: 0 | DJ11: 0 | DK11: 0 | DL11: 0 | DM11: 0 | DN11: 0 | DO11: 0 | DP11: 0 | DQ11: 0 | DR11: 0 | DS11: 0 | DT11: 0
A12: Проценты к уплате | B12: 2330 | C12: руб. | D12: =SUM(E12:AN12) -> 0 | E12: 0 | F12: 0 | G12: 0 | H12: 0 | I12: 0 | J12: 0 | K12: 0 | L12: 0 | M12: 0 | N12: 0 | O12: 0 | P12: 0 | Q12: 0 | R12: 0 | S12: 0 | T12: 0 | U12: 0 | V12: 0 | W12: 0 | X12: 0 | Y12: 0 | Z12: 0 | AA12: 0 | AB12: 0 | AC12: 0 | AD12: 0 | AE12: 0 | AF12: 0 | AG12: 0 | AH12: 0 | AI12: 0 | AJ12: 0 | AK12: 0 | AL12: 0 | AM12: 0 | AN12: 0 | AO12: 0 | AP12: 0 | AQ12: 0 | AR12: 0 | AS12: 0 | AT12: 0 | AU12: 0 | AV12: 0 | AW12: 0 | AX12: 0 | AY12: 0 | AZ12: 0 | BA12: 0 | BB12: 0 | BC12: 0 | BD12: 0 | BE12: 0 | BF12: 0 | BG12: 0 | BH12: 0 | BI12: 0 | BJ12: 0 | BK12: 0 | BL12: 0 | BM12: 0 | BN12: 0 | BO12: 0 | BP12: 0 | BQ12: 0 | BR12: 0 | BS12: 0 | BT12: 0 | BU12: 0 | BV12: 0 | BW12: 0 | BX12: 0 | BY12: 0 | BZ12: 0 | CA12: 0 | CB12: 0 | CC12: 0 | CD12: 0 | CE12: 0 | CF12: 0 | CG12: 0 | CH12: 0 | CI12: 0 | CJ12: 0 | CK12: 0 | CL12: 0 | CM12: 0 | CN12: 0 | CO12: 0 | CP12: 0 | CQ12: 0 | CR12: 0 | CS12: 0 | CT12: 0 | CU12: 0 | CV12: 0 | CW12: 0 | CX12: 0 | CY12: 0 | CZ12: 0 | DA12: 0 | DB12: 0 | DC12: 0 | DD12: 0 | DE12: 0 | DF12: 0 | DG12: 0 | DH12: 0 | DI12: 0 | DJ12: 0 | DK12: 0 | DL12: 0 | DM12: 0 | DN12: 0 | DO12: 0 | DP12: 0 | DQ12: 0 | DR12: 0 | DS12: 0 | DT12: 0
A13: Прочие доходы | B13: 2340 | C13: руб. | D13: =SUM(E13:AN13) -> 0 | E13: 0 | F13: 0 | G13: 0 | H13: 0 | I13: 0 | J13: 0 | K13: 0 | L13: 0 | M13: 0 | N13: 0 | O13: 0 | P13: 0 | Q13: 0 | R13: 0 | S13: 0 | T13: 0 | U13: 0 | V13: 0 | W13: 0 | X13: 0 | Y13: 0 | Z13: 0 | AA13: 0 | AB13: 0 | AC13: 0 | AD13: 0 | AE13: 0 | AF13: 0 | AG13: 0 | AH13: 0 | AI13: 0 | AJ13: 0 | AK13: 0 | AL13: 0 | AM13: 0 | AN13: 0 | AO13: 0 | AP13: 0 | AQ13: 0 | AR13: 0 | AS13: 0 | AT13: 0 | AU13: 0 | AV13: 0 | AW13: 0 | AX13: 0 | AY13: 0 | AZ13: 0 | BA13: 0 | BB13: 0 | BC13: 0 | BD13: 0 | BE13: 0 | BF13: 0 | BG13: 0 | BH13: 0 | BI13: 0 | BJ13: 0 | BK13: 0 | BL13: 0 | BM13: 0 | BN13: 0 | BO13: 0 | BP13: 0 | BQ13: 0 | BR13: 0 | BS13: 0 | BT13: 0 | BU13: 0 | BV13: 0 | BW13: 0 | BX13: 0 | BY13: 0 | BZ13: 0 | CA13: 0 | CB13: 0 | CC13: 0 | CD13: 0 | CE13: 0 | CF13: 0 | CG13: 0 | CH13: 0 | CI13: 0 | CJ13: 0 | CK13: 0 | CL13: 0 | CM13: 0 | CN13: 0 | CO13: 0 | CP13: 0 | CQ13: 0 | CR13: 0 | CS13: 0 | CT13: 0 | CU13: 0 | CV13: 0 | CW13: 0 | CX13: 0 | CY13: 0 | CZ13: 0 | DA13: 0 | DB13: 0 | DC13: 0 | DD13: 0 | DE13: 0 | DF13: 0 | DG13: 0 | DH13: 0 | DI13: 0 | DJ13: 0 | DK13: 0 | DL13: 0 | DM13: 0 | DN13: 0 | DO13: 0 | DP13: 0 | DQ13: 0 | DR13: 0 | DS13: 0 | DT13: 0
A14: Прочие расходы | B14: 2350 | C14: руб. | D14: =SUM(E14:AN14) -> 0 | E14: 0 | F14: 0 | G14: 0 | H14: 0 | I14: 0 | J14: 0 | K14: 0 | L14: 0 | M14: 0 | N14: 0 | O14: 0 | P14: 0 | Q14: 0 | R14: 0 | S14: 0 | T14: 0 | U14: 0 | V14: 0 | W14: 0 | X14: 0 | Y14: 0 | Z14: 0 | AA14: 0 | AB14: 0 | AC14: 0 | AD14: 0 | AE14: 0 | AF14: 0 | AG14: 0 | AH14: 0 | AI14: 0 | AJ14: 0 | AK14: 0 | AL14: 0 | AM14: 0 | AN14: 0 | AO14: 0 | AP14: 0 | AQ14: 0 | AR14: 0 | AS14: 0 | AT14: 0 | AU14: 0 | AV14: 0 | AW14: 0 | AX14: 0 | AY14: 0 | AZ14: 0 | BA14: 0 | BB14: 0 | BC14: 0 | BD14: 0 | BE14: 0 | BF14: 0 | BG14: 0 | BH14: 0 | BI14: 0 | BJ14: 0 | BK14: 0 | BL14: 0 | BM14: 0 | BN14: 0 | BO14: 0 | BP14: 0 | BQ14: 0 | BR14: 0 | BS14: 0 | BT14: 0 | BU14: 0 | BV14: 0 | BW14: 0 | BX14: 0 | BY14: 0 | BZ14: 0 | CA14: 0 | CB14: 0 | CC14: 0 | CD14: 0 | CE14: 0 | CF14: 0 | CG14: 0 | CH14: 0 | CI14: 0 | CJ14: 0 | CK14: 0 | CL14: 0 | CM14: 0 | CN14: 0 | CO14: 0 | CP14: 0 | CQ14: 0 | CR14: 0 | CS14: 0 | CT14: 0 | CU14: 0 | CV14: 0 | CW14: 0 | CX14: 0 | CY14: 0 | CZ14: 0 | DA14: 0 | DB14: 0 | DC14: 0 | DD14: 0 | DE14: 0 | DF14: 0 | DG14: 0 | DH14: 0 | DI14: 0 | DJ14: 0 | DK14: 0 | DL14: 0 | DM14: 0 | DN14: 0 | DO14: 0 | DP14: 0 | DQ14: 0 | DR14: 0 | DS14: 0 | DT14: 0
A15: Прибыль (убыток) до налогообложения | B15: 2300 | C15: руб. | D15: =SUM(E15:AN15) -> 8.6112908e+13 | E15: =E9+E11-E12+E13-E14 -> 9.1278535e+10 | F15: =F9+F11-F12+F13-F14 -> 9.3644521e+10 | G15: =G9+G11-G12+G13-G14 -> 9.6074892e+10 | H15: =H9+H11-H12+H13-H14 -> 9.8571476e+10 | I15: =I9+I11-I12+I13-I14 -> 1.0113615e+11 | J15: =J9+J11-J12+J13-J14 -> 1.0377086e+11 | K15: =K9+K11-K12+K13-K14 -> 1.0647759e+11 | L15: =L9+L11-L12+L13-L14 -> 1.0925839e+11 | ... DT15: =DT9+DT11-DT12+DT13-DT14 -> 1.6695369e+12
A16: Текущий налог на прибыль, 6% | B16: 2410 | C16: руб. | D16: =SUM(E16:AN16) -> 2.0505727e+11 | E16: 0 | F16: 0 | G16: 0 | H16: 0 | I16: 0 | J16: 0 | K16: 0 | L16: 0 | M16: 0 | N16: 0 | O16: 0 | P16: 0 | Q16: ='Налоги и сборы до'!Q5 -> 6.217482e+09 | R16: ='Налоги и сборы до'!R5 -> 6.3810739e+09 | S16: ='Налоги и сборы до'!S5 -> 6.5491773e+09 | T16: ='Налоги и сборы до'!T5 -> 6.7219217e+09 | U16: ='Налоги и сборы до'!U5 -> 6.8994404e+09 | V16: ='Налоги и сборы до'!V5 -> 7.0818704e+09 | W16: ='Налоги и сборы до'!W5 -> 7.2693531e+09 | X16: ='Налоги и сборы до'!X5 -> 7.462034e+09 | ... DT16: ='Налоги и сборы до'!DT5 -> 1.1807033e+11
A17: Изменение отложенных налоговых обязательств | B17: 2430 | C17: руб. | D17: =SUM(E17:AN17) -> 0 | E17: 0 | F17: 0 | G17: 0 | H17: 0 | I17: 0 | J17: 0 | K17: 0 | L17: 0 | M17: 0 | N17: 0 | O17: 0 | P17: 0 | Q17: 0 | R17: 0 | S17: 0 | T17: 0 | U17: 0 | V17: 0 | W17: 0 | X17: 0 | Y17: 0 | Z17: 0 | AA17: 0 | AB17: 0 | AC17: 0 | AD17: 0 | AE17: 0 | AF17: 0 | AG17: 0 | AH17: 0 | AI17: 0 | AJ17: 0 | AK17: 0 | AL17: 0 | AM17: 0 | AN17: 0 | AO17: 0 | AP17: 0 | AQ17: 0 | AR17: 0 | AS17: 0 | AT17: 0 | AU17: 0 | AV17: 0 | AW17: 0 | AX17: 0 | AY17: 0 | AZ17: 0 | BA17: 0 | BB17: 0 | BC17: 0 | BD17: 0 | BE17: 0 | BF17: 0 | BG17: 0 | BH17: 0 | BI17: 0 | BJ17: 0 | BK17: 0 | BL17: 0 | BM17: 0 | BN17: 0 | BO17: 0 | BP17: 0 | BQ17: 0 | BR17: 0 | BS17: 0 | BT17: 0 | BU17: 0 | BV17: 0 | BW17: 0 | BX17: 0 | BY17: 0 | BZ17: 0 | CA17: 0 | CB17: 0 | CC17: 0 | CD17: 0 | CE17: 0 | CF17: 0 | CG17: 0 | CH17: 0 | CI17: 0 | CJ17: 0 | CK17: 0 | CL17: 0 | CM17: 0 | CN17: 0 | CO17: 0 | CP17: 0 | CQ17: 0 | CR17: 0 | CS17: 0 | CT17: 0 | CU17: 0 | CV17: 0 | CW17: 0 | CX17: 0 | CY17: 0 | CZ17: 0 | DA17: 0 | DB17: 0 | DC17: 0 | DD17: 0 | DE17: 0 | DF17: 0 | DG17: 0 | DH17: 0 | DI17: 0 | DJ17: 0 | DK17: 0 | DL17: 0 | DM17: 0 | DN17: 0 | DO17: 0 | DP17: 0 | DQ17: 0 | DR17: 0 | DS17: 0 | DT17: 0
A18: Изменение отложенных налоговых активов | B18: 2450 | C18: руб. | D18: =SUM(E18:AN18) -> 0 | E18: 0 | F18: 0 | G18: 0 | H18: 0 | I18: 0 | J18: 0 | K18: 0 | L18: 0 | M18: 0 | N18: 0 | O18: 0 | P18: 0 | Q18: 0 | R18: 0 | S18: 0 | T18: 0 | U18: 0 | V18: 0 | W18: 0 | X18: 0 | Y18: 0 | Z18: 0 | AA18: 0 | AB18: 0 | AC18: 0 | AD18: 0 | AE18: 0 | AF18: 0 | AG18: 0 | AH18: 0 | AI18: 0 | AJ18: 0 | AK18: 0 | AL18: 0 | AM18: 0 | AN18: 0 | AO18: 0 | AP18: 0 | AQ18: 0 | AR18: 0 | AS18: 0 | AT18: 0 | AU18: 0 | AV18: 0 | AW18: 0 | AX18: 0 | AY18: 0 | AZ18: 0 | BA18: 0 | BB18: 0 | BC18: 0 | BD18: 0 | BE18: 0 | BF18: 0 | BG18: 0 | BH18: 0 | BI18: 0 | BJ18: 0 | BK18: 0 | BL18: 0 | BM18: 0 | BN18: 0 | BO18: 0 | BP18: 0 | BQ18: 0 | BR18: 0 | BS18: 0 | BT18: 0 | BU18: 0 | BV18: 0 | BW18: 0 | BX18: 0 | BY18: 0 | BZ18: 0 | CA18: 0 | CB18: 0 | CC18: 0 | CD18: 0 | CE18: 0 | CF18: 0 | CG18: 0 | CH18: 0 | CI18: 0 | CJ18: 0 | CK18: 0 | CL18: 0 | CM18: 0 | CN18: 0 | CO18: 0 | CP18: 0 | CQ18: 0 | CR18: 0 | CS18: 0 | CT18: 0 | CU18: 0 | CV18: 0 | CW18: 0 | CX18: 0 | CY18: 0 | CZ18: 0 | DA18: 0 | DB18: 0 | DC18: 0 | DD18: 0 | DE18: 0 | DF18: 0 | DG18: 0 | DH18: 0 | DI18: 0 | DJ18: 0 | DK18: 0 | DL18: 0 | DM18: 0 | DN18: 0 | DO18: 0 | DP18: 0 | DQ18: 0 | DR18: 0 | DS18: 0 | DT18: 0
A19: Прочее | B19: 2460 | C19: руб. | D19: =SUM(E19:AN19) -> 0 | E19: 0 | F19: 0 | G19: 0 | H19: 0 | I19: 0 | J19: 0 | K19: 0 | L19: 0 | M19: 0 | N19: 0 | O19: 0 | P19: 0 | Q19: 0 | R19: 0 | S19: 0 | T19: 0 | U19: 0 | V19: 0 | W19: 0 | X19: 0 | Y19: 0 | Z19: 0 | AA19: 0 | AB19: 0 | AC19: 0 | AD19: 0 | AE19: 0 | AF19: 0 | AG19: 0 | AH19: 0 | AI19: 0 | AJ19: 0 | AK19: 0 | AL19: 0 | AM19: 0 | AN19: 0 | AO19: 0 | AP19: 0 | AQ19: 0 | AR19: 0 | AS19: 0 | AT19: 0 | AU19: 0 | AV19: 0 | AW19: 0 | AX19: 0 | AY19: 0 | AZ19: 0 | BA19: 0 | BB19: 0 | BC19: 0 | BD19: 0 | BE19: 0 | BF19: 0 | BG19: 0 | BH19: 0 | BI19: 0 | BJ19: 0 | BK19: 0 | BL19: 0 | BM19: 0 | BN19: 0 | BO19: 0 | BP19: 0 | BQ19: 0 | BR19: 0 | BS19: 0 | BT19: 0 | BU19: 0 | BV19: 0 | BW19: 0 | BX19: 0 | BY19: 0 | BZ19: 0 | CA19: 0 | CB19: 0 | CC19: 0 | CD19: 0 | CE19: 0 | CF19: 0 | CG19: 0 | CH19: 0 | CI19: 0 | CJ19: 0 | CK19: 0 | CL19: 0 | CM19: 0 | CN19: 0 | CO19: 0 | CP19: 0 | CQ19: 0 | CR19: 0 | CS19: 0 | CT19: 0 | CU19: 0 | CV19: 0 | CW19: 0 | CX19: 0 | CY19: 0 | CZ19: 0 | DA19: 0 | DB19: 0 | DC19: 0 | DD19: 0 | DE19: 0 | DF19: 0 | DG19: 0 | DH19: 0 | DI19: 0 | DJ19: 0 | DK19: 0 | DL19: 0 | DM19: 0 | DN19: 0 | DO19: 0 | DP19: 0 | DQ19: 0 | DR19: 0 | DS19: 0 | DT19: 0
A20: Чистая прибыль (убыток) | B20: 2400 | C20: руб. | D20: =SUM(E20:AN20) -> 8.5907851e+13 | E20: =E4-E5-E7-E8-E14-E16 -> 9.1278535e+10 | F20: =F4-F5-F7-F8-F14-F16 -> 9.3644521e+10 | G20: =G4-G5-G7-G8-G14-G16 -> 9.6074892e+10 | H20: =H4-H5-H7-H8-H14-H16 -> 9.8571476e+10 | I20: =I4-I5-I7-I8-I14-I16 -> 1.0113615e+11 | J20: =J4-J5-J7-J8-J14-J16 -> 1.0377086e+11 | K20: =K4-K5-K7-K8-K14-K16 -> 1.0647759e+11 | L20: =L4-L5-L7-L8-L14-L16 -> 1.0925839e+11 | ... DT20: =DT4-DT5-DT7-DT8-DT14-DT16 -> 1.5514665e+12
A21: Накопительный итог | C21: руб. | D21: =SUM(E21:AN21) -> 2.1164855e+15 | E21: =E20 -> 9.1278535e+10 | F21: =F20+E21 -> 1.8492306e+11 | G21: =G20+F21 -> 2.8099795e+11 | H21: =H20+G21 -> 3.7956943e+11 | I21: =I20+H21 -> 4.8070558e+11 | J21: =J20+I21 -> 5.8447644e+11 | K21: =K20+J21 -> 6.9095403e+11 | L21: =L20+K21 -> 8.0021242e+11 | M21: =M20+L21 -> 9.1232779e+11 | ... AN21: =AN20+AM21 -> 8.5907851e+13 | AO21: =AO20 -> 1.5662729e+11 | AP21: =AP20+AO21 -> 3.1747547e+11 | AQ21: =AQ20+AP21 -> 4.8266237e+11 | AR21: =AR20+AQ21 -> 6.5230924e+11 | AS21: =AS20+AR21 -> 8.2654083e+11 | AT21: =AT20+AS21 -> 1.0054855e+12 | AU21: =AU20+AT21 -> 1.1892755e+12 | AV21: =AV20+AU21 -> 1.3780465e+12 | AW21: =AW20+AV21 -> 1.5719387e+12 | ... DT21: =DT20+DS21 -> 5.0686689e+13

Sheet Отчет о движ. ден. ср.
B2: Отчёт о движении денежных средств | F2: 1 год | R2: 2 год | AD2: 3 год | AP2: 4 год | BB2: 5 год | BN2: 6 год | BZ2: 7 год | CL2: 8 год | CX2: 9 год | DJ2: 10 год
F3: 1 | G3: 2 | H3: 3 | I3: 4 | J3: 5 | K3: 6 | L3: 7 | M3: 8 | N3: 9 | O3: 10 | P3: 11 | Q3: 12 | R3: 1 | S3: 2 | T3: 3 | U3: 4 | V3: 5 | W3: 6 | X3: 7 | Y3: 8 | Z3: 9 | AA3: 10 | AB3: 11 | AC3: 12 | AD3: 1 | AE3: 2 | AF3: 3 | AG3: 4 | AH3: 5 | AI3: 6 | AJ3: 7 | AK3: 8 | AL3: 9 | AM3: 10 | AN3: 11 | AO3: 12 | AP3: 1 | AQ3: 2 | AR3: 3 | AS3: 4 | AT3: 5 | AU3: 6 | AV3: 7 | AW3: 8 | AX3: 9 | AY3: 10 | AZ3: 11 | BA3: 12 | BB3: 1 | BC3: 2 | BD3: 3 | BE3: 4 | BF3: 5 | BG3: 6 | BH3: 7 | BI3: 8 | BJ3: 9 | BK3: 10 | BL3: 11 | BM3: 12 | BN3: 1 | BO3: 2 | BP3: 3 | BQ3: 4 | BR3: 5 | BS3: 6 | BT3: 7 | BU3: 8 | BV3: 9 | BW3: 10 | BX3: 11 | BY3: 12 | BZ3: 1 | CA3: 2 | CB3: 3 | CC3: 4 | CD3: 5 | CE3: 6 | CF3: 7 | CG3: 8 | CH3: 9 | CI3: 10 | CJ3: 11 | CK3: 12 | CL3: 1 | CM3: 2 | CN3: 3 | CO3: 4 | CP3: 5 | CQ3: 6 | CR3: 7 | CS3: 8 | CT3: 9 | CU3: 10 | CV3: 11 | CW3: 12 | CX3: 1 | CY3: 2 | CZ3: 3 | DA3: 4 | DB3: 5 | DC3: 6 | DD3: 7 | DE3: 8 | DF3: 9 | DG3: 10 | DH3: 11 | DI3: 12 | DJ3: 1 | DK3: 2 | DL3: 3 | DM3: 4 | DN3: 5 | DO3: 6 | DP3: 7 | DQ3: 8 | DR3: 9 | DS3: 10 | DT3: 11 | DU3: 12
B4: Наименование показателя | C4: Код | D4: Ед. из. | E4: Сумма | F4: 1 | G4: 2 | H4: 3 | I4: 4 | J4: 5 | K4: 6 | L4: 7 | M4: 8 | N4: 9 | O4: 10 | P4: 11 | Q4: 12 | R4: 13 | S4: 14 | T4: 15 | U4: 16 | V4: 17 | W4: 18 | X4: 19 | Y4: 20 | Z4: 21 | AA4: 22 | AB4: 23 | AC4: 24 | AD4: 25 | AE4: 26 | AF4: 27 | AG4: 28 | AH4: 29 | AI4: 30 | AJ4: 31 | AK4: 32 | AL4: 33 | AM4: 34 | AN4: 35 | AO4: 36 | AP4: 1 | AQ4: 2 | AR4: 3 | AS4: 4 | AT4: 5 | AU4: 6 | AV4: 7 | AW4: 8 | AX4: 9 | AY4: 10 | AZ4: 11 | BA4: 12 | BB4: 13 | BC4: 14 | BD4: 15 | BE4: 16 | BF4: 17 | BG4: 18 | BH4: 19 | BI4: 20 | BJ4: 21 | BK4: 22 | BL4: 23 | BM4: 24 | BN4: 25 | BO4: 26 | BP4: 27 | BQ4: 28 | BR4: 29 | BS4: 30 | BT4: 31 | BU4: 32 | BV4: 33 | BW4: 34 | BX4: 35 | BY4: 36 | BZ4: 1 | CA4: 2 | CB4: 3 | CC4: 4 | CD4: 5 | CE4: 6 | CF4: 7 | CG4: 8 | CH4: 9 | CI4: 10 | CJ4: 11 | CK4: 12 | CL4: 13 | CM4: 14 | CN4: 15 | CO4: 16 | CP4: 17 | CQ4: 18 | CR4: 19 | CS4: 20 | CT4: 21 | CU4: 22 | CV4: 23 | CW4: 24 | CX4: 25 | CY4: 26 | CZ4: 27 | DA4: 28 | DB4: 29 | DC4: 30 | DD4: 31 | DE4: 32 | DF4: 33 | DG4: 34 | DH4: 35 | DI4: 36 | DJ4: 1 | DK4: 2 | DL4: 3 | DM4: 4 | DN4: 5 | DO4: 6 | DP4: 7 | DQ4: 8 | DR4: 9 | DS4: 10 | DT4: 11 | DU4: 12
B5: Денежные потоки от текущих операций
B6: Поступления - всего | C6: 4110 | D6: руб. | E6: =SUM(F6:DU6) -> 5.7707737e+13 | F6: =F8+F9+F10+F11 -> 0 | G6: =G8+G9+G10+G11 -> 0 | H6: =H8+H9+H10+H11 -> 0 | I6: =I8+I9+I10+I11 -> 0 | J6: =J8+J9+J10+J11 -> 0 | K6: =K8+K9+K10+K11 -> 0 | L6: =L8+L9+L10+L11 -> 0 | M6: =M8+M9+M10+M11 -> 0 | ... DU6: =DU8+DU9+DU10+DU11 -> 1.672578e+12
B7: в том числе:
B8: от продажи продукции, товаров, работ и услуг | C8: 4111 | D8: руб. | E8: =SUM(F8:DU8) -> 5.7707737e+13 | F8: 0 | G8: ='Экономический эффект'!F15 -> 0 | H8: ='Экономический эффект'!G15 -> 0 | I8: ='Экономический эффект'!H15 -> 0 | J8: ='Экономический эффект'!I15 -> 0 | K8: ='Экономический эффект'!J15 -> 0 | L8: ='Экономический эффект'!K15 -> 0 | M8: ='Экономический эффект'!L15 -> 0 | N8: ='Экономический эффект'!M15 -> 0 | ... Q8: ='Экономический эффект'!P15 -> 0 | R8: ='Выручка, до'!D9 -> 9.1278535e+10 | S8: ='Выручка, до'!E9 -> 9.3644521e+10 | T8: ='Выручка, до'!F9 -> 9.6074892e+10 | U8: ='Выручка, до'!G9 -> 9.8571476e+10 | V8: ='Выручка, до'!H9 -> 1.0113615e+11 | W8: ='Выручка, до'!I9 -> 1.0377086e+11 | X8: ='Выручка, до'!J9 -> 1.0647759e+11 | Y8: ='Выручка, до'!K9 -> 1.0925839e+11 | ... DU8: ='Выручка, до'!DG9 -> 1.672578e+12
B9: арендных платежей, лицензионных платежей, роялти, комиссионных и иных аналогичных платежей | C9: 4112 | D9: руб. | E9: =SUM(F9:AO9) -> 0 | F9: 0 | G9: 0 | H9: 0 | I9: 0 | J9: 0 | K9: 0 | L9: 0 | M9: 0 | N9: 0 | O9: 0 | P9: 0 | Q9: 0 | R9: 0 | S9: 0 | T9: 0 | U9: 0 | V9: 0 | W9: 0 | X9: 0 | Y9: 0 | Z9: 0 | AA9: 0 | AB9: 0 | AC9: 0 | AD9: 0 | AE9: 0 | AF9: 0 | AG9: 0 | AH9: 0 | AI9: 0 | AJ9: 0 | AK9: 0 | AL9: 0 | AM9: 0 | AN9: 0 | AO9: 0 | AP9: 0 | AQ9: 0 | AR9: 0 | AS9: 0 | AT9: 0 | AU9: 0 | AV9: 0 | AW9: 0 | AX9: 0 | AY9: 0 | AZ9: 0 | BA9: 0 | BB9: 0 | BC9: 0 | BD9: 0 | BE9: 0 | BF9: 0 | BG9: 0 | BH9: 0 | BI9: 0 | BJ9: 0 | BK9: 0 | BL9: 0 | BM9: 0 | BN9: 0 | BO9: 0 | BP9: 0 | BQ9: 0 | BR9: 0 | BS9: 0 | BT9: 0 | BU9: 0 | BV9: 0 | BW9: 0 | BX9: 0 | BY9: 0 | BZ9: 0 | CA9: 0 | CB9: 0 | CC9: 0 | CD9: 0 | CE9: 0 | CF9: 0 | CG9: 0 | CH9: 0 | CI9: 0 | CJ9: 0 | CK9: 0 | CL9: 0 | CM9: 0 | CN9: 0 | CO9: 0 | CP9: 0 | CQ9: 0 | CR9: 0 | CS9: 0 | CT9: 0 | CU9: 0 | CV9: 0 | CW9: 0 | CX9: 0 | CY9: 0 | CZ9: 0 | DA9: 0 | DB9: 0 | DC9: 0 | DD9: 0 | DE9: 0 | DF9: 0 | DG9: 0 | DH9: 0 | DI9: 0 | DJ9: 0 | DK9: 0 | DL9: 0 | DM9: 0 | DN9: 0 | DO9: 0 | DP9: 0 | DQ9: 0 | DR9: 0 | DS9: 0 | DT9: 0 | DU9: 0
B10: от перепродажи финансовых вложений | C10: 4113 | D10: руб. | E10: =SUM(F10:AO10) -> 0 | F10: 0 | G10: 0 | H10: 0 | I10: 0 | J10: 0 | K10: 0 | L10: 0 | M10: 0 | N10: 0 | O10: 0 | P10: 0 | Q10: 0 | R10: 0 | S10: 0 | T10: 0 | U10: 0 | V10: 0 | W10: 0 | X10: 0 | Y10: 0 | Z10: 0 | AA10: 0 | AB10: 0 | AC10: 0 | AD10: 0 | AE10: 0 | AF10: 0 | AG10: 0 | AH10: 0 | AI10: 0 | AJ10: 0 | AK10: 0 | AL10: 0 | AM10: 0 | AN10: 0 | AO10: 0 | AP10: 0 | AQ10: 0 | AR10: 0 | AS10: 0 | AT10: 0 | AU10: 0 | AV10: 0 | AW10: 0 | AX10: 0 | AY10: 0 | AZ10: 0 | BA10: 0 | BB10: 0 | BC10: 0 | BD10: 0 | BE10: 0 | BF10: 0 | BG10: 0 | BH10: 0 | BI10: 0 | BJ10: 0 | BK10: 0 | BL10: 0 | BM10: 0 | BN10: 0 | BO10: 0 | BP10: 0 | BQ10: 0 | BR10: 0 | BS10: 0 | BT10: 0 | BU10: 0 | BV10: 0 | BW10: 0 | BX10: 0 | BY10: 0 | BZ10: 0 | CA10: 0 | CB10: 0 | CC10: 0 | CD10: 0 | CE10: 0 | CF10: 0 | CG10: 0 | CH10: 0 | CI10: 0 | CJ10: 0 | CK10: 0 | CL10: 0 | CM10: 0 | CN10: 0 | CO10: 0 | CP10: 0 | CQ10: 0 | CR10: 0 | CS10: 0 | CT10: 0 | CU10: 0 | CV10: 0 | CW10: 0 | CX10: 0 | CY10: 0 | CZ10: 0 | DA10: 0 | DB10: 0 | DC10: 0 | DD10: 0 | DE10: 0 | DF10: 0 | DG10: 0 | DH10: 0 | DI10: 0 | DJ10: 0 | DK10: 0 | DL10: 0 | DM10: 0 | DN10: 0 | DO10: 0 | DP10: 0 | DQ10: 0 | DR10: 0 | DS10: 0 | DT10: 0 | DU10: 0
B11: прочие поступления | C11: 4119 | D11: руб. | E11: =SUM(F11:AO11) -> 0 | F11: 0 | G11: 0 | H11: 0 | I11: 0 | J11: 0 | K11: 0 | L11: 0 | M11: 0 | N11: 0 | O11: 0 | P11: 0 | Q11: 0 | R11: 0 | S11: 0 | T11: 0 | U11: 0 | V11: 0 | W11: 0 | X11: 0 | Y11: 0 | Z11: 0 | AA11: 0 | AB11: 0 | AC11: 0 | AD11: 0 | AE11: 0 | AF11: 0 | AG11: 0 | AH11: 0 | AI11: 0 | AJ11: 0 | AK11: 0 | AL11: 0 | AM11: 0 | AN11: 0 | AO11: 0 | AP11: 0 | AQ11: 0 | AR11: 0 | AS11: 0 | AT11: 0 | AU11: 0 | AV11: 0 | AW11: 0 | AX11: 0 | AY11: 0 | AZ11: 0 | BA11: 0 | BB11: 0 | BC11: 0 | BD11: 0 | BE11: 0 | BF11: 0 | BG11: 0 | BH11: 0 | BI11: 0 | BJ11: 0 | BK11: 0 | BL11: 0 | BM11: 0 | BN11: 0 | BO11: 0 | BP11: 0 | BQ11: 0 | BR11: 0 | BS11: 0 | BT11: 0 | BU11: 0 | BV11: 0 | BW11: 0 | BX11: 0 | BY11: 0 | BZ11: 0 | CA11: 0 | CB11: 0 | CC11: 0 | CD11: 0 | CE11: 0 | CF11: 0 | CG11: 0 | CH11: 0 | CI11: 0 | CJ11: 0 | CK11: 0 | CL11: 0 | CM11: 0 | CN11: 0 | CO11: 0 | CP11: 0 | CQ11: 0 | CR11: 0 | CS11: 0 | CT11: 0 | CU11: 0 | CV11: 0 | CW11: 0 | CX11: 0 | CY11: 0 | CZ11: 0 | DA11: 0 | DB11: 0 | DC11: 0 | DD11: 0 | DE11: 0 | DF11: 0 | DG11: 0 | DH11: 0 | DI11: 0 | DJ11: 0 | DK11: 0 | DL11: 0 | DM11: 0 | DN11: 0 | DO11: 0 | DP11: 0 | DQ11: 0 | DR11: 0 | DS11: 0 | DT11: 0 | DU11: 0
B12: Платежи - всего | C12: 4120 | D12: руб. | E12: =SUM(F12:DU12) -> 2.9932536e+13 | F12: =F14+F15+F16+F17+F18 -> 3.6209562e+10 | G12: =G14+G15+G16+G17+G18 -> 3.7061317e+10 | H12: =H14+H15+H16+H17+H18 -> 3.7936251e+10 | I12: =I14+I15+I16+I17+I18 -> 3.8835021e+10 | J12: =J14+J15+J16+J17+J18 -> 3.9758305e+10 | K12: =K14+K15+K16+K17+K18 -> 4.0706799e+10 | L12: =L14+L15+L16+L17+L18 -> 4.1681221e+10 | M12: =M14+M15+M16+M17+M18 -> 4.268231e+10 | ... DU12: =DU14+DU15+DU16+DU17+DU18 -> 8.5350581e+11
B13: в том числе:
B14: поставщикам (подрядчикам) за сырье, материалы, работы, услуги | C14: 4121 | D14: руб. | E14: =SUM(F14:DU14) -> 2.5785742e+11 | F14: ='Операционные затраты'!E37 -> 2103504999 | G14: ='Операционные затраты'!F37 -> 2103504999 | H14: ='Операционные затраты'!G37 -> 2103504999 | I14: ='Операционные затраты'!H37 -> 2103504999 | J14: ='Операционные затраты'!I37 -> 2103504999 | K14: ='Операционные затраты'!J37 -> 2103504999 | L14: ='Операционные затраты'!K37 -> 2103504999 | M14: ='Операционные затраты'!L37 -> 2103504999 | ... DU14: ='Операционные затраты'!DT37 -> 2.1538659e+09
B15: в связи с оплатой труда работников | C15: 4122 | D15: руб. | E15: =SUM(F15:DU15) -> 144002059992 | F15: =SUM('Операционные затраты'!E23:E26) -> 1200171666 | G15: =SUM('Операционные затраты'!F23:F26) -> 1200171666 | H15: =SUM('Операционные затраты'!G23:G26) -> 1200171666 | I15: =SUM('Операционные затраты'!H23:H26) -> 1200171666 | J15: =SUM('Операционные затраты'!I23:I26) -> 1200171666 | K15: =SUM('Операционные затраты'!J23:J26) -> 1200171666 | L15: =SUM('Операционные затраты'!K23:K26) -> 1200171666 | M15: =SUM('Операционные затраты'!L23:L26) -> 1200171666 | ... DU15: =SUM('Операционные затраты'!DT23:DT26) -> 1200000000
B16: процентов по долговым обязательствам | C16: 4123 | D16: руб. | E16: =SUM(F16:DU16) -> 0 | F16: 0 | G16: 0 | H16: 0 | I16: 0 | J16: 0 | K16: 0 | L16: 0 | M16: 0 | N16: 0 | O16: 0 | P16: 0 | Q16: 0 | R16: 0 | S16: 0 | T16: 0 | U16: 0 | V16: 0 | W16: 0 | X16: 0 | Y16: 0 | Z16: 0 | AA16: 0 | AB16: 0 | AC16: 0 | AD16: 0 | AE16: 0 | AF16: 0 | AG16: 0 | AH16: 0 | AI16: 0 | AJ16: 0 | AK16: 0 | AL16: 0 | AM16: 0 | AN16: 0 | AO16: 0 | AP16: 0 | AQ16: 0 | AR16: 0 | AS16: 0 | AT16: 0 | AU16: 0 | AV16: 0 | AW16: 0 | AX16: 0 | AY16: 0 | AZ16: 0 | BA16: 0 | BB16: 0 | BC16: 0 | BD16: 0 | BE16: 0 | BF16: 0 | BG16: 0 | BH16: 0 | BI16: 0 | BJ16: 0 | BK16: 0 | BL16: 0 | BM16: 0 | BN16: 0 | BO16: 0 | BP16: 0 | BQ16: 0 | BR16: 0 | BS16: 0 | BT16: 0 | BU16: 0 | BV16: 0 | BW16: 0 | BX16: 0 | BY16: 0 | BZ16: 0 | CA16: 0 | CB16: 0 | CC16: 0 | CD16: 0 | CE16: 0 | CF16: 0 | CG16: 0 | CH16: 0 | CI16: 0 | CJ16: 0 | CK16: 0 | CL16: 0 | CM16: 0 | CN16: 0 | CO16: 0 | CP16: 0 | CQ16: 0 | CR16: 0 | CS16: 0 | CT16: 0 | CU16: 0 | CV16: 0 | CW16: 0 | CX16: 0 | CY16: 0 | CZ16: 0 | DA16: 0 | DB16: 0 | DC16: 0 | DD16: 0 | DE16: 0 | DF16: 0 | DG16: 0 | DH16: 0 | DI16: 0 | DJ16: 0 | DK16: 0 | DL16: 0 | DM16: 0 | DN16: 0 | DO16: 0 | DP16: 0 | DQ16: 0 | DR16: 0 | DS16: 0 | DT16: 0 | DU16: 0
B17: налога на прибыль организаций | C17: 4124 | D17: руб. | E17: =SUM(F17:DU17) -> 4.1007228e+12 | F17: ='Налоги и сборы до'!E5 -> 4.5639268e+09 | G17: ='Налоги и сборы до'!F5 -> 4.6822261e+09 | H17: ='Налоги и сборы до'!G5 -> 4.8037446e+09 | I17: ='Налоги и сборы до'!H5 -> 4.9285738e+09 | J17: ='Налоги и сборы до'!I5 -> 5.0568077e+09 | K17: ='Налоги и сборы до'!J5 -> 5.188543e+09 | L17: ='Налоги и сборы до'!K5 -> 5.3238794e+09 | M17: ='Налоги и сборы до'!L5 -> 5.4629195e+09 | ... DU17: ='Налоги и сборы до'!DT5 -> 1.1807033e+11
B18: прочие платежи | C18: 4129 | D18: руб. | E18: =SUM(F18:DU18) -> 2.5429953e+13 | F18: =SUM('Налоги и сборы до'!E6,'Налоги и сборы до'!E7,'Налоги и сборы до'!E9) -> 2.8341959e+10 | G18: =SUM('Налоги и сборы до'!F6,'Налоги и сборы до'!F7,'Налоги и сборы до'!F9) -> 2.9075415e+10 | H18: =SUM('Налоги и сборы до'!G6,'Налоги и сборы до'!G7,'Налоги и сборы до'!G9) -> 2.982883e+10 | I18: =SUM('Налоги и сборы до'!H6,'Налоги и сборы до'!H7,'Налоги и сборы до'!H9) -> 3.0602771e+10 | J18: =SUM('Налоги и сборы до'!I6,'Налоги и сборы до'!I7,'Налоги и сборы до'!I9) -> 3.139782e+10 | K18: =SUM('Налоги и сборы до'!J6,'Налоги и сборы до'!J7,'Налоги и сборы до'!J9) -> 3.2214579e+10 | L18: =SUM('Налоги и сборы до'!K6,'Налоги и сборы до'!K7,'Налоги и сборы до'!K9) -> 3.3053665e+10 | M18: =SUM('Налоги и сборы до'!L6,'Налоги и сборы до'!L7,'Налоги и сборы до'!L9) -> 3.3915714e+10 | ... DU18: =SUM('Налоги и сборы до'!DT6,'Налоги и сборы до'!DT7,'Налоги и сборы до'!DT9) -> 7.3208162e+11
B19: Сальдо денежных потоков от текущих операций | C19: 4100 | D19: руб. | E19: =SUM(F19:DU19) -> 2.7775202e+13 | F19: =F6-F12 -> -3.6209562e+10 | G19: =G6-G12 -> -3.7061317e+10 | H19: =H6-H12 -> -3.7936251e+10 | I19: =I6-I12 -> -3.8835021e+10 | J19: =J6-J12 -> -3.9758305e+10 | K19: =K6-K12 -> -4.0706799e+10 | L19: =L6-L12 -> -4.1681221e+10 | M19: =M6-M12 -> -4.268231e+10 | ... DU19: =DU6-DU12 -> 8.1907217e+11
B20: Денежные потоки от инвестиционных операций
B21: Поступления - всего | C21: 4210 | D21: руб. | E21: =SUM(F21:AO21) -> 0 | F21: =F23+F24+F25+F26+F27 -> 0 | G21: =G23+G24+G25+G26+G27 -> 0 | H21: =H23+H24+H25+H26+H27 -> 0 | I21: =I23+I24+I25+I26+I27 -> 0 | J21: =J23+J24+J25+J26+J27 -> 0 | K21: =K23+K24+K25+K26+K27 -> 0 | L21: =L23+L24+L25+L26+L27 -> 0 | M21: =M23+M24+M25+M26+M27 -> 0 | ... DU21: =DU23+DU24+DU25+DU26+DU27 -> 0
B22: в том числе:
B23: от продажи внеоборотных активов (кроме финансовых вложений) | C23: 4211 | D23: руб. | E23: =SUM(F23:AO23) -> 0 | F23: 0 | G23: 0 | H23: 0 | I23: 0 | J23: 0 | K23: 0 | L23: 0 | M23: 0 | N23: 0 | O23: 0 | P23: 0 | Q23: 0 | R23: 0 | S23: 0 | T23: 0 | U23: 0 | V23: 0 | W23: 0 | X23: 0 | Y23: 0 | Z23: 0 | AA23: 0 | AB23: 0 | AC23: 0 | AD23: 0 | AE23: 0 | AF23: 0 | AG23: 0 | AH23: 0 | AI23: 0 | AJ23: 0 | AK23: 0 | AL23: 0 | AM23: 0 | AN23: 0 | AO23: 0 | AP23: 0 | AQ23: 0 | AR23: 0 | AS23: 0 | AT23: 0 | AU23: 0 | AV23: 0 | AW23: 0 | AX23: 0 | AY23: 0 | AZ23: 0 | BA23: 0 | BB23: 0 | BC23: 0 | BD23: 0 | BE23: 0 | BF23: 0 | BG23: 0 | BH23: 0 | BI23: 0 | BJ23: 0 | BK23: 0 | BL23: 0 | BM23: 0 | BN23: 0 | BO23: 0 | BP23: 0 | BQ23: 0 | BR23: 0 | BS23: 0 | BT23: 0 | BU23: 0 | BV23: 0 | BW23: 0 | BX23: 0 | BY23: 0 | BZ23: 0 | CA23: 0 | CB23: 0 | CC23: 0 | CD23: 0 | CE23: 0 | CF23: 0 | CG23: 0 | CH23: 0 | CI23: 0 | CJ23: 0 | CK23: 0 | CL23: 0 | CM23: 0 | CN23: 0 | CO23: 0 | CP23: 0 | CQ23: 0 | CR23: 0 | CS23: 0 | CT23: 0 | CU23: 0 | CV23: 0 | CW23: 0 | CX23: 0 | CY23: 0 | CZ23: 0 | DA23: 0 | DB23: 0 | DC23: 0 | DD23: 0 | DE23: 0 | DF23: 0 | DG23: 0 | DH23: 0 | DI23: 0 | DJ23: 0 | DK23: 0 | DL23: 0 | DM23: 0 | DN23: 0 | DO23: 0 | DP23: 0 | DQ23: 0 | DR23: 0 | DS23: 0 | DT23: 0 | DU23: 0
B24: от продажи акций других организаций (долей участия) | C24: 4212 | D24: руб. | E24: =SUM(F24:AO24) -> 0 | F24: 0 | G24: 0 | H24: 0 | I24: 0 | J24: 0 | K24: 0 | L24: 0 | M24: 0 | N24: 0 | O24: 0 | P24: 0 | Q24: 0 | R24: 0 | S24: 0 | T24: 0 | U24: 0 | V24: 0 | W24: 0 | X24: 0 | Y24: 0 | Z24: 0 | AA24: 0 | AB24: 0 | AC24: 0 | AD24: 0 | AE24: 0 | AF24: 0 | AG24: 0 | AH24: 0 | AI24: 0 | AJ24: 0 | AK24: 0 | AL24: 0 | AM24: 0 | AN24: 0 | AO24: 0 | AP24: 0 | AQ24: 0 | AR24: 0 | AS24: 0 | AT24: 0 | AU24: 0 | AV24: 0 | AW24: 0 | AX24: 0 | AY24: 0 | AZ24: 0 | BA24: 0 | BB24: 0 | BC24: 0 | BD24: 0 | BE24: 0 | BF24: 0 | BG24: 0 | BH24: 0 | BI24: 0 | BJ24: 0 | BK24: 0 | BL24: 0 | BM24: 0 | BN24: 0 | BO24: 0 | BP24: 0 | BQ24: 0 | BR24: 0 | BS24: 0 | BT24: 0 | BU24: 0 | BV24: 0 | BW24: 0 | BX24: 0 | BY24: 0 | BZ24: 0 | CA24: 0 | CB24: 0 | CC24: 0 | CD24: 0 | CE24: 0 | CF24: 0 | CG24: 0 | CH24: 0 | CI24: 0 | CJ24: 0 | CK24: 0 | CL24: 0 | CM24: 0 | CN24: 0 | CO24: 0 | CP24: 0 | CQ24: 0 | CR24: 0 | CS24: 0 | CT24: 0 | CU24: 0 | CV24: 0 | CW24: 0 | CX24: 0 | CY24: 0 | CZ24: 0 | DA24: 0 | DB24: 0 | DC24: 0 | DD24: 0 | DE24: 0 | DF24: 0 | DG24: 0 | DH24: 0 | DI24: 0 | DJ24: 0 | DK24: 0 | DL24: 0 | DM24: 0 | DN24: 0 | DO24: 0 | DP24: 0 | DQ24: 0 | DR24: 0 | DS24: 0 | DT24: 0 | DU24: 0
B25: от возврата предоставленных займов, от продажи долговых ценных бумаг (прав требования денежных средств к другим лицам) | C25: 4213 | D25: руб. | E25: =SUM(F25:AO25) -> 0 | F25: 0 | G25: 0 | H25: 0 | I25: 0 | J25: 0 | K25: 0 | L25: 0 | M25: 0 | N25: 0 | O25: 0 | P25: 0 | Q25: 0 | R25: 0 | S25: 0 | T25: 0 | U25: 0 | V25: 0 | W25: 0 | X25: 0 | Y25: 0 | Z25: 0 | AA25: 0 | AB25: 0 | AC25: 0 | AD25: 0 | AE25: 0 | AF25: 0 | AG25: 0 | AH25: 0 | AI25: 0 | AJ25: 0 | AK25: 0 | AL25: 0 | AM25: 0 | AN25: 0 | AO25: 0 | AP25: 0 | AQ25: 0 | AR25: 0 | AS25: 0 | AT25: 0 | AU25: 0 | AV25: 0 | AW25: 0 | AX25: 0 | AY25: 0 | AZ25: 0 | BA25: 0 | BB25: 0 | BC25: 0 | BD25: 0 | BE25: 0 | BF25: 0 | BG25: 0 | BH25: 0 | BI25: 0 | BJ25: 0 | BK25: 0 | BL25: 0 | BM25: 0 | BN25: 0 | BO25: 0 | BP25: 0 | BQ25: 0 | BR25: 0 | BS25: 0 | BT25: 0 | BU25: 0 | BV25: 0 | BW25: 0 | BX25: 0 | BY25: 0 | BZ25: 0 | CA25: 0 | CB25: 0 | CC25: 0 | CD25: 0 | CE25: 0 | CF25: 0 | CG25: 0 | CH25: 0 | CI25: 0 | CJ25: 0 | CK25: 0 | CL25: 0 | CM25: 0 | CN25: 0 | CO25: 0 | CP25: 0 | CQ25: 0 | CR25: 0 | CS25: 0 | CT25: 0 | CU25: 0 | CV25: 0 | CW25: 0 | CX25: 0 | CY25: 0 | CZ25: 0 | DA25: 0 | DB25: 0 | DC25: 0 | DD25: 0 | DE25: 0 | DF25: 0 | DG25: 0 | DH25: 0 | DI25: 0 | DJ25: 0 | DK25: 0 | DL25: 0 | DM25: 0 | DN25: 0 | DO25: 0 | DP25: 0 | DQ25: 0 | DR25: 0 | DS25: 0 | DT25: 0 | DU25: 0
B26: дивидендов, процентов по долговым финансовым вложениям и аналогичных поступлений от долевого участия в других организациях | C26: 4214 | D26: руб. | E26: =SUM(F26:AO26) -> 0 | F26: 0 | G26: 0 | H26: 0 | I26: 0 | J26: 0 | K26: 0 | L26: 0 | M26: 0 | N26: 0 | O26: 0 | P26: 0 | Q26: 0 | R26: 0 | S26: 0 | T26: 0 | U26: 0 | V26: 0 | W26: 0 | X26: 0 | Y26: 0 | Z26: 0 | AA26: 0 | AB26: 0 | AC26: 0 | AD26: 0 | AE26: 0 | AF26: 0 | AG26: 0 | AH26: 0 | AI26: 0 | AJ26: 0 | AK26: 0 | AL26: 0 | AM26: 0 | AN26: 0 | AO26: 0 | AP26: 0 | AQ26: 0 | AR26: 0 | AS26: 0 | AT26: 0 | AU26: 0 | AV26: 0 | AW26: 0 | AX26: 0 | AY26: 0 | AZ26: 0 | BA26: 0 | BB26: 0 | BC26: 0 | BD26: 0 | BE26: 0 | BF26: 0 | BG26: 0 | BH26: 0 | BI26: 0 | BJ26: 0 | BK26: 0 | BL26: 0 | BM26: 0 | BN26: 0 | BO26: 0 | BP26: 0 | BQ26: 0 | BR26: 0 | BS26: 0 | BT26: 0 | BU26: 0 | BV26: 0 | BW26: 0 | BX26: 0 | BY26: 0 | BZ26: 0 | CA26: 0 | CB26: 0 | CC26: 0 | CD26: 0 | CE26: 0 | CF26: 0 | CG26: 0 | CH26: 0 | CI26: 0 | CJ26: 0 | CK26: 0 | CL26: 0 | CM26: 0 | CN26: 0 | CO26: 0 | CP26: 0 | CQ26: 0 | CR26: 0 | CS26: 0 | CT26: 0 | CU26: 0 | CV26: 0 | CW26: 0 | CX26: 0 | CY26: 0 | CZ26: 0 | DA26: 0 | DB26: 0 | DC26: 0 | DD26: 0 | DE26: 0 | DF26: 0 | DG26: 0 | DH26: 0 | DI26: 0 | DJ26: 0 | DK26: 0 | DL26: 0 | DM26: 0 | DN26: 0 | DO26: 0 | DP26: 0 | DQ26: 0 | DR26: 0 | DS26: 0 | DT26: 0 | DU26: 0
B27: прочие поступления | C27: 4219 | D27: руб. | E27: =SUM(F27:AO27) -> 0 | F27: 0 | G27: 0 | H27: 0 | I27: 0 | J27: 0 | K27: 0 | L27: 0 | M27: 0 | N27: 0 | O27: 0 | P27: 0 | Q27: 0 | R27: 0 | S27: 0 | T27: 0 | U27: 0 | V27: 0 | W27: 0 | X27: 0 | Y27: 0 | Z27: 0 | AA27: 0 | AB27: 0 | AC27: 0 | AD27: 0 | AE27: 0 | AF27: 0 | AG27: 0 | AH27: 0 | AI27: 0 | AJ27: 0 | AK27: 0 | AL27: 0 | AM27: 0 | AN27: 0 | AO27: 0 | AP27: 0 | AQ27: 0 | AR27: 0 | AS27: 0 | AT27: 0 | AU27: 0 | AV27: 0 | AW27: 0 | AX27: 0 | AY27: 0 | AZ27: 0 | BA27: 0 | BB27: 0 | BC27: 0 | BD27: 0 | BE27: 0 | BF27: 0 | BG27: 0 | BH27: 0 | BI27: 0 | BJ27: 0 | BK27: 0 | BL27: 0 | BM27: 0 | BN27: 0 | BO27: 0 | BP27: 0 | BQ27: 0 | BR27: 0 | BS27: 0 | BT27: 0 | BU27: 0 | BV27: 0 | BW27: 0 | BX27: 0 | BY27: 0 | BZ27: 0 | CA27: 0 | CB27: 0 | CC27: 0 | CD27: 0 | CE27: 0 | CF27: 0 | CG27: 0 | CH27: 0 | CI27: 0 | CJ27: 0 | CK27: 0 | CL27: 0 | CM27: 0 | CN27: 0 | CO27: 0 | CP27: 0 | CQ27: 0 | CR27: 0 | CS27: 0 | CT27: 0 | CU27: 0 | CV27: 0 | CW27: 0 | CX27: 0 | CY27: 0 | CZ27: 0 | DA27: 0 | DB27: 0 | DC27: 0 | DD27: 0 | DE27: 0 | DF27: 0 | DG27: 0 | DH27: 0 | DI27: 0 | DJ27: 0 | DK27: 0 | DL27: 0 | DM27: 0 | DN27: 0 | DO27: 0 | DP27: 0 | DQ27: 0 | DR27: 0 | DS27: 0 | DT27: 0 | DU27: 0
B28: Платежи - всего | C28: 4220 | D28: руб. | E28: =SUM(F28:DU28) -> 0 | F28: =F30+F31+F32+F33+F34 -> 0 | G28: =G30+G31+G32+G33+G34 -> 0 | H28: =H30+H31+H32+H33+H34 -> 0 | I28: =I30+I31+I32+I33+I34 -> 0 | J28: =J30+J31+J32+J33+J34 -> 0 | K28: =K30+K31+K32+K33+K34 -> 0 | L28: =L30+L31+L32+L33+L34 -> 0 | M28: =M30+M31+M32+M33+M34 -> 0 | ... DU28: =DU30+DU31+DU32+DU33+DU34 -> 0
B29: в том числе:
B30: в связи с приобретением, созданием, модернизацией, реконструкцией и подготовкой к использованию внеоборотных активов | C30: 4221 | D30: руб. | E30: =SUM(F30:AO30) -> 0 | F30: 0 | G30: 0 | H30: 0 | I30: 0 | J30: 0 | K30: 0 | L30: 0 | M30: 0 | N30: 0 | O30: 0 | P30: 0 | Q30: 0 | R30: 0 | S30: 0 | T30: 0 | U30: 0 | V30: 0 | W30: 0 | X30: 0 | Y30: 0 | Z30: 0 | AA30: 0 | AB30: 0 | AC30: 0 | AD30: 0 | AE30: 0 | AF30: 0 | AG30: 0 | AH30: 0 | AI30: 0 | AJ30: 0 | AK30: 0 | AL30: 0 | AM30: 0 | AN30: 0 | AO30: 0 | AP30: 0 | AQ30: 0 | AR30: 0 | AS30: 0 | AT30: 0 | AU30: 0 | AV30: 0 | AW30: 0 | AX30: 0 | AY30: 0 | AZ30: 0 | BA30: 0 | BB30: 0 | BC30: 0 | BD30: 0 | BE30: 0 | BF30: 0 | BG30: 0 | BH30: 0 | BI30: 0 | BJ30: 0 | BK30: 0 | BL30: 0 | BM30: 0 | BN30: 0 | BO30: 0 | BP30: 0 | BQ30: 0 | BR30: 0 | BS30: 0 | BT30: 0 | BU30: 0 | BV30: 0 | BW30: 0 | BX30: 0 | BY30: 0 | BZ30: 0 | CA30: 0 | CB30: 0 | CC30: 0 | CD30: 0 | CE30: 0 | CF30: 0 | CG30: 0 | CH30: 0 | CI30: 0 | CJ30: 0 | CK30: 0 | CL30: 0 | CM30: 0 | CN30: 0 | CO30: 0 | CP30: 0 | CQ30: 0 | CR30: 0 | CS30: 0 | CT30: 0 | CU30: 0 | CV30: 0 | CW30: 0 | CX30: 0 | CY30: 0 | CZ30: 0 | DA30: 0 | DB30: 0 | DC30: 0 | DD30: 0 | DE30: 0 | DF30: 0 | DG30: 0 | DH30: 0 | DI30: 0 | DJ30: 0 | DK30: 0 | DL30: 0 | DM30: 0 | DN30: 0 | DO30: 0 | DP30: 0 | DQ30: 0 | DR30: 0 | DS30: 0 | DT30: 0 | DU30: 0
B31: в связи с приобретением акций других организаций (долей участия) | C31: 4222 | D31: руб. | E31: =SUM(F31:AO31) -> 0 | F31: 0 | G31: 0 | H31: 0 | I31: 0 | J31: 0 | K31: 0 | L31: 0 | M31: 0 | N31: 0 | O31: 0 | P31: 0 | Q31: 0 | R31: 0 | S31: 0 | T31: 0 | U31: 0 | V31: 0 | W31: 0 | X31: 0 | Y31: 0 | Z31: 0 | AA31: 0 | AB31: 0 | AC31: 0 | AD31: 0 | AE31: 0 | AF31: 0 | AG31: 0 | AH31: 0 | AI31: 0 | AJ31: 0 | AK31: 0 | AL31: 0 | AM31: 0 | AN31: 0 | AO31: 0 | AP31: 0 | AQ31: 0 | AR31: 0 | AS31: 0 | AT31: 0 | AU31: 0 | AV31: 0 | AW31: 0 | AX31: 0 | AY31: 0 | AZ31: 0 | BA31: 0 | BB31: 0 | BC31: 0 | BD31: 0 | BE31: 0 | BF31: 0 | BG31: 0 | BH31: 0 | BI31: 0 | BJ31: 0 | BK31: 0 | BL31: 0 | BM31: 0 | BN31: 0 | BO31: 0 | BP31: 0 | BQ31: 0 | BR31: 0 | BS31: 0 | BT31: 0 | BU31: 0 | BV31: 0 | BW31: 0 | BX31: 0 | BY31: 0 | BZ31: 0 | CA31: 0 | CB31: 0 | CC31: 0 | CD31: 0 | CE31: 0 | CF31: 0 | CG31: 0 | CH31: 0 | CI31: 0 | CJ31: 0 | CK31: 0 | CL31: 0 | CM31: 0 | CN31: 0 | CO31: 0 | CP31: 0 | CQ31: 0 | CR31: 0 | CS31: 0 | CT31: 0 | CU31: 0 | CV31: 0 | CW31: 0 | CX31: 0 | CY31: 0 | CZ31: 0 | DA31: 0 | DB31: 0 | DC31: 0 | DD31: 0 | DE31: 0 | DF31: 0 | DG31: 0 | DH31: 0 | DI31: 0 | DJ31: 0 | DK31: 0 | DL31: 0 | DM31: 0 | DN31: 0 | DO31: 0 | DP31: 0 | DQ31: 0 | DR31: 0 | DS31: 0 | DT31: 0 | DU31: 0
B32: в связи с приобретением долговых ценных бумаг (прав требования денежных средств к другим лицам), предоставление займов другим лицам | C32: 4223 | D32: руб. | E32: =SUM(F32:AO32) -> 0 | F32: 0 | G32: 0 | H32: 0 | I32: 0 | J32: 0 | K32: 0 | L32: 0 | M32: 0 | N32: 0 | O32: 0 | P32: 0 | Q32: 0 | R32: 0 | S32: 0 | T32: 0 | U32: 0 | V32: 0 | W32: 0 | X32: 0 | Y32: 0 | Z32: 0 | AA32: 0 | AB32: 0 | AC32: 0 | AD32: 0 | AE32: 0 | AF32: 0 | AG32: 0 | AH32: 0 | AI32: 0 | AJ32: 0 | AK32: 0 | AL32: 0 | AM32: 0 | AN32: 0 | AO32: 0 | AP32: 0 | AQ32: 0 | AR32: 0 | AS32: 0 | AT32: 0 | AU32: 0 | AV32: 0 | AW32: 0 | AX32: 0 | AY32: 0 | AZ32: 0 | BA32: 0 | BB32: 0 | BC32: 0 | BD32: 0 | BE32: 0 | BF32: 0 | BG32: 0 | BH32: 0 | BI32: 0 | BJ32: 0 | BK32: 0 | BL32: 0 | BM32: 0 | BN32: 0 | BO32: 0 | BP32: 0 | BQ32: 0 | BR32: 0 | BS32: 0 | BT32: 0 | BU32: 0 | BV32: 0 | BW32: 0 | BX32: 0 | BY32: 0 | BZ32: 0 | CA32: 0 | CB32: 0 | CC32: 0 | CD32: 0 | CE32: 0 | CF32: 0 | CG32: 0 | CH32: 0 | CI32: 0 | CJ32: 0 | CK32: 0 | CL32: 0 | CM32: 0 | CN32: 0 | CO32: 0 | CP32: 0 | CQ32: 0 | CR32: 0 | CS32: 0 | CT32: 0 | CU32: 0 | CV32: 0 | CW32: 0 | CX32: 0 | CY32: 0 | CZ32: 0 | DA32: 0 | DB32: 0 | DC32: 0 | DD32: 0 | DE32: 0 | DF32: 0 | DG32: 0 | DH32: 0 | DI32: 0 | DJ32: 0 | DK32: 0 | DL32: 0 | DM32: 0 | DN32: 0 | DO32: 0 | DP32: 0 | DQ32: 0 | DR32: 0 | DS32: 0 | DT32: 0 | DU32: 0
B33: процентов по долговым обязательствам, включаемым в стоимость инвестиционного актива | C33: 4224 | D33: руб. | E33: =SUM(F33:AO33) -> 0 | F33: 0 | G33: 0 | H33: 0 | I33: 0 | J33: 0 | K33: 0 | L33: 0 | M33: 0 | N33: 0 | O33: 0 | P33: 0 | Q33: 0 | R33: 0 | S33: 0 | T33: 0 | U33: 0 | V33: 0 | W33: 0 | X33: 0 | Y33: 0 | Z33: 0 | AA33: 0 | AB33: 0 | AC33: 0 | AD33: 0 | AE33: 0 | AF33: 0 | AG33: 0 | AH33: 0 | AI33: 0 | AJ33: 0 | AK33: 0 | AL33: 0 | AM33: 0 | AN33: 0 | AO33: 0 | AP33: 0 | AQ33: 0 | AR33: 0 | AS33: 0 | AT33: 0 | AU33: 0 | AV33: 0 | AW33: 0 | AX33: 0 | AY33: 0 | AZ33: 0 | BA33: 0 | BB33: 0 | BC33: 0 | BD33: 0 | BE33: 0 | BF33: 0 | BG33: 0 | BH33: 0 | BI33: 0 | BJ33: 0 | BK33: 0 | BL33: 0 | BM33: 0 | BN33: 0 | BO33: 0 | BP33: 0 | BQ33: 0 | BR33: 0 | BS33: 0 | BT33: 0 | BU33: 0 | BV33: 0 | BW33: 0 | BX33: 0 | BY33: 0 | BZ33: 0 | CA33: 0 | CB33: 0 | CC33: 0 | CD33: 0 | CE33: 0 | CF33: 0 | CG33: 0 | CH33: 0 | CI33: 0 | CJ33: 0 | CK33: 0 | CL33: 0 | CM33: 0 | CN33: 0 | CO33: 0 | CP33: 0 | CQ33: 0 | CR33: 0 | CS33: 0 | CT33: 0 | CU33: 0 | CV33: 0 | CW33: 0 | CX33: 0 | CY33: 0 | CZ33: 0 | DA33: 0 | DB33: 0 | DC33: 0 | DD33: 0 | DE33: 0 | DF33: 0 | DG33: 0 | DH33: 0 | DI33: 0 | DJ33: 0 | DK33: 0 | DL33: 0 | DM33: 0 | DN33: 0 | DO33: 0 | DP33: 0 | DQ33: 0 | DR33: 0 | DS33: 0 | DT33: 0 | DU33: 0
B34: прочие платежи | C34: 4229 | D34: руб. | E34: =SUM(F34:AO34) -> 0 | F34: 0 | G34: 0 | H34: 0 | I34: 0 | J34: 0 | K34: 0 | L34: 0 | M34: 0 | N34: 0 | O34: 0 | P34: 0 | Q34: 0 | R34: 0 | S34: 0 | T34: 0 | U34: 0 | V34: 0 | W34: 0 | X34: 0 | Y34: 0 | Z34: 0 | AA34: 0 | AB34: 0 | AC34: 0 | AD34: 0 | AE34: 0 | AF34: 0 | AG34: 0 | AH34: 0 | AI34: 0 | AJ34: 0 | AK34: 0 | AL34: 0 | AM34: 0 | AN34: 0 | AO34: 0 | AP34: 0 | AQ34: 0 | AR34: 0 | AS34: 0 | AT34: 0 | AU34: 0 | AV34: 0 | AW34: 0 | AX34: 0 | AY34: 0 | AZ34: 0 | BA34: 0 | BB34: 0 | BC34: 0 | BD34: 0 | BE34: 0 | BF34: 0 | BG34: 0 | BH34: 0 | BI34: 0 | BJ34: 0 | BK34: 0 | BL34: 0 | BM34: 0 | BN34: 0 | BO34: 0 | BP34: 0 | BQ34: 0 | BR34: 0 | BS34: 0 | BT34: 0 | BU34: 0 | BV34: 0 | BW34: 0 | BX34: 0 | BY34: 0 | BZ34: 0 | CA34: 0 | CB34: 0 | CC34: 0 | CD34: 0 | CE34: 0 | CF34: 0 | CG34: 0 | CH34: 0 | CI34: 0 | CJ34: 0 | CK34: 0 | CL34: 0 | CM34: 0 | CN34: 0 | CO34: 0 | CP34: 0 | CQ34: 0 | CR34: 0 | CS34: 0 | CT34: 0 | CU34: 0 | CV34: 0 | CW34: 0 | CX34: 0 | CY34: 0 | CZ34: 0 | DA34: 0 | DB34: 0 | DC34: 0 | DD34: 0 | DE34: 0 | DF34: 0 | DG34: 0 | DH34: 0 | DI34: 0 | DJ34: 0 | DK34: 0 | DL34: 0 | DM34: 0 | DN34: 0 | DO34: 0 | DP34: 0 | DQ34: 0 | DR34: 0 | DS34: 0 | DT34: 0 | DU34: 0
B35: Сальдо денежных потоков от инвестиционных операций | C35: 4200 | D35: руб. | E35: =SUM(F35:DU35) -> 0 | F35: =F21-F28 -> 0 | G35: =G21-G28 -> 0 | H35: =H21-H28 -> 0 | I35: =I21-I28 -> 0 | J35: =J21-J28 -> 0 | K35: =K21-K28 -> 0 | L35: =L21-L28 -> 0 | M35: =M21-M28 -> 0 | ... DU35: =DU21-DU28 -> 0
B36: Денежные потоки от финансовых операций
B37: Поступления - всего | C37: 4310 | D37: руб. | E37: =SUM(F37:DY37) -> 0 | F37: =F39+F40+F41+F42+F43 -> 0 | G37: =G39+G40+G41+G42+G43 -> 0 | H37: =H39+H40+H41+H42+H43 -> 0 | I37: =I39+I40+I41+I42+I43 -> 0 | J37: =J39+J40+J41+J42+J43 -> 0 | K37: =K39+K40+K41+K42+K43 -> 0 | L37: =L39+L40+L41+L42+L43 -> 0 | M37: =M39+M40+M41+M42+M43 -> 0 | ... DU37: =DU39+DU40+DU41+DU42+DU43 -> 0
B38: в том числе:
B39: получение кредитов и займов | C39: 4311 | D39: руб. | E39: =SUM(F39:AO39) -> 0 | F39: 0 | G39: 0 | H39: 0 | I39: 0 | J39: ='Исходные данные'!J36 -> 0 | K39: ='Исходные данные'!K36 -> 0 | L39: ='Исходные данные'!L36 -> 0 | M39: ='Исходные данные'!M36 -> 0 | N39: ='Исходные данные'!N36 -> 0 | O39: ='Исходные данные'!O36 -> 0 | P39: ='Исходные данные'!P36 -> 0 | Q39: ='Исходные данные'!Q36 -> 0 | ... AO39: ='Исходные данные'!AO36 -> 0 | AP39: 0 | AQ39: 0 | AR39: 0 | AS39: 0 | AT39: ='Исходные данные'!AT36 -> 0 | AU39: ='Исходные данные'!AU36 -> 0 | AV39: ='Исходные данные'!AV36 -> 0 | AW39: ='Исходные данные'!AW36 -> 0 | AX39: ='Исходные данные'!AX36 -> 0 | AY39: ='Исходные данные'!AY36 -> 0 | AZ39: ='Исходные данные'!AZ36 -> 0 | BA39: ='Исходные данные'!BA36 -> 0 | ... BY39: ='Исходные данные'!BY36 -> 0 | BZ39: 0 | CA39: 0 | CB39: 0 | CC39: 0 | CD39: ='Исходные данные'!CD36 -> 0 | CE39: ='Исходные данные'!CE36 -> 0 | CF39: ='Исходные данные'!CF36 -> 0 | CG39: ='Исходные данные'!CG36 -> 0 | CH39: ='Исходные данные'!CH36 -> 0 | CI39: ='Исходные данные'!CI36 -> 0 | CJ39: ='Исходные данные'!CJ36 -> 0 | CK39: ='Исходные данные'!CK36 -> 0 | ... DI39: ='Исходные данные'!DI36 -> 0 | DJ39: 0 | DK39: 0 | DL39: 0 | DM39: 0 | DN39: ='Исходные данные'!DN36 -> 0 | DO39: ='Исходные данные'!DO36 -> 0 | DP39: ='Исходные данные'!DP36 -> 0 | DQ39: ='Исходные данные'!DQ36 -> 0 | DR39: ='Исходные данные'!DR36 -> 0 | DS39: ='Исходные данные'!DS36 -> 0 | DT39: ='Исходные данные'!DT36 -> 0 | DU39: ='Исходные данные'!DU36 -> 0
B40: денежных вкладов собственников (участников) | C40: 4312 | D40: руб. | E40: =SUM(F40:DY40) -> 0 | F40: 0 | G40: 0 | H40: 0 | I40: 0 | J40: 0 | K40: 0 | L40: 0 | M40: 0 | N40: 0 | O40: 0 | P40: 0 | Q40: 0 | R40: 0 | S40: 0 | T40: 0 | U40: 0 | V40: 0 | W40: 0 | X40: 0 | Y40: 0 | Z40: 0 | AA40: 0 | AB40: 0 | AC40: 0 | AD40: 0 | AE40: 0 | AF40: 0 | AG40: 0 | AH40: 0 | AI40: 0 | AJ40: 0 | AK40: 0 | AL40: 0 | AM40: 0 | AN40: 0 | AO40: 0 | AP40: 0 | AQ40: 0 | AR40: 0 | AS40: 0 | AT40: 0 | AU40: 0 | AV40: 0 | AW40: 0 | AX40: 0 | AY40: 0 | AZ40: 0 | BA40: 0 | BB40: 0 | BC40: 0 | BD40: 0 | BE40: 0 | BF40: 0 | BG40: 0 | BH40: 0 | BI40: 0 | BJ40: 0 | BK40: 0 | BL40: 0 | BM40: 0 | BN40: 0 | BO40: 0 | BP40: 0 | BQ40: 0 | BR40: 0 | BS40: 0 | BT40: 0 | BU40: 0 | BV40: 0 | BW40: 0 | BX40: 0 | BY40: 0 | BZ40: 0 | CA40: 0 | CB40: 0 | CC40: 0 | CD40: 0 | CE40: 0 | CF40: 0 | CG40: 0 | CH40: 0 | CI40: 0 | CJ40: 0 | CK40: 0 | CL40: 0 | CM40: 0 | CN40: 0 | CO40: 0 | CP40: 0 | CQ40: 0 | CR40: 0 | CS40: 0 | CT40: 0 | CU40: 0 | CV40: 0 | CW40: 0 | CX40: 0 | CY40: 0 | CZ40: 0 | DA40: 0 | DB40: 0 | DC40: 0 | DD40: 0 | DE40: 0 | DF40: 0 | DG40: 0 | DH40: 0 | DI40: 0 | DJ40: 0 | DK40: 0 | DL40: 0 | DM40: 0 | DN40: 0 | DO40: 0 | DP40: 0 | DQ40: 0 | DR40: 0 | DS40: 0 | DT40: 0 | DU40: 0
B41: от выпуска акций, увеличения долей участия | C41: 4313 | D41: руб. | E41: =SUM(F41:AO41) -> 0 | F41: 0 | G41: 0 | H41: 0 | I41: 0 | J41: 0 | K41: 0 | L41: 0 | M41: 0 | N41: 0 | O41: 0 | P41: 0 | Q41: 0 | R41: 0 | S41: 0 | T41: 0 | U41: 0 | V41: 0 | W41: 0 | X41: 0 | Y41: 0 | Z41: 0 | AA41: 0 | AB41: 0 | AC41: 0 | AD41: 0 | AE41: 0 | AF41: 0 | AG41: 0 | AH41: 0 | AI41: 0 | AJ41: 0 | AK41: 0 | AL41: 0 | AM41: 0 | AN41: 0 | AO41: 0 | AP41: 0 | AQ41: 0 | AR41: 0 | AS41: 0 | AT41: 0 | AU41: 0 | AV41: 0 | AW41: 0 | AX41: 0 | AY41: 0 | AZ41: 0 | BA41: 0 | BB41: 0 | BC41: 0 | BD41: 0 | BE41: 0 | BF41: 0 | BG41: 0 | BH41: 0 | BI41: 0 | BJ41: 0 | BK41: 0 | BL41: 0 | BM41: 0 | BN41: 0 | BO41: 0 | BP41: 0 | BQ41: 0 | BR41: 0 | BS41: 0 | BT41: 0 | BU41: 0 | BV41: 0 | BW41: 0 | BX41: 0 | BY41: 0 | BZ41: 0 | CA41: 0 | CB41: 0 | CC41: 0 | CD41: 0 | CE41: 0 | CF41: 0 | CG41: 0 | CH41: 0 | CI41: 0 | CJ41: 0 | CK41: 0 | CL41: 0 | CM41: 0 | CN41: 0 | CO41: 0 | CP41: 0 | CQ41: 0 | CR41: 0 | CS41: 0 | CT41: 0 | CU41: 0 | CV41: 0 | CW41: 0 | CX41: 0 | CY41: 0 | CZ41: 0 | DA41: 0 | DB41: 0 | DC41: 0 | DD41: 0 | DE41: 0 | DF41: 0 | DG41: 0 | DH41: 0 | DI41: 0 | DJ41: 0 | DK41: 0 | DL41: 0 | DM41: 0 | DN41: 0 | DO41: 0 | DP41: 0 | DQ41: 0 | DR41: 0 | DS41: 0 | DT41: 0 | DU41: 0
B42: от выпуска облигаций, векселей и других долговых ценных бумаг и др. | C42: 4314 | D42: руб. | E42: =SUM(F42:AO42) -> 0 | F42: 0 | G42: 0 | H42: 0 | I42: 0 | J42: 0 | K42: 0 | L42: 0 | M42: 0 | N42: 0 | O42: 0 | P42: 0 | Q42: 0 | R42: 0 | S42: 0 | T42: 0 | U42: 0 | V42: 0 | W42: 0 | X42: 0 | Y42: 0 | Z42: 0 | AA42: 0 | AB42: 0 | AC42: 0 | AD42: 0 | AE42: 0 | AF42: 0 | AG42: 0 | AH42: 0 | AI42: 0 | AJ42: 0 | AK42: 0 | AL42: 0 | AM42: 0 | AN42: 0 | AO42: 0 | AP42: 0 | AQ42: 0 | AR42: 0 | AS42: 0 | AT42: 0 | AU42: 0 | AV42: 0 | AW42: 0 | AX42: 0 | AY42: 0 | AZ42: 0 | BA42: 0 | BB42: 0 | BC42: 0 | BD42: 0 | BE42: 0 | BF42: 0 | BG42: 0 | BH42: 0 | BI42: 0 | BJ42: 0 | BK42: 0 | BL42: 0 | BM42: 0 | BN42: 0 | BO42: 0 | BP42: 0 | BQ42: 0 | BR42: 0 | BS42: 0 | BT42: 0 | BU42: 0 | BV42: 0 | BW42: 0 | BX42: 0 | BY42: 0 | BZ42: 0 | CA42: 0 | CB42: 0 | CC42: 0 | CD42: 0 | CE42: 0 | CF42: 0 | CG42: 0 | CH42: 0 | CI42: 0 | CJ42: 0 | CK42: 0 | CL42: 0 | CM42: 0 | CN42: 0 | CO42: 0 | CP42: 0 | CQ42: 0 | CR42: 0 | CS42: 0 | CT42: 0 | CU42: 0 | CV42: 0 | CW42: 0 | CX42: 0 | CY42: 0 | CZ42: 0 | DA42: 0 | DB42: 0 | DC42: 0 | DD42: 0 | DE42: 0 | DF42: 0 | DG42: 0 | DH42: 0 | DI42: 0 | DJ42: 0 | DK42: 0 | DL42: 0 | DM42: 0 | DN42: 0 | DO42: 0 | DP42: 0 | DQ42: 0 | DR42: 0 | DS42: 0 | DT42: 0 | DU42: 0
B43: прочие поступления | C43: 4319 | D43: руб. | E43: =SUM(F43:AO43) -> 0 | F43: 0 | G43: 0 | H43: 0 | I43: 0 | J43: 0 | K43: 0 | L43: 0 | M43: 0 | N43: 0 | O43: 0 | P43: 0 | Q43: 0 | R43: 0 | S43: 0 | T43: 0 | U43: 0 | V43: 0 | W43: 0 | X43: 0 | Y43: 0 | Z43: 0 | AA43: 0 | AB43: 0 | AC43: 0 | AD43: 0 | AE43: 0 | AF43: 0 | AG43: 0 | AH43: 0 | AI43: 0 | AJ43: 0 | AK43: 0 | AL43: 0 | AM43: 0 | AN43: 0 | AO43: 0 | AP43: 0 | AQ43: 0 | AR43: 0 | AS43: 0 | AT43: 0 | AU43: 0 | AV43: 0 | AW43: 0 | AX43: 0 | AY43: 0 | AZ43: 0 | BA43: 0 | BB43: 0 | BC43: 0 | BD43: 0 | BE43: 0 | BF43: 0 | BG43: 0 | BH43: 0 | BI43: 0 | BJ43: 0 | BK43: 0 | BL43: 0 | BM43: 0 | BN43: 0 | BO43: 0 | BP43: 0 | BQ43: 0 | BR43: 0 | BS43: 0 | BT43: 0 | BU43: 0 | BV43: 0 | BW43: 0 | BX43: 0 | BY43: 0 | BZ43: 0 | CA43: 0 | CB43: 0 | CC43: 0 | CD43: 0 | CE43: 0 | CF43: 0 | CG43: 0 | CH43: 0 | CI43: 0 | CJ43: 0 | CK43: 0 | CL43: 0 | CM43: 0 | CN43: 0 | CO43: 0 | CP43: 0 | CQ43: 0 | CR43: 0 | CS43: 0 | CT43: 0 | CU43: 0 | CV43: 0 | CW43: 0 | CX43: 0 | CY43: 0 | CZ43: 0 | DA43: 0 | DB43: 0 | DC43: 0 | DD43: 0 | DE43: 0 | DF43: 0 | DG43: 0 | DH43: 0 | DI43: 0 | DJ43: 0 | DK43: 0 | DL43: 0 | DM43: 0 | DN43: 0 | DO43: 0 | DP43: 0 | DQ43: 0 | DR43: 0 | DS43: 0 | DT43: 0 | DU43: 0
B44: Платежи - всего | C44: 4320 | D44: руб. | E44: =SUM(F44:AO44) -> 0 | F44: =F46+F47+F48+F49 -> 0 | G44: =G46+G47+G48+G49 -> 0 | H44: =H46+H47+H48+H49 -> 0 | I44: =I46+I47+I48+I49 -> 0 | J44: =J46+J47+J48+J49 -> 0 | K44: =K46+K47+K48+K49 -> 0 | L44: =L46+L47+L48+L49 -> 0 | M44: =M46+M47+M48+M49 -> 0 | ... DU44: =DU46+DU47+DU48+DU49 -> 0
B45: в том числе:
B46: собственникам (участникам) в связи с выкупом у них акций (долей участия) организации или их выходом из состава участников | C46: 4321 | D46: руб. | E46: =SUM(F46:AO46) -> 0 | F46: 0 | G46: 0 | H46: 0 | I46: 0 | J46: 0 | K46: 0 | L46: 0 | M46: 0 | N46: 0 | O46: 0 | P46: 0 | Q46: 0 | R46: 0 | S46: 0 | T46: 0 | U46: 0 | V46: 0 | W46: 0 | X46: 0 | Y46: 0 | Z46: 0 | AA46: 0 | AB46: 0 | AC46: 0 | AD46: 0 | AE46: 0 | AF46: 0 | AG46: 0 | AH46: 0 | AI46: 0 | AJ46: 0 | AK46: 0 | AL46: 0 | AM46: 0 | AN46: 0 | AO46: 0 | AP46: 0 | AQ46: 0 | AR46: 0 | AS46: 0 | AT46: 0 | AU46: 0 | AV46: 0 | AW46: 0 | AX46: 0 | AY46: 0 | AZ46: 0 | BA46: 0 | BB46: 0 | BC46: 0 | BD46: 0 | BE46: 0 | BF46: 0 | BG46: 0 | BH46: 0 | BI46: 0 | BJ46: 0 | BK46: 0 | BL46: 0 | BM46: 0 | BN46: 0 | BO46: 0 | BP46: 0 | BQ46: 0 | BR46: 0 | BS46: 0 | BT46: 0 | BU46: 0 | BV46: 0 | BW46: 0 | BX46: 0 | BY46: 0 | BZ46: 0 | CA46: 0 | CB46: 0 | CC46: 0 | CD46: 0 | CE46: 0 | CF46: 0 | CG46: 0 | CH46: 0 | CI46: 0 | CJ46: 0 | CK46: 0 | CL46: 0 | CM46: 0 | CN46: 0 | CO46: 0 | CP46: 0 | CQ46: 0 | CR46: 0 | CS46: 0 | CT46: 0 | CU46: 0 | CV46: 0 | CW46: 0 | CX46: 0 | CY46: 0 | CZ46: 0 | DA46: 0 | DB46: 0 | DC46: 0 | DD46: 0 | DE46: 0 | DF46: 0 | DG46: 0 | DH46: 0 | DI46: 0 | DJ46: 0 | DK46: 0 | DL46: 0 | DM46: 0 | DN46: 0 | DO46: 0 | DP46: 0 | DQ46: 0 | DR46: 0 | DS46: 0 | DT46: 0 | DU46: 0
